Workbook
Name Instrument: INDEX(#REF!,#REF!):INDEX(#REF!,#REF!)
Name Instrument: INDEX(#REF!,#REF!):INDEX(#REF!,#REF!)
Name Instrument2: INDEX(#REF!,#REF!):INDEX(#REF!,#REF!)
Name Instrument2: INDEX(#REF!,#REF!):INDEX(#REF!,#REF!)
Name Sektioner: INDEX(#REF!,#REF!):INDEX(#REF!,#REF!)
Name Sektioner: INDEX(#REF!,#REF!):INDEX(#REF!,#REF!)
Name takstblad: [1]Takstblad!$A$2:$R$249
Name takstblad: [1]Takstblad!$A$2:$R$249
Name takstblad: Takstblad!$A$2:$T$276
Name TAP: Takstblad!$A$34:$A$54
Name Text2: 'Cover letter'!#REF!
Name Text2: 'Cover letter ECE_MPE'!#REF!
Name Text3: 'Cover letter'!$A$14
Name Text3: 'Cover letter ECE_MPE'!$A$14
Name VIP: Takstblad!$A$5:$A$30

Sheet Takstblad
A1: Rate Catalog - incl. Salary and price increase | C1: Hvis der tastes en medarbejder inkl. Kostpris ind, så skriv PhD I kolonne B, idet den så medtages I forskningsadministrationsberegningen
C2: Monthly Salary | N2: Cost Price
A3: Kategori | C3: 2026 | D3: =+C3+1 -> 2027 | E3: =+D3+1 -> 2028 | F3: =+E3+1 -> 2029 | G3: =+F3+1 -> 2030 | H3: =+G3+1 -> 2031 | I3: =+H3+1 -> 2032 | J3: =+I3+1 -> 2033 | K3: =+J3+1 -> 2034 | L3: =+K3+1 -> 2035 | N3: =+C3 -> 2026 | O3: =+D3 -> 2027 | P3: =+E3 -> 2028 | Q3: =+F3 -> 2029 | R3: =+G3 -> 2030 | S3: =+H3 -> 2031 | T3: =+I3 -> 2032 | U3: =+J3 -> 2033 | ... W3: =+L3 -> 2035 | Y3: Løn stigning | Z3: 1.025
A4: VIP | C4: Column1 | Y4: Prisstigning | Z4: 1.02
A5: "Choose job position" | B5: =_xlfn.XLOOKUP(Tabel12[[#This Row],[VIP]],Tabel19[Job functions],Tabel19[Column1],"",0)&"" | Y5: Timer/md | Z5: =1460/12 -> 121.66667
A6: Institutleader/Head of Research | B6: =_xlfn.XLOOKUP(Tabel12[[#This Row],[VIP]],Tabel19[Job functions],Tabel19[Column1],"",0)&"" | C6: 114000 | D6: =ROUNDUP(+C6*$Z$3,-3) -> 117000 | E6: =ROUNDUP(+D6*$Z$3,-3) -> 120000 | F6: =ROUNDUP(+E6*$Z$3,-3) -> 123000 | G6: =ROUNDUP(+F6*$Z$3,-3) -> 127000 | H6: =ROUNDUP(+G6*$Z$3,-3) -> 131000 | I6: =ROUNDUP(+H6*$Z$3,-3) -> 135000 | J6: =ROUNDUP(+I6*$Z$3,-3) -> 139000 | K6: =ROUNDUP(+J6*$Z$3,-3) -> 143000 | L6: =ROUNDUP(+K6*$Z$3,-3) -> 147000 | N6: =+C6/$Z$5 -> 936.9863 | O6: =+D6/$Z$5 -> 961.64384 | P6: =+E6/$Z$5 -> 986.30137 | Q6: =+F6/$Z$5 -> 1010.9589 | R6: =+G6/$Z$5 -> 1043.8356 | S6: =+H6/$Z$5 -> 1076.7123 | T6: =+I6/$Z$5 -> 1109.589 | U6: =+J6/$Z$5 -> 1142.4658 | ... W6: =+L6/$Z$5 -> 1208.2192
A7: Professor - high rate | B7: =_xlfn.XLOOKUP(Tabel12[[#This Row],[VIP]],Tabel19[Job functions],Tabel19[Column1],"",0)&"" | C7: 90000 | D7: =ROUNDUP(+C7*$Z$3,-3) -> 93000 | E7: =ROUNDUP(+D7*$Z$3,-3) -> 96000 | F7: =ROUNDUP(+E7*$Z$3,-3) -> 99000 | G7: =ROUNDUP(+F7*$Z$3,-3) -> 102000 | H7: =ROUNDUP(+G7*$Z$3,-3) -> 105000 | I7: =ROUNDUP(+H7*$Z$3,-3) -> 108000 | J7: =ROUNDUP(+I7*$Z$3,-3) -> 111000 | K7: =ROUNDUP(+J7*$Z$3,-3) -> 114000 | L7: =ROUNDUP(+K7*$Z$3,-3) -> 117000 | N7: =+C7/$Z$5 -> 739.72603 | O7: =+D7/$Z$5 -> 764.38356 | P7: =+E7/$Z$5 -> 789.0411 | Q7: =+F7/$Z$5 -> 813.69863 | R7: =+G7/$Z$5 -> 838.35616 | S7: =+H7/$Z$5 -> 863.0137 | T7: =+I7/$Z$5 -> 887.67123 | U7: =+J7/$Z$5 -> 912.32877 | ... W7: =+L7/$Z$5 -> 961.64384
A8: Professor - avr. rate | B8: =_xlfn.XLOOKUP(Tabel12[[#This Row],[VIP]],Tabel19[Job functions],Tabel19[Column1],"",0)&"" | C8: 87000 | D8: =ROUNDUP(+C8*$Z$3,-3) -> 90000 | E8: =ROUNDUP(+D8*$Z$3,-3) -> 93000 | F8: =ROUNDUP(+E8*$Z$3,-3) -> 96000 | G8: =ROUNDUP(+F8*$Z$3,-3) -> 99000 | H8: =ROUNDUP(+G8*$Z$3,-3) -> 102000 | I8: =ROUNDUP(+H8*$Z$3,-3) -> 105000 | J8: =ROUNDUP(+I8*$Z$3,-3) -> 108000 | K8: =ROUNDUP(+J8*$Z$3,-3) -> 111000 | L8: =ROUNDUP(+K8*$Z$3,-3) -> 114000 | N8: =+C8/$Z$5 -> 715.06849 | O8: =+D8/$Z$5 -> 739.72603 | P8: =+E8/$Z$5 -> 764.38356 | Q8: =+F8/$Z$5 -> 789.0411 | R8: =+G8/$Z$5 -> 813.69863 | S8: =+H8/$Z$5 -> 838.35616 | T8: =+I8/$Z$5 -> 863.0137 | U8: =+J8/$Z$5 -> 887.67123 | ... W8: =+L8/$Z$5 -> 936.9863
A9: Research Director - high rate | B9: =_xlfn.XLOOKUP(Tabel12[[#This Row],[VIP]],Tabel19[Job functions],Tabel19[Column1],"",0)&"" | C9: 90000 | D9: =ROUNDUP(+C9*$Z$3,-3) -> 93000 | E9: =ROUNDUP(+D9*$Z$3,-3) -> 96000 | F9: =ROUNDUP(+E9*$Z$3,-3) -> 99000 | G9: =ROUNDUP(+F9*$Z$3,-3) -> 102000 | H9: =ROUNDUP(+G9*$Z$3,-3) -> 105000 | I9: =ROUNDUP(+H9*$Z$3,-3) -> 108000 | J9: =ROUNDUP(+I9*$Z$3,-3) -> 111000 | K9: =ROUNDUP(+J9*$Z$3,-3) -> 114000 | L9: =ROUNDUP(+K9*$Z$3,-3) -> 117000 | N9: =+C9/$Z$5 -> 739.72603 | O9: =+D9/$Z$5 -> 764.38356 | P9: =+E9/$Z$5 -> 789.0411 | Q9: =+F9/$Z$5 -> 813.69863 | R9: =+G9/$Z$5 -> 838.35616 | S9: =+H9/$Z$5 -> 863.0137 | T9: =+I9/$Z$5 -> 887.67123 | U9: =+J9/$Z$5 -> 912.32877 | ... W9: =+L9/$Z$5 -> 961.64384
A10: Research Director - avr. rate | B10: =_xlfn.XLOOKUP(Tabel12[[#This Row],[VIP]],Tabel19[Job functions],Tabel19[Column1],"",0)&"" | C10: 87000 | D10: =ROUNDUP(+C10*$Z$3,-3) -> 90000 | E10: =ROUNDUP(+D10*$Z$3,-3) -> 93000 | F10: =ROUNDUP(+E10*$Z$3,-3) -> 96000 | G10: =ROUNDUP(+F10*$Z$3,-3) -> 99000 | H10: =ROUNDUP(+G10*$Z$3,-3) -> 102000 | I10: =ROUNDUP(+H10*$Z$3,-3) -> 105000 | J10: =ROUNDUP(+I10*$Z$3,-3) -> 108000 | K10: =ROUNDUP(+J10*$Z$3,-3) -> 111000 | L10: =ROUNDUP(+K10*$Z$3,-3) -> 114000 | N10: =+C10/$Z$5 -> 715.06849 | O10: =+D10/$Z$5 -> 739.72603 | P10: =+E10/$Z$5 -> 764.38356 | Q10: =+F10/$Z$5 -> 789.0411 | R10: =+G10/$Z$5 -> 813.69863 | S10: =+H10/$Z$5 -> 838.35616 | T10: =+I10/$Z$5 -> 863.0137 | U10: =+J10/$Z$5 -> 887.67123 | ... W10: =+L10/$Z$5 -> 936.9863
A11: Associate Professor - high rate | B11: =_xlfn.XLOOKUP(Tabel12[[#This Row],[VIP]],Tabel19[Job functions],Tabel19[Column1],"",0)&"" | C11: 73000 | D11: =ROUNDUP(+C11*$Z$3,-3) -> 75000 | E11: =ROUNDUP(+D11*$Z$3,-3) -> 77000 | F11: =ROUNDUP(+E11*$Z$3,-3) -> 79000 | G11: =ROUNDUP(+F11*$Z$3,-3) -> 81000 | H11: =ROUNDUP(+G11*$Z$3,-3) -> 84000 | I11: =ROUNDUP(+H11*$Z$3,-3) -> 87000 | J11: =ROUNDUP(+I11*$Z$3,-3) -> 90000 | K11: =ROUNDUP(+J11*$Z$3,-3) -> 93000 | L11: =ROUNDUP(+K11*$Z$3,-3) -> 96000 | N11: =+C11/$Z$5 -> 600 | O11: =+D11/$Z$5 -> 616.43836 | P11: =+E11/$Z$5 -> 632.87671 | Q11: =+F11/$Z$5 -> 649.31507 | R11: =+G11/$Z$5 -> 665.75342 | S11: =+H11/$Z$5 -> 690.41096 | T11: =+I11/$Z$5 -> 715.06849 | U11: =+J11/$Z$5 -> 739.72603 | ... W11: =+L11/$Z$5 -> 789.0411
A12: Associate Professor - avr. rate | B12: =_xlfn.XLOOKUP(Tabel12[[#This Row],[VIP]],Tabel19[Job functions],Tabel19[Column1],"",0)&"" | C12: 70000 | D12: =ROUNDUP(+C12*$Z$3,-3) -> 72000 | E12: =ROUNDUP(+D12*$Z$3,-3) -> 74000 | F12: =ROUNDUP(+E12*$Z$3,-3) -> 76000 | G12: =ROUNDUP(+F12*$Z$3,-3) -> 78000 | H12: =ROUNDUP(+G12*$Z$3,-3) -> 80000 | I12: =ROUNDUP(+H12*$Z$3,-3) -> 82000 | J12: =ROUNDUP(+I12*$Z$3,-3) -> 85000 | K12: =ROUNDUP(+J12*$Z$3,-3) -> 88000 | L12: =ROUNDUP(+K12*$Z$3,-3) -> 91000 | N12: =+C12/$Z$5 -> 575.34247 | O12: =+D12/$Z$5 -> 591.78082 | P12: =+E12/$Z$5 -> 608.21918 | Q12: =+F12/$Z$5 -> 624.65753 | R12: =+G12/$Z$5 -> 641.09589 | S12: =+H12/$Z$5 -> 657.53425 | T12: =+I12/$Z$5 -> 673.9726 | U12: =+J12/$Z$5 -> 698.63014 | ... W12: =+L12/$Z$5 -> 747.94521
A13: Senior Researcher - high rate | B13: =_xlfn.XLOOKUP(Tabel12[[#This Row],[VIP]],Tabel19[Job functions],Tabel19[Column1],"",0)&"" | C13: 74000 | D13: =ROUNDUP(+C13*$Z$3,-3) -> 76000 | E13: =ROUNDUP(+D13*$Z$3,-3) -> 78000 | F13: =ROUNDUP(+E13*$Z$3,-3) -> 80000 | G13: =ROUNDUP(+F13*$Z$3,-3) -> 82000 | H13: =ROUNDUP(+G13*$Z$3,-3) -> 85000 | I13: =ROUNDUP(+H13*$Z$3,-3) -> 88000 | J13: =ROUNDUP(+I13*$Z$3,-3) -> 91000 | K13: =ROUNDUP(+J13*$Z$3,-3) -> 94000 | L13: =ROUNDUP(+K13*$Z$3,-3) -> 97000 | N13: =+C13/$Z$5 -> 608.21918 | O13: =+D13/$Z$5 -> 624.65753 | P13: =+E13/$Z$5 -> 641.09589 | Q13: =+F13/$Z$5 -> 657.53425 | R13: =+G13/$Z$5 -> 673.9726 | S13: =+H13/$Z$5 -> 698.63014 | T13: =+I13/$Z$5 -> 723.28767 | U13: =+J13/$Z$5 -> 747.94521 | ... W13: =+L13/$Z$5 -> 797.26027
A14: Senior Researcher - avr. rate | B14: =_xlfn.XLOOKUP(Tabel12[[#This Row],[VIP]],Tabel19[Job functions],Tabel19[Column1],"",0)&"" | C14: 71000 | D14: =ROUNDUP(+C14*$Z$3,-3) -> 73000 | E14: =ROUNDUP(+D14*$Z$3,-3) -> 75000 | F14: =ROUNDUP(+E14*$Z$3,-3) -> 77000 | G14: =ROUNDUP(+F14*$Z$3,-3) -> 79000 | H14: =ROUNDUP(+G14*$Z$3,-3) -> 81000 | I14: =ROUNDUP(+H14*$Z$3,-3) -> 84000 | J14: =ROUNDUP(+I14*$Z$3,-3) -> 87000 | K14: =ROUNDUP(+J14*$Z$3,-3) -> 90000 | L14: =ROUNDUP(+K14*$Z$3,-3) -> 93000 | N14: =+C14/$Z$5 -> 583.56164 | O14: =+D14/$Z$5 -> 600 | P14: =+E14/$Z$5 -> 616.43836 | Q14: =+F14/$Z$5 -> 632.87671 | R14: =+G14/$Z$5 -> 649.31507 | S14: =+H14/$Z$5 -> 665.75342 | T14: =+I14/$Z$5 -> 690.41096 | U14: =+J14/$Z$5 -> 715.06849 | ... W14: =+L14/$Z$5 -> 764.38356
A15: Assistant Professor | B15: =_xlfn.XLOOKUP(Tabel12[[#This Row],[VIP]],Tabel19[Job functions],Tabel19[Column1],"",0)&"" | C15: 55000 | D15: =ROUNDUP(+C15*$Z$3,-3) -> 57000 | E15: =ROUNDUP(+D15*$Z$3,-3) -> 59000 | F15: =ROUNDUP(+E15*$Z$3,-3) -> 61000 | G15: =ROUNDUP(+F15*$Z$3,-3) -> 63000 | H15: =ROUNDUP(+G15*$Z$3,-3) -> 65000 | I15: =ROUNDUP(+H15*$Z$3,-3) -> 67000 | J15: =ROUNDUP(+I15*$Z$3,-3) -> 69000 | K15: =ROUNDUP(+J15*$Z$3,-3) -> 71000 | L15: =ROUNDUP(+K15*$Z$3,-3) -> 73000 | N15: =+C15/$Z$5 -> 452.05479 | O15: =+D15/$Z$5 -> 468.49315 | P15: =+E15/$Z$5 -> 484.93151 | Q15: =+F15/$Z$5 -> 501.36986 | R15: =+G15/$Z$5 -> 517.80822 | S15: =+H15/$Z$5 -> 534.24658 | T15: =+I15/$Z$5 -> 550.68493 | U15: =+J15/$Z$5 -> 567.12329 | ... W15: =+L15/$Z$5 -> 600
A16: Tenure Track - high rate | B16: =_xlfn.XLOOKUP(Tabel12[[#This Row],[VIP]],Tabel19[Job functions],Tabel19[Column1],"",0)&"" | C16: 57000 | D16: =ROUNDUP(+C16*$Z$3,-3) -> 59000 | E16: =ROUNDUP(+D16*$Z$3,-3) -> 61000 | F16: =ROUNDUP(+E16*$Z$3,-3) -> 63000 | G16: =ROUNDUP(+F16*$Z$3,-3) -> 65000 | H16: =ROUNDUP(+G16*$Z$3,-3) -> 67000 | I16: =ROUNDUP(+H16*$Z$3,-3) -> 69000 | J16: =ROUNDUP(+I16*$Z$3,-3) -> 71000 | K16: =ROUNDUP(+J16*$Z$3,-3) -> 73000 | L16: =ROUNDUP(+K16*$Z$3,-3) -> 75000 | N16: =+C16/$Z$5 -> 468.49315 | O16: =+D16/$Z$5 -> 484.93151 | P16: =+E16/$Z$5 -> 501.36986 | Q16: =+F16/$Z$5 -> 517.80822 | R16: =+G16/$Z$5 -> 534.24658 | S16: =+H16/$Z$5 -> 550.68493 | T16: =+I16/$Z$5 -> 567.12329 | U16: =+J16/$Z$5 -> 583.56164 | ... W16: =+L16/$Z$5 -> 616.43836
A17: Tenure Track - avr. rate | B17: =_xlfn.XLOOKUP(Tabel12[[#This Row],[VIP]],Tabel19[Job functions],Tabel19[Column1],"",0)&"" | C17: 55000 | D17: =ROUNDUP(+C17*$Z$3,-3) -> 57000 | E17: =ROUNDUP(+D17*$Z$3,-3) -> 59000 | F17: =ROUNDUP(+E17*$Z$3,-3) -> 61000 | G17: =ROUNDUP(+F17*$Z$3,-3) -> 63000 | H17: =ROUNDUP(+G17*$Z$3,-3) -> 65000 | I17: =ROUNDUP(+H17*$Z$3,-3) -> 67000 | J17: =ROUNDUP(+I17*$Z$3,-3) -> 69000 | K17: =ROUNDUP(+J17*$Z$3,-3) -> 71000 | L17: =ROUNDUP(+K17*$Z$3,-3) -> 73000 | N17: =+C17/$Z$5 -> 452.05479 | O17: =+D17/$Z$5 -> 468.49315 | P17: =+E17/$Z$5 -> 484.93151 | Q17: =+F17/$Z$5 -> 501.36986 | R17: =+G17/$Z$5 -> 517.80822 | S17: =+H17/$Z$5 -> 534.24658 | T17: =+I17/$Z$5 -> 550.68493 | U17: =+J17/$Z$5 -> 567.12329 | ... W17: =+L17/$Z$5 -> 600
... A27: Post Doc abroad (Applicant, no project supplement) - low rate | B27: =_xlfn.XLOOKUP(Tabel12[[#This Row],[VIP]],Tabel19[Job functions],Tabel19[Column1],"",0)&"" | C27: 53000 | D27: =ROUNDUP(+C27*$Z$3,-3) -> 55000 | E27: =ROUNDUP(+D27*$Z$3,-3) -> 57000 | F27: =ROUNDUP(+E27*$Z$3,-3) -> 59000 | G27: =ROUNDUP(+F27*$Z$3,-3) -> 61000 | H27: =ROUNDUP(+G27*$Z$3,-3) -> 63000 | I27: =ROUNDUP(+H27*$Z$3,-3) -> 65000 | J27: =ROUNDUP(+I27*$Z$3,-3) -> 67000 | K27: =ROUNDUP(+J27*$Z$3,-3) -> 69000 | L27: =ROUNDUP(+K27*$Z$3,-3) -> 71000 | N27: =+C27/$Z$5 -> 435.61644 | O27: =+D27/$Z$5 -> 452.05479 | P27: =+E27/$Z$5 -> 468.49315 | Q27: =+F27/$Z$5 -> 484.93151 | R27: =+G27/$Z$5 -> 501.36986 | S27: =+H27/$Z$5 -> 517.80822 | T27: =+I27/$Z$5 -> 534.24658 | U27: =+J27/$Z$5 -> 550.68493 | ... W27: =+L27/$Z$5 -> 583.56164
B28: =_xlfn.XLOOKUP(Tabel12[[#This Row],[VIP]],Tabel19[Job functions],Tabel19[Column1],"",0)&"" | C28: 0 | D28: =ROUNDUP(+C28*$Z$3,-3) -> 0 | E28: =ROUNDUP(+D28*$Z$3,-3) -> 0 | F28: =ROUNDUP(+E28*$Z$3,-3) -> 0 | G28: =ROUNDUP(+F28*$Z$3,-3) -> 0 | H28: =ROUNDUP(+G28*$Z$3,-3) -> 0 | I28: =ROUNDUP(+H28*$Z$3,-3) -> 0 | J28: =ROUNDUP(+I28*$Z$3,-3) -> 0 | K28: =ROUNDUP(+J28*$Z$3,-3) -> 0 | L28: =ROUNDUP(+K28*$Z$3,-3) -> 0 | N28: =+C28/$Z$5 -> 0 | O28: =+D28/$Z$5 -> 0 | P28: =+E28/$Z$5 -> 0 | Q28: =+F28/$Z$5 -> 0 | R28: =+G28/$Z$5 -> 0 | S28: =+H28/$Z$5 -> 0 | T28: =+I28/$Z$5 -> 0 | U28: =+J28/$Z$5 -> 0 | ... W28: =+L28/$Z$5 -> 0
B29: =_xlfn.XLOOKUP(Tabel12[[#This Row],[VIP]],Tabel19[Job functions],Tabel19[Column1],"",0)&"" | C29: 0 | D29: =ROUNDUP(+C29*$Z$3,-3) -> 0 | E29: =ROUNDUP(+D29*$Z$3,-3) -> 0 | F29: =ROUNDUP(+E29*$Z$3,-3) -> 0 | G29: =ROUNDUP(+F29*$Z$3,-3) -> 0 | H29: =ROUNDUP(+G29*$Z$3,-3) -> 0 | I29: =ROUNDUP(+H29*$Z$3,-3) -> 0 | J29: =ROUNDUP(+I29*$Z$3,-3) -> 0 | K29: =ROUNDUP(+J29*$Z$3,-3) -> 0 | L29: =ROUNDUP(+K29*$Z$3,-3) -> 0 | N29: =+C29/$Z$5 -> 0 | O29: =+D29/$Z$5 -> 0 | P29: =+E29/$Z$5 -> 0 | Q29: =+F29/$Z$5 -> 0 | R29: =+G29/$Z$5 -> 0 | S29: =+H29/$Z$5 -> 0 | T29: =+I29/$Z$5 -> 0 | U29: =+J29/$Z$5 -> 0 | ... W29: =+L29/$Z$5 -> 0
B30: =_xlfn.XLOOKUP(Tabel12[[#This Row],[VIP]],Tabel19[Job functions],Tabel19[Column1],"",0)&"" | C30: 0 | D30: =ROUNDUP(+C30*$Z$3,-3) -> 0 | E30: =ROUNDUP(+D30*$Z$3,-3) -> 0 | F30: =ROUNDUP(+E30*$Z$3,-3) -> 0 | G30: =ROUNDUP(+F30*$Z$3,-3) -> 0 | H30: =ROUNDUP(+G30*$Z$3,-3) -> 0 | I30: =ROUNDUP(+H30*$Z$3,-3) -> 0 | J30: =ROUNDUP(+I30*$Z$3,-3) -> 0 | K30: =ROUNDUP(+J30*$Z$3,-3) -> 0 | L30: =ROUNDUP(+K30*$Z$3,-3) -> 0 | N30: =+C30/$Z$5 -> 0 | O30: =+D30/$Z$5 -> 0 | P30: =+E30/$Z$5 -> 0 | Q30: =+F30/$Z$5 -> 0 | R30: =+G30/$Z$5 -> 0 | S30: =+H30/$Z$5 -> 0 | T30: =+I30/$Z$5 -> 0 | U30: =+J30/$Z$5 -> 0 | ... W30: =+L30/$Z$5 -> 0
A32: TAP | C32: Column1 | D32: Hvis der tastes en medarbejder inkl. Kostpris ind, så skriv Laborant, Tekniker eller TAP/Ørig kandidatuddannet I kolonne B, idet den så medtages I forskningsadministrationsberegningen
A33: "Choose job position" | B33: =_xlfn.XLOOKUP(Tabel13[[#This Row],[TAP]],Tabel19[Job functions],Tabel19[Column1],"",0)&""
A34: Student help | B34: =_xlfn.XLOOKUP(Tabel13[[#This Row],[TAP]],Tabel19[Job functions],Tabel19[Column1],"",0)&"" | C34: 25000 | D34: =ROUNDUP(+C34*$Z$3,-2) -> 25700 | E34: =ROUNDUP(+D34*$Z$3,-2) -> 26400 | F34: =ROUNDUP(+E34*$Z$3,-2) -> 27100 | G34: =ROUNDUP(+F34*$Z$3,-2) -> 27800 | H34: =ROUNDUP(+G34*$Z$3,-2) -> 28500 | I34: =ROUNDUP(+H34*$Z$3,-2) -> 29300 | J34: =ROUNDUP(+I34*$Z$3,-2) -> 30100 | K34: =ROUNDUP(+J34*$Z$3,-2) -> 30900 | L34: =ROUNDUP(+K34*$Z$3,-2) -> 31700 | N34: =+C34/$Z$5 -> 205.47945 | O34: =+D34/$Z$5 -> 211.23288 | P34: =+E34/$Z$5 -> 216.9863 | Q34: =+F34/$Z$5 -> 222.73973 | R34: =+G34/$Z$5 -> 228.49315 | S34: =+H34/$Z$5 -> 234.24658 | T34: =+I34/$Z$5 -> 240.82192 | U34: =+J34/$Z$5 -> 247.39726 | ... W34: =+L34/$Z$5 -> 260.54795
A35: TAP/Other masters degree | B35: =_xlfn.XLOOKUP(Tabel13[[#This Row],[TAP]],Tabel19[Job functions],Tabel19[Column1],"",0)&"" -> TAP/Other Masters degree | C35: 59000 | D35: =ROUNDUP(+C35*$Z$3,-2) -> 60500 | E35: =ROUNDUP(+D35*$Z$3,-2) -> 62100 | F35: =ROUNDUP(+E35*$Z$3,-2) -> 63700 | G35: =ROUNDUP(+F35*$Z$3,-2) -> 65300 | H35: =ROUNDUP(+G35*$Z$3,-2) -> 67000 | I35: =ROUNDUP(+H35*$Z$3,-2) -> 68700 | J35: =ROUNDUP(+I35*$Z$3,-2) -> 70500 | K35: =ROUNDUP(+J35*$Z$3,-2) -> 72300 | L35: =ROUNDUP(+K35*$Z$3,-2) -> 74200 | N35: =+C35/$Z$5 -> 484.93151 | O35: =+D35/$Z$5 -> 497.26027 | P35: =+E35/$Z$5 -> 510.41096 | Q35: =+F35/$Z$5 -> 523.56164 | R35: =+G35/$Z$5 -> 536.71233 | S35: =+H35/$Z$5 -> 550.68493 | T35: =+I35/$Z$5 -> 564.65753 | U35: =+J35/$Z$5 -> 579.45205 | ... W35: =+L35/$Z$5 -> 609.86301
A36: Data/IT employee | B36: =_xlfn.XLOOKUP(Tabel13[[#This Row],[TAP]],Tabel19[Job functions],Tabel19[Column1],"",0)&"" | C36: 57000 | D36: =ROUNDUP(+C36*$Z$3,-2) -> 58500 | E36: =ROUNDUP(+D36*$Z$3,-2) -> 60000 | F36: =ROUNDUP(+E36*$Z$3,-2) -> 61500 | G36: =ROUNDUP(+F36*$Z$3,-2) -> 63100 | H36: =ROUNDUP(+G36*$Z$3,-2) -> 64700 | I36: =ROUNDUP(+H36*$Z$3,-2) -> 66400 | J36: =ROUNDUP(+I36*$Z$3,-2) -> 68100 | K36: =ROUNDUP(+J36*$Z$3,-2) -> 69900 | L36: =ROUNDUP(+K36*$Z$3,-2) -> 71700 | N36: =+C36/$Z$5 -> 468.49315 | O36: =+D36/$Z$5 -> 480.82192 | P36: =+E36/$Z$5 -> 493.15068 | Q36: =+F36/$Z$5 -> 505.47945 | R36: =+G36/$Z$5 -> 518.63014 | S36: =+H36/$Z$5 -> 531.78082 | T36: =+I36/$Z$5 -> 545.75342 | U36: =+J36/$Z$5 -> 559.72603 | ... W36: =+L36/$Z$5 -> 589.31507
A37: Laboratory technician - high rate | B37: =_xlfn.XLOOKUP(Tabel13[[#This Row],[TAP]],Tabel19[Job functions],Tabel19[Column1],"",0)&"" -> Laboratory technician | C37: 48000 | D37: =ROUNDUP(+C37*$Z$3,-2) -> 49200 | E37: =ROUNDUP(+D37*$Z$3,-2) -> 50500 | F37: =ROUNDUP(+E37*$Z$3,-2) -> 51800 | G37: =ROUNDUP(+F37*$Z$3,-2) -> 53100 | H37: =ROUNDUP(+G37*$Z$3,-2) -> 54500 | I37: =ROUNDUP(+H37*$Z$3,-2) -> 55900 | J37: =ROUNDUP(+I37*$Z$3,-2) -> 57300 | K37: =ROUNDUP(+J37*$Z$3,-2) -> 58800 | L37: =ROUNDUP(+K37*$Z$3,-2) -> 60300 | N37: =+C37/$Z$5 -> 394.52055 | O37: =+D37/$Z$5 -> 404.38356 | P37: =+E37/$Z$5 -> 415.06849 | Q37: =+F37/$Z$5 -> 425.75342 | R37: =+G37/$Z$5 -> 436.43836 | S37: =+H37/$Z$5 -> 447.94521 | T37: =+I37/$Z$5 -> 459.45205 | U37: =+J37/$Z$5 -> 470.9589 | ... W37: =+L37/$Z$5 -> 495.61644
A38: Laboratory technician - avr. rate | B38: =_xlfn.XLOOKUP(Tabel13[[#This Row],[TAP]],Tabel19[Job functions],Tabel19[Column1],"",0)&"" -> Laboratory technician | C38: 44000 | D38: =ROUNDUP(+C38*$Z$3,-2) -> 45100 | E38: =ROUNDUP(+D38*$Z$3,-2) -> 46300 | F38: =ROUNDUP(+E38*$Z$3,-2) -> 47500 | G38: =ROUNDUP(+F38*$Z$3,-2) -> 48700 | H38: =ROUNDUP(+G38*$Z$3,-2) -> 50000 | I38: =ROUNDUP(+H38*$Z$3,-2) -> 51300 | J38: =ROUNDUP(+I38*$Z$3,-2) -> 52600 | K38: =ROUNDUP(+J38*$Z$3,-2) -> 54000 | L38: =ROUNDUP(+K38*$Z$3,-2) -> 55400 | N38: =+C38/$Z$5 -> 361.64384 | O38: =+D38/$Z$5 -> 370.68493 | P38: =+E38/$Z$5 -> 380.54795 | Q38: =+F38/$Z$5 -> 390.41096 | R38: =+G38/$Z$5 -> 400.27397 | S38: =+H38/$Z$5 -> 410.9589 | T38: =+I38/$Z$5 -> 421.64384 | U38: =+J38/$Z$5 -> 432.32877 | ... W38: =+L38/$Z$5 -> 455.34247
A39: Laboratory technician - low rate | B39: =_xlfn.XLOOKUP(Tabel13[[#This Row],[TAP]],Tabel19[Job functions],Tabel19[Column1],"",0)&"" -> Laboratory technician | C39: 41000 | D39: =ROUNDUP(+C39*$Z$3,-2) -> 42100 | E39: =ROUNDUP(+D39*$Z$3,-2) -> 43200 | F39: =ROUNDUP(+E39*$Z$3,-2) -> 44300 | G39: =ROUNDUP(+F39*$Z$3,-2) -> 45500 | H39: =ROUNDUP(+G39*$Z$3,-2) -> 46700 | I39: =ROUNDUP(+H39*$Z$3,-2) -> 47900 | J39: =ROUNDUP(+I39*$Z$3,-2) -> 49100 | K39: =ROUNDUP(+J39*$Z$3,-2) -> 50400 | L39: =ROUNDUP(+K39*$Z$3,-2) -> 51700 | N39: =+C39/$Z$5 -> 336.9863 | O39: =+D39/$Z$5 -> 346.0274 | P39: =+E39/$Z$5 -> 355.06849 | Q39: =+F39/$Z$5 -> 364.10959 | R39: =+G39/$Z$5 -> 373.9726 | S39: =+H39/$Z$5 -> 383.83562 | T39: =+I39/$Z$5 -> 393.69863 | U39: =+J39/$Z$5 -> 403.56164 | ... W39: =+L39/$Z$5 -> 424.93151
A40: Technician - high rate | B40: =_xlfn.XLOOKUP(Tabel13[[#This Row],[TAP]],Tabel19[Job functions],Tabel19[Column1],"",0)&"" -> Technician | C40: 53000 | D40: =ROUNDUP(+C40*$Z$3,-2) -> 54400 | E40: =ROUNDUP(+D40*$Z$3,-2) -> 55800 | F40: =ROUNDUP(+E40*$Z$3,-2) -> 57200 | G40: =ROUNDUP(+F40*$Z$3,-2) -> 58700 | H40: =ROUNDUP(+G40*$Z$3,-2) -> 60200 | I40: =ROUNDUP(+H40*$Z$3,-2) -> 61800 | J40: =ROUNDUP(+I40*$Z$3,-2) -> 63400 | K40: =ROUNDUP(+J40*$Z$3,-2) -> 65000 | L40: =ROUNDUP(+K40*$Z$3,-2) -> 66700 | N40: =+C40/$Z$5 -> 435.61644 | O40: =+D40/$Z$5 -> 447.12329 | P40: =+E40/$Z$5 -> 458.63014 | Q40: =+F40/$Z$5 -> 470.13699 | R40: =+G40/$Z$5 -> 482.46575 | S40: =+H40/$Z$5 -> 494.79452 | T40: =+I40/$Z$5 -> 507.94521 | U40: =+J40/$Z$5 -> 521.09589 | ... W40: =+L40/$Z$5 -> 548.21918
A41: Technician - avr. rate | B41: =_xlfn.XLOOKUP(Tabel13[[#This Row],[TAP]],Tabel19[Job functions],Tabel19[Column1],"",0)&"" -> Technician | C41: 50000 | D41: =ROUNDUP(+C41*$Z$3,-2) -> 51300 | E41: =ROUNDUP(+D41*$Z$3,-2) -> 52600 | F41: =ROUNDUP(+E41*$Z$3,-2) -> 54000 | G41: =ROUNDUP(+F41*$Z$3,-2) -> 55400 | H41: =ROUNDUP(+G41*$Z$3,-2) -> 56800 | I41: =ROUNDUP(+H41*$Z$3,-2) -> 58300 | J41: =ROUNDUP(+I41*$Z$3,-2) -> 59800 | K41: =ROUNDUP(+J41*$Z$3,-2) -> 61300 | L41: =ROUNDUP(+K41*$Z$3,-2) -> 62900 | N41: =+C41/$Z$5 -> 410.9589 | O41: =+D41/$Z$5 -> 421.64384 | P41: =+E41/$Z$5 -> 432.32877 | Q41: =+F41/$Z$5 -> 443.83562 | R41: =+G41/$Z$5 -> 455.34247 | S41: =+H41/$Z$5 -> 466.84932 | T41: =+I41/$Z$5 -> 479.17808 | U41: =+J41/$Z$5 -> 491.50685 | ... W41: =+L41/$Z$5 -> 516.9863
A42: Technician - low rate | B42: =_xlfn.XLOOKUP(Tabel13[[#This Row],[TAP]],Tabel19[Job functions],Tabel19[Column1],"",0)&"" -> Technician | C42: 45000 | D42: =ROUNDUP(+C42*$Z$3,-2) -> 46200 | E42: =ROUNDUP(+D42*$Z$3,-2) -> 47400 | F42: =ROUNDUP(+E42*$Z$3,-2) -> 48600 | G42: =ROUNDUP(+F42*$Z$3,-2) -> 49900 | H42: =ROUNDUP(+G42*$Z$3,-2) -> 51200 | I42: =ROUNDUP(+H42*$Z$3,-2) -> 52500 | J42: =ROUNDUP(+I42*$Z$3,-2) -> 53900 | K42: =ROUNDUP(+J42*$Z$3,-2) -> 55300 | L42: =ROUNDUP(+K42*$Z$3,-2) -> 56700 | N42: =+C42/$Z$5 -> 369.86301 | O42: =+D42/$Z$5 -> 379.72603 | P42: =+E42/$Z$5 -> 389.58904 | Q42: =+F42/$Z$5 -> 399.45205 | R42: =+G42/$Z$5 -> 410.13699 | S42: =+H42/$Z$5 -> 420.82192 | T42: =+I42/$Z$5 -> 431.50685 | U42: =+J42/$Z$5 -> 443.0137 | ... W42: =+L42/$Z$5 -> 466.0274
A43: Other TAP - avr. rate | B43: =_xlfn.XLOOKUP(Tabel13[[#This Row],[TAP]],Tabel19[Job functions],Tabel19[Column1],"",0)&"" | C43: 47000 | D43: =ROUNDUP(+C43*$Z$3,-2) -> 48200 | E43: =ROUNDUP(+D43*$Z$3,-2) -> 49500 | F43: =ROUNDUP(+E43*$Z$3,-2) -> 50800 | G43: =ROUNDUP(+F43*$Z$3,-2) -> 52100 | H43: =ROUNDUP(+G43*$Z$3,-2) -> 53500 | I43: =ROUNDUP(+H43*$Z$3,-2) -> 54900 | J43: =ROUNDUP(+I43*$Z$3,-2) -> 56300 | K43: =ROUNDUP(+J43*$Z$3,-2) -> 57800 | L43: =ROUNDUP(+K43*$Z$3,-2) -> 59300 | N43: =+C43/$Z$5 -> 386.30137 | O43: =+D43/$Z$5 -> 396.16438 | P43: =+E43/$Z$5 -> 406.84932 | Q43: =+F43/$Z$5 -> 417.53425 | R43: =+G43/$Z$5 -> 428.21918 | S43: =+H43/$Z$5 -> 439.72603 | T43: =+I43/$Z$5 -> 451.23288 | U43: =+J43/$Z$5 -> 462.73973 | ... W43: =+L43/$Z$5 -> 487.39726
A44: Secretary | B44: =_xlfn.XLOOKUP(Tabel13[[#This Row],[TAP]],Tabel19[Job functions],Tabel19[Column1],"",0)&"" | C44: 46000 | D44: =ROUNDUP(+C44*$Z$3,-2) -> 47200 | E44: =ROUNDUP(+D44*$Z$3,-2) -> 48400 | F44: =ROUNDUP(+E44*$Z$3,-2) -> 49700 | G44: =ROUNDUP(+F44*$Z$3,-2) -> 51000 | H44: =ROUNDUP(+G44*$Z$3,-2) -> 52300 | I44: =ROUNDUP(+H44*$Z$3,-2) -> 53700 | J44: =ROUNDUP(+I44*$Z$3,-2) -> 55100 | K44: =ROUNDUP(+J44*$Z$3,-2) -> 56500 | L44: =ROUNDUP(+K44*$Z$3,-2) -> 58000 | N44: =+C44/$Z$5 -> 378.08219 | O44: =+D44/$Z$5 -> 387.94521 | P44: =+E44/$Z$5 -> 397.80822 | Q44: =+F44/$Z$5 -> 408.49315 | R44: =+G44/$Z$5 -> 419.17808 | S44: =+H44/$Z$5 -> 429.86301 | T44: =+I44/$Z$5 -> 441.36986 | U44: =+J44/$Z$5 -> 452.87671 | ... W44: =+L44/$Z$5 -> 476.71233
A45: Special/manager consultant- high rate | B45: =_xlfn.XLOOKUP(Tabel13[[#This Row],[TAP]],Tabel19[Job functions],Tabel19[Column1],"",0)&"" | C45: 69000 | D45: =ROUNDUP(+C45*$Z$3,-2) -> 70800 | E45: =ROUNDUP(+D45*$Z$3,-2) -> 72600 | F45: =ROUNDUP(+E45*$Z$3,-2) -> 74500 | G45: =ROUNDUP(+F45*$Z$3,-2) -> 76400 | H45: =ROUNDUP(+G45*$Z$3,-2) -> 78400 | I45: =ROUNDUP(+H45*$Z$3,-2) -> 80400 | J45: =ROUNDUP(+I45*$Z$3,-2) -> 82500 | K45: =ROUNDUP(+J45*$Z$3,-2) -> 84600 | L45: =ROUNDUP(+K45*$Z$3,-2) -> 86800 | N45: =+C45/$Z$5 -> 567.12329 | O45: =+D45/$Z$5 -> 581.91781 | P45: =+E45/$Z$5 -> 596.71233 | Q45: =+F45/$Z$5 -> 612.32877 | R45: =+G45/$Z$5 -> 627.94521 | S45: =+H45/$Z$5 -> 644.38356 | T45: =+I45/$Z$5 -> 660.82192 | U45: =+J45/$Z$5 -> 678.08219 | ... W45: =+L45/$Z$5 -> 713.42466
... A47: Special/manager consultant - low rate | B47: =_xlfn.XLOOKUP(Tabel13[[#This Row],[TAP]],Tabel19[Job functions],Tabel19[Column1],"",0)&"" | C47: 62000 | D47: =ROUNDUP(+C47*$Z$3,-2) -> 63600 | E47: =ROUNDUP(+D47*$Z$3,-2) -> 65200 | F47: =ROUNDUP(+E47*$Z$3,-2) -> 66900 | G47: =ROUNDUP(+F47*$Z$3,-2) -> 68600 | H47: =ROUNDUP(+G47*$Z$3,-2) -> 70400 | I47: =ROUNDUP(+H47*$Z$3,-2) -> 72200 | J47: =ROUNDUP(+I47*$Z$3,-2) -> 74100 | K47: =ROUNDUP(+J47*$Z$3,-2) -> 76000 | L47: =ROUNDUP(+K47*$Z$3,-2) -> 77900 | N47: =+C47/$Z$5 -> 509.58904 | O47: =+D47/$Z$5 -> 522.73973 | P47: =+E47/$Z$5 -> 535.89041 | Q47: =+F47/$Z$5 -> 549.86301 | R47: =+G47/$Z$5 -> 563.83562 | S47: =+H47/$Z$5 -> 578.63014 | T47: =+I47/$Z$5 -> 593.42466 | U47: =+J47/$Z$5 -> 609.0411 | ... W47: =+L47/$Z$5 -> 640.27397
B48: =_xlfn.XLOOKUP(Tabel13[[#This Row],[TAP]],Tabel19[Job functions],Tabel19[Column1],"",0)&"" | C48: 0 | D48: =ROUNDUP(+C48*$Z$3,-2) -> 0 | E48: =ROUNDUP(+D48*$Z$3,-2) -> 0 | F48: =ROUNDUP(+E48*$Z$3,-2) -> 0 | G48: =ROUNDUP(+F48*$Z$3,-2) -> 0 | H48: =ROUNDUP(+G48*$Z$3,-2) -> 0 | I48: =ROUNDUP(+H48*$Z$3,-2) -> 0 | J48: =ROUNDUP(+I48*$Z$3,-2) -> 0 | K48: =ROUNDUP(+J48*$Z$3,-2) -> 0 | L48: =ROUNDUP(+K48*$Z$3,-2) -> 0 | N48: =+C48/$Z$5 -> 0 | O48: =+D48/$Z$5 -> 0 | P48: =+E48/$Z$5 -> 0 | Q48: =+F48/$Z$5 -> 0 | R48: =+G48/$Z$5 -> 0 | S48: =+H48/$Z$5 -> 0 | T48: =+I48/$Z$5 -> 0 | U48: =+J48/$Z$5 -> 0 | ... W48: =+L48/$Z$5 -> 0
B49: =_xlfn.XLOOKUP(Tabel13[[#This Row],[TAP]],Tabel19[Job functions],Tabel19[Column1],"",0)&"" | C49: 0 | D49: =ROUNDUP(+C49*$Z$3,-2) -> 0 | E49: =ROUNDUP(+D49*$Z$3,-2) -> 0 | F49: =ROUNDUP(+E49*$Z$3,-2) -> 0 | G49: =ROUNDUP(+F49*$Z$3,-2) -> 0 | H49: =ROUNDUP(+G49*$Z$3,-2) -> 0 | I49: =ROUNDUP(+H49*$Z$3,-2) -> 0 | J49: =ROUNDUP(+I49*$Z$3,-2) -> 0 | K49: =ROUNDUP(+J49*$Z$3,-2) -> 0 | L49: =ROUNDUP(+K49*$Z$3,-2) -> 0 | N49: =+C49/$Z$5 -> 0 | O49: =+D49/$Z$5 -> 0 | P49: =+E49/$Z$5 -> 0 | Q49: =+F49/$Z$5 -> 0 | R49: =+G49/$Z$5 -> 0 | S49: =+H49/$Z$5 -> 0 | T49: =+I49/$Z$5 -> 0 | U49: =+J49/$Z$5 -> 0 | ... W49: =+L49/$Z$5 -> 0
B50: =_xlfn.XLOOKUP(Tabel13[[#This Row],[TAP]],Tabel19[Job functions],Tabel19[Column1],"",0)&"" | C50: 0 | D50: =ROUNDUP(+C50*$Z$3,-2) -> 0 | E50: =ROUNDUP(+D50*$Z$3,-2) -> 0 | F50: =ROUNDUP(+E50*$Z$3,-2) -> 0 | G50: =ROUNDUP(+F50*$Z$3,-2) -> 0 | H50: =ROUNDUP(+G50*$Z$3,-2) -> 0 | I50: =ROUNDUP(+H50*$Z$3,-2) -> 0 | J50: =ROUNDUP(+I50*$Z$3,-2) -> 0 | K50: =ROUNDUP(+J50*$Z$3,-2) -> 0 | L50: =ROUNDUP(+K50*$Z$3,-2) -> 0 | N50: =+C50/$Z$5 -> 0 | O50: =+D50/$Z$5 -> 0 | P50: =+E50/$Z$5 -> 0 | Q50: =+F50/$Z$5 -> 0 | R50: =+G50/$Z$5 -> 0 | S50: =+H50/$Z$5 -> 0 | T50: =+I50/$Z$5 -> 0 | U50: =+J50/$Z$5 -> 0 | ... W50: =+L50/$Z$5 -> 0
B51: =_xlfn.XLOOKUP(Tabel13[[#This Row],[TAP]],Tabel19[Job functions],Tabel19[Column1],"",0)&"" | C51: 0 | D51: =ROUNDUP(+C51*$Z$3,-2) -> 0 | E51: =ROUNDUP(+D51*$Z$3,-2) -> 0 | F51: =ROUNDUP(+E51*$Z$3,-2) -> 0 | G51: =ROUNDUP(+F51*$Z$3,-2) -> 0 | H51: =ROUNDUP(+G51*$Z$3,-2) -> 0 | I51: =ROUNDUP(+H51*$Z$3,-2) -> 0 | J51: =ROUNDUP(+I51*$Z$3,-2) -> 0 | K51: =ROUNDUP(+J51*$Z$3,-2) -> 0 | L51: =ROUNDUP(+K51*$Z$3,-2) -> 0 | N51: =+C51/$Z$5 -> 0 | O51: =+D51/$Z$5 -> 0 | P51: =+E51/$Z$5 -> 0 | Q51: =+F51/$Z$5 -> 0 | R51: =+G51/$Z$5 -> 0 | S51: =+H51/$Z$5 -> 0 | T51: =+I51/$Z$5 -> 0 | U51: =+J51/$Z$5 -> 0 | ... W51: =+L51/$Z$5 -> 0
B52: =_xlfn.XLOOKUP(Tabel13[[#This Row],[TAP]],Tabel19[Job functions],Tabel19[Column1],"",0)&"" | C52: 0 | D52: =ROUNDUP(+C52*$Z$3,-2) -> 0 | E52: =ROUNDUP(+D52*$Z$3,-2) -> 0 | F52: =ROUNDUP(+E52*$Z$3,-2) -> 0 | G52: =ROUNDUP(+F52*$Z$3,-2) -> 0 | H52: =ROUNDUP(+G52*$Z$3,-2) -> 0 | I52: =ROUNDUP(+H52*$Z$3,-2) -> 0 | J52: =ROUNDUP(+I52*$Z$3,-2) -> 0 | K52: =ROUNDUP(+J52*$Z$3,-2) -> 0 | L52: =ROUNDUP(+K52*$Z$3,-2) -> 0 | N52: =+C52/$Z$5 -> 0 | O52: =+D52/$Z$5 -> 0 | P52: =+E52/$Z$5 -> 0 | Q52: =+F52/$Z$5 -> 0 | R52: =+G52/$Z$5 -> 0 | S52: =+H52/$Z$5 -> 0 | T52: =+I52/$Z$5 -> 0 | U52: =+J52/$Z$5 -> 0 | ... W52: =+L52/$Z$5 -> 0
B53: =_xlfn.XLOOKUP(Tabel13[[#This Row],[TAP]],Tabel19[Job functions],Tabel19[Column1],"",0)&"" | C53: 0 | D53: =ROUNDUP(+C53*$Z$3,-2) -> 0 | E53: =ROUNDUP(+D53*$Z$3,-2) -> 0 | F53: =ROUNDUP(+E53*$Z$3,-2) -> 0 | G53: =ROUNDUP(+F53*$Z$3,-2) -> 0 | H53: =ROUNDUP(+G53*$Z$3,-2) -> 0 | I53: =ROUNDUP(+H53*$Z$3,-2) -> 0 | J53: =ROUNDUP(+I53*$Z$3,-2) -> 0 | K53: =ROUNDUP(+J53*$Z$3,-2) -> 0 | L53: =ROUNDUP(+K53*$Z$3,-2) -> 0 | N53: =+C53/$Z$5 -> 0 | O53: =+D53/$Z$5 -> 0 | P53: =+E53/$Z$5 -> 0 | Q53: =+F53/$Z$5 -> 0 | R53: =+G53/$Z$5 -> 0 | S53: =+H53/$Z$5 -> 0 | T53: =+I53/$Z$5 -> 0 | U53: =+J53/$Z$5 -> 0 | ... W53: =+L53/$Z$5 -> 0
B54: =_xlfn.XLOOKUP(Tabel13[[#This Row],[TAP]],Tabel19[Job functions],Tabel19[Column1],"",0)&"" | C54: 0 | D54: =ROUNDUP(+C54*$Z$3,-2) -> 0 | E54: =ROUNDUP(+D54*$Z$3,-2) -> 0 | F54: =ROUNDUP(+E54*$Z$3,-2) -> 0 | G54: =ROUNDUP(+F54*$Z$3,-2) -> 0 | H54: =ROUNDUP(+G54*$Z$3,-2) -> 0 | I54: =ROUNDUP(+H54*$Z$3,-2) -> 0 | J54: =ROUNDUP(+I54*$Z$3,-2) -> 0 | K54: =ROUNDUP(+J54*$Z$3,-2) -> 0 | L54: =ROUNDUP(+K54*$Z$3,-2) -> 0 | N54: =+C54/$Z$5 -> 0 | O54: =+D54/$Z$5 -> 0 | P54: =+E54/$Z$5 -> 0 | Q54: =+F54/$Z$5 -> 0 | R54: =+G54/$Z$5 -> 0 | S54: =+H54/$Z$5 -> 0 | T54: =+I54/$Z$5 -> 0 | U54: =+J54/$Z$5 -> 0 | ... W54: =+L54/$Z$5 -> 0
A56: DRIFT | B56: Column1
A57: Secretary salary | C57: =C44 -> 46000 | D57: =ROUNDUP(+C57*$Z$3,-2) -> 47200 | E57: =ROUNDUP(+D57*$Z$3,-2) -> 48400 | F57: =ROUNDUP(+E57*$Z$3,-2) -> 49700 | G57: =ROUNDUP(+F57*$Z$3,-2) -> 51000 | H57: =ROUNDUP(+G57*$Z$3,-2) -> 52300 | I57: =ROUNDUP(+H57*$Z$3,-2) -> 53700 | J57: =ROUNDUP(+I57*$Z$3,-2) -> 55100 | K57: =ROUNDUP(+J57*$Z$3,-2) -> 56500 | L57: =ROUNDUP(+K57*$Z$3,-2) -> 58000
A58: Supplement to research administration TAP AGRO | B58: AGRO | C58: 7200 | D58: =ROUNDUP(+C58*$Z$3,-2) -> 7400 | E58: =ROUNDUP(+D58*$Z$3,-2) -> 7600 | F58: =ROUNDUP(+E58*$Z$3,-2) -> 7800 | G58: =ROUNDUP(+F58*$Z$3,-2) -> 8000 | H58: =ROUNDUP(+G58*$Z$3,-2) -> 8200 | I58: =ROUNDUP(+H58*$Z$3,-2) -> 8500 | J58: =ROUNDUP(+I58*$Z$3,-2) -> 8800 | K58: =ROUNDUP(+J58*$Z$3,-2) -> 9100 | L58: =ROUNDUP(+K58*$Z$3,-2) -> 9400 | N58: =+C58/$Z$5 -> 59.178082 | O58: =+D58/$Z$5 -> 60.821918 | P58: =+E58/$Z$5 -> 62.465753 | Q58: =+F58/$Z$5 -> 64.109589 | R58: =+G58/$Z$5 -> 65.753425 | S58: =+H58/$Z$5 -> 67.39726 | T58: =+I58/$Z$5 -> 69.863014 | U58: =+J58/$Z$5 -> 72.328767 | ... W58: =+L58/$Z$5 -> 77.260274
A59: Supplement to research administration TAP QGG | B59: QGG | C59: 3500 | D59: =ROUNDUP(+C59*$Z$3,-2) -> 3600 | E59: =ROUNDUP(+D59*$Z$3,-2) -> 3700 | F59: =ROUNDUP(+E59*$Z$3,-2) -> 3800 | G59: =ROUNDUP(+F59*$Z$3,-2) -> 3900 | H59: =ROUNDUP(+G59*$Z$3,-2) -> 4000 | I59: =ROUNDUP(+H59*$Z$3,-2) -> 4100 | J59: =ROUNDUP(+I59*$Z$3,-2) -> 4300 | K59: =ROUNDUP(+J59*$Z$3,-2) -> 4500 | L59: =ROUNDUP(+K59*$Z$3,-2) -> 4700 | N59: =+C59/$Z$5 -> 28.767123 | O59: =+D59/$Z$5 -> 29.589041 | P59: =+E59/$Z$5 -> 30.410959 | Q59: =+F59/$Z$5 -> 31.232877 | R59: =+G59/$Z$5 -> 32.054795 | S59: =+H59/$Z$5 -> 32.876712 | T59: =+I59/$Z$5 -> 33.69863 | U59: =+J59/$Z$5 -> 35.342466 | ... W59: =+L59/$Z$5 -> 38.630137
A60: Supplement to research administration TAP ANIVET | B60: ANIVET | C60: 3800 | D60: =ROUNDUP(+C60*$Z$3,-2) -> 3900 | E60: =ROUNDUP(+D60*$Z$3,-2) -> 4000 | F60: =ROUNDUP(+E60*$Z$3,-2) -> 4100 | G60: =ROUNDUP(+F60*$Z$3,-2) -> 4300 | H60: =ROUNDUP(+G60*$Z$3,-2) -> 4500 | I60: =ROUNDUP(+H60*$Z$3,-2) -> 4700 | J60: =ROUNDUP(+I60*$Z$3,-2) -> 4900 | K60: =ROUNDUP(+J60*$Z$3,-2) -> 5100 | L60: =ROUNDUP(+K60*$Z$3,-2) -> 5300 | N60: =+C60/$Z$5 -> 31.232877 | O60: =+D60/$Z$5 -> 32.054795 | P60: =+E60/$Z$5 -> 32.876712 | Q60: =+F60/$Z$5 -> 33.69863 | R60: =+G60/$Z$5 -> 35.342466 | S60: =+H60/$Z$5 -> 36.986301 | T60: =+I60/$Z$5 -> 38.630137 | U60: =+J60/$Z$5 -> 40.273973 | ... W60: =+L60/$Z$5 -> 43.561644
A61: Supplement to research administration TAP FOOD | B61: FOOD | C61: 3800 | D61: =ROUNDUP(+C61*$Z$3,-2) -> 3900 | E61: =ROUNDUP(+D61*$Z$3,-2) -> 4000 | F61: =ROUNDUP(+E61*$Z$3,-2) -> 4100 | G61: =ROUNDUP(+F61*$Z$3,-2) -> 4300 | H61: =ROUNDUP(+G61*$Z$3,-2) -> 4500 | I61: =ROUNDUP(+H61*$Z$3,-2) -> 4700 | J61: =ROUNDUP(+I61*$Z$3,-2) -> 4900 | K61: =ROUNDUP(+J61*$Z$3,-2) -> 5100 | L61: =ROUNDUP(+K61*$Z$3,-2) -> 5300 | N61: =+C61/$Z$5 -> 31.232877 | O61: =+D61/$Z$5 -> 32.054795 | P61: =+E61/$Z$5 -> 32.876712 | Q61: =+F61/$Z$5 -> 33.69863 | R61: =+G61/$Z$5 -> 35.342466 | S61: =+H61/$Z$5 -> 36.986301 | T61: =+I61/$Z$5 -> 38.630137 | U61: =+J61/$Z$5 -> 40.273973 | ... W61: =+L61/$Z$5 -> 43.561644
A62: Supplement to research administration TAP BCE | B62: BCE | C62: 4700 | D62: =ROUNDUP(+C62*$Z$3,-2) -> 4900 | E62: =ROUNDUP(+D62*$Z$3,-2) -> 5100 | F62: =ROUNDUP(+E62*$Z$3,-2) -> 5300 | G62: =ROUNDUP(+F62*$Z$3,-2) -> 5500 | H62: =ROUNDUP(+G62*$Z$3,-2) -> 5700 | I62: =ROUNDUP(+H62*$Z$3,-2) -> 5900 | J62: =ROUNDUP(+I62*$Z$3,-2) -> 6100 | K62: =ROUNDUP(+J62*$Z$3,-2) -> 6300 | L62: =ROUNDUP(+K62*$Z$3,-2) -> 6500 | N62: =+C62/$Z$5 -> 38.630137 | O62: =+D62/$Z$5 -> 40.273973 | P62: =+E62/$Z$5 -> 41.917808 | Q62: =+F62/$Z$5 -> 43.561644 | R62: =+G62/$Z$5 -> 45.205479 | S62: =+H62/$Z$5 -> 46.849315 | T62: =+I62/$Z$5 -> 48.493151 | U62: =+J62/$Z$5 -> 50.136986 | ... W62: =+L62/$Z$5 -> 53.424658
A63: Supplement to research administration TAP CAE | B63: CAE | C63: 0 | D63: =ROUNDUP(+C63*$Z$3,-2) -> 0 | E63: =ROUNDUP(+D63*$Z$3,-2) -> 0 | F63: =ROUNDUP(+E63*$Z$3,-2) -> 0 | G63: =ROUNDUP(+F63*$Z$3,-2) -> 0 | H63: =ROUNDUP(+G63*$Z$3,-2) -> 0 | I63: =ROUNDUP(+H63*$Z$3,-2) -> 0 | J63: =ROUNDUP(+I63*$Z$3,-2) -> 0 | K63: =ROUNDUP(+J63*$Z$3,-2) -> 0 | L63: =ROUNDUP(+K63*$Z$3,-2) -> 0 | N63: =+C63/$Z$5 -> 0 | O63: =+D63/$Z$5 -> 0 | P63: =+E63/$Z$5 -> 0 | Q63: =+F63/$Z$5 -> 0 | R63: =+G63/$Z$5 -> 0 | S63: =+H63/$Z$5 -> 0 | T63: =+I63/$Z$5 -> 0 | U63: =+J63/$Z$5 -> 0 | ... W63: =+L63/$Z$5 -> 0
A64: Supplement to research administration TAP DCA | B64: DCA | C64: 0 | D64: =ROUNDUP(+C64*$Z$3,-2) -> 0 | E64: =ROUNDUP(+D64*$Z$3,-2) -> 0 | F64: =ROUNDUP(+E64*$Z$3,-2) -> 0 | G64: =ROUNDUP(+F64*$Z$3,-2) -> 0 | H64: =ROUNDUP(+G64*$Z$3,-2) -> 0 | I64: =ROUNDUP(+H64*$Z$3,-2) -> 0 | J64: =ROUNDUP(+I64*$Z$3,-2) -> 0 | K64: =ROUNDUP(+J64*$Z$3,-2) -> 0 | L64: =ROUNDUP(+K64*$Z$3,-2) -> 0 | N64: =+C64/$Z$5 -> 0 | O64: =+D64/$Z$5 -> 0 | P64: =+E64/$Z$5 -> 0 | Q64: =+F64/$Z$5 -> 0 | R64: =+G64/$Z$5 -> 0 | S64: =+H64/$Z$5 -> 0 | T64: =+I64/$Z$5 -> 0 | U64: =+J64/$Z$5 -> 0 | ... W64: =+L64/$Z$5 -> 0
A65: Supplement to research administration TAP DCE | B65: DCE | C65: 0 | D65: =ROUNDUP(+C65*$Z$3,-2) -> 0 | E65: =ROUNDUP(+D65*$Z$3,-2) -> 0 | F65: =ROUNDUP(+E65*$Z$3,-2) -> 0 | G65: =ROUNDUP(+F65*$Z$3,-2) -> 0 | H65: =ROUNDUP(+G65*$Z$3,-2) -> 0 | I65: =ROUNDUP(+H65*$Z$3,-2) -> 0 | J65: =ROUNDUP(+I65*$Z$3,-2) -> 0 | K65: =ROUNDUP(+J65*$Z$3,-2) -> 0 | L65: =ROUNDUP(+K65*$Z$3,-2) -> 0 | N65: =+C65/$Z$5 -> 0 | O65: =+D65/$Z$5 -> 0 | P65: =+E65/$Z$5 -> 0 | Q65: =+F65/$Z$5 -> 0 | R65: =+G65/$Z$5 -> 0 | S65: =+H65/$Z$5 -> 0 | T65: =+I65/$Z$5 -> 0 | U65: =+J65/$Z$5 -> 0 | ... W65: =+L65/$Z$5 -> 0
A66: Supplement to research administration TAP ECE | B66: ECE | C66: 0 | D66: =ROUNDUP(+C66*$Z$3,-2) -> 0 | E66: =ROUNDUP(+D66*$Z$3,-2) -> 0 | F66: =ROUNDUP(+E66*$Z$3,-2) -> 0 | G66: =ROUNDUP(+F66*$Z$3,-2) -> 0 | H66: =ROUNDUP(+G66*$Z$3,-2) -> 0 | I66: =ROUNDUP(+H66*$Z$3,-2) -> 0 | J66: =ROUNDUP(+I66*$Z$3,-2) -> 0 | K66: =ROUNDUP(+J66*$Z$3,-2) -> 0 | L66: =ROUNDUP(+K66*$Z$3,-2) -> 0 | N66: =+C66/$Z$5 -> 0 | O66: =+D66/$Z$5 -> 0 | P66: =+E66/$Z$5 -> 0 | Q66: =+F66/$Z$5 -> 0 | R66: =+G66/$Z$5 -> 0 | S66: =+H66/$Z$5 -> 0 | T66: =+I66/$Z$5 -> 0 | U66: =+J66/$Z$5 -> 0 | ... W66: =+L66/$Z$5 -> 0
A67: Supplement to research administration TAP ECOS | B67: ECOS | C67: 0 | D67: =ROUNDUP(+C67*$Z$3,-2) -> 0 | E67: =ROUNDUP(+D67*$Z$3,-2) -> 0 | F67: =ROUNDUP(+E67*$Z$3,-2) -> 0 | G67: =ROUNDUP(+F67*$Z$3,-2) -> 0 | H67: =ROUNDUP(+G67*$Z$3,-2) -> 0 | I67: =ROUNDUP(+H67*$Z$3,-2) -> 0 | J67: =ROUNDUP(+I67*$Z$3,-2) -> 0 | K67: =ROUNDUP(+J67*$Z$3,-2) -> 0 | L67: =ROUNDUP(+K67*$Z$3,-2) -> 0 | N67: =+C67/$Z$5 -> 0 | O67: =+D67/$Z$5 -> 0 | P67: =+E67/$Z$5 -> 0 | Q67: =+F67/$Z$5 -> 0 | R67: =+G67/$Z$5 -> 0 | S67: =+H67/$Z$5 -> 0 | T67: =+I67/$Z$5 -> 0 | U67: =+J67/$Z$5 -> 0 | ... W67: =+L67/$Z$5 -> 0
A68: Supplement to research administration TAP ENVS | B68: ENVS | C68: 0 | D68: =ROUNDUP(+C68*$Z$3,-2) -> 0 | E68: =ROUNDUP(+D68*$Z$3,-2) -> 0 | F68: =ROUNDUP(+E68*$Z$3,-2) -> 0 | G68: =ROUNDUP(+F68*$Z$3,-2) -> 0 | H68: =ROUNDUP(+G68*$Z$3,-2) -> 0 | I68: =ROUNDUP(+H68*$Z$3,-2) -> 0 | J68: =ROUNDUP(+I68*$Z$3,-2) -> 0 | K68: =ROUNDUP(+J68*$Z$3,-2) -> 0 | L68: =ROUNDUP(+K68*$Z$3,-2) -> 0 | N68: =+C68/$Z$5 -> 0 | O68: =+D68/$Z$5 -> 0 | P68: =+E68/$Z$5 -> 0 | Q68: =+F68/$Z$5 -> 0 | R68: =+G68/$Z$5 -> 0 | S68: =+H68/$Z$5 -> 0 | T68: =+I68/$Z$5 -> 0 | U68: =+J68/$Z$5 -> 0 | ... W68: =+L68/$Z$5 -> 0
A69: Supplement to research administration TAP ICROFS | B69: ICROFS | C69: 0 | D69: =ROUNDUP(+C69*$Z$3,-2) -> 0 | E69: =ROUNDUP(+D69*$Z$3,-2) -> 0 | F69: =ROUNDUP(+E69*$Z$3,-2) -> 0 | G69: =ROUNDUP(+F69*$Z$3,-2) -> 0 | H69: =ROUNDUP(+G69*$Z$3,-2) -> 0 | I69: =ROUNDUP(+H69*$Z$3,-2) -> 0 | J69: =ROUNDUP(+I69*$Z$3,-2) -> 0 | K69: =ROUNDUP(+J69*$Z$3,-2) -> 0 | L69: =ROUNDUP(+K69*$Z$3,-2) -> 0 | N69: =+C69/$Z$5 -> 0 | O69: =+D69/$Z$5 -> 0 | P69: =+E69/$Z$5 -> 0 | Q69: =+F69/$Z$5 -> 0 | R69: =+G69/$Z$5 -> 0 | S69: =+H69/$Z$5 -> 0 | T69: =+I69/$Z$5 -> 0 | U69: =+J69/$Z$5 -> 0 | ... W69: =+L69/$Z$5 -> 0
A70: Supplement to research administration TAP MPE | B70: MPE | C70: 5100 | D70: =ROUNDUP(+C70*$Z$3,-2) -> 5300 | E70: =ROUNDUP(+D70*$Z$3,-2) -> 5500 | F70: =ROUNDUP(+E70*$Z$3,-2) -> 5700 | G70: =ROUNDUP(+F70*$Z$3,-2) -> 5900 | H70: =ROUNDUP(+G70*$Z$3,-2) -> 6100 | I70: =ROUNDUP(+H70*$Z$3,-2) -> 6300 | J70: =ROUNDUP(+I70*$Z$3,-2) -> 6500 | K70: =ROUNDUP(+J70*$Z$3,-2) -> 6700 | L70: =ROUNDUP(+K70*$Z$3,-2) -> 6900 | N70: =+C70/$Z$5 -> 41.917808 | O70: =+D70/$Z$5 -> 43.561644 | P70: =+E70/$Z$5 -> 45.205479 | Q70: =+F70/$Z$5 -> 46.849315 | R70: =+G70/$Z$5 -> 48.493151 | S70: =+H70/$Z$5 -> 50.136986 | T70: =+I70/$Z$5 -> 51.780822 | U70: =+J70/$Z$5 -> 53.424658 | ... W70: =+L70/$Z$5 -> 56.712329
A71: Supplement to research administration operations FOOD | B71: FOOD | C71: 4200 | D71: =ROUNDUP(+C71*$Z$4,-2) -> 4300 | E71: =ROUNDUP(+D71*$Z$4,-2) -> 4400 | F71: =ROUNDUP(+E71*$Z$4,-2) -> 4500 | G71: =ROUNDUP(+F71*$Z$4,-2) -> 4600 | H71: =ROUNDUP(+G71*$Z$4,-2) -> 4700 | I71: =ROUNDUP(+H71*$Z$4,-2) -> 4800 | J71: =ROUNDUP(+I71*$Z$4,-2) -> 4900 | K71: =ROUNDUP(+J71*$Z$4,-2) -> 5000 | L71: =ROUNDUP(+K71*$Z$4,-2) -> 5100
A72: Supplement to research administration operations ANIVET | B72: ANIVET | C72: 3600 | D72: =ROUNDUP(+C72*$Z$4,-2) -> 3700 | E72: =ROUNDUP(+D72*$Z$4,-2) -> 3800 | F72: =ROUNDUP(+E72*$Z$4,-2) -> 3900 | G72: =ROUNDUP(+F72*$Z$4,-2) -> 4000 | H72: =ROUNDUP(+G72*$Z$4,-2) -> 4100 | I72: =ROUNDUP(+H72*$Z$4,-2) -> 4200 | J72: =ROUNDUP(+I72*$Z$4,-2) -> 4300 | K72: =ROUNDUP(+J72*$Z$4,-2) -> 4400 | L72: =ROUNDUP(+K72*$Z$4,-2) -> 4500
A73: Supplement to research administration operations AGRO | B73: AGRO | C73: 6200 | D73: =ROUNDUP(+C73*$Z$4,-2) -> 6400 | E73: =ROUNDUP(+D73*$Z$4,-2) -> 6600 | F73: =ROUNDUP(+E73*$Z$4,-2) -> 6800 | G73: =ROUNDUP(+F73*$Z$4,-2) -> 7000 | H73: =ROUNDUP(+G73*$Z$4,-2) -> 7200 | I73: =ROUNDUP(+H73*$Z$4,-2) -> 7400 | J73: =ROUNDUP(+I73*$Z$4,-2) -> 7600 | K73: =ROUNDUP(+J73*$Z$4,-2) -> 7800 | L73: =ROUNDUP(+K73*$Z$4,-2) -> 8000
A74: Supplement to research administration operations QGG | B74: QGG | C74: 0 | D74: =ROUNDUP(+C74*$Z$4,-2) -> 0 | E74: =ROUNDUP(+D74*$Z$4,-2) -> 0 | F74: =ROUNDUP(+E74*$Z$4,-2) -> 0 | G74: =ROUNDUP(+F74*$Z$4,-2) -> 0 | H74: =ROUNDUP(+G74*$Z$4,-2) -> 0 | I74: =ROUNDUP(+H74*$Z$4,-2) -> 0 | J74: =ROUNDUP(+I74*$Z$4,-2) -> 0 | K74: =ROUNDUP(+J74*$Z$4,-2) -> 0 | L74: =ROUNDUP(+K74*$Z$4,-2) -> 0
A75: Supplement to research administration operations BCE | B75: BCE | C75: 0 | D75: =ROUNDUP(+C75*$Z$4,-2) -> 0 | E75: =ROUNDUP(+D75*$Z$4,-2) -> 0 | F75: =ROUNDUP(+E75*$Z$4,-2) -> 0 | G75: =ROUNDUP(+F75*$Z$4,-2) -> 0 | H75: =ROUNDUP(+G75*$Z$4,-2) -> 0 | I75: =ROUNDUP(+H75*$Z$4,-2) -> 0 | J75: =ROUNDUP(+I75*$Z$4,-2) -> 0 | K75: =ROUNDUP(+J75*$Z$4,-2) -> 0 | L75: =ROUNDUP(+K75*$Z$4,-2) -> 0
A76: Supplement to research administration operations CAE | B76: CAE | C76: 0 | D76: =ROUNDUP(+C76*$Z$4,-2) -> 0 | E76: =ROUNDUP(+D76*$Z$4,-2) -> 0 | F76: =ROUNDUP(+E76*$Z$4,-2) -> 0 | G76: =ROUNDUP(+F76*$Z$4,-2) -> 0 | H76: =ROUNDUP(+G76*$Z$4,-2) -> 0 | I76: =ROUNDUP(+H76*$Z$4,-2) -> 0 | J76: =ROUNDUP(+I76*$Z$4,-2) -> 0 | K76: =ROUNDUP(+J76*$Z$4,-2) -> 0 | L76: =ROUNDUP(+K76*$Z$4,-2) -> 0
A77: Supplement to research administration operations DCA | B77: DCA | C77: 0 | D77: =ROUNDUP(+C77*$Z$4,-2) -> 0 | E77: =ROUNDUP(+D77*$Z$4,-2) -> 0 | F77: =ROUNDUP(+E77*$Z$4,-2) -> 0 | G77: =ROUNDUP(+F77*$Z$4,-2) -> 0 | H77: =ROUNDUP(+G77*$Z$4,-2) -> 0 | I77: =ROUNDUP(+H77*$Z$4,-2) -> 0 | J77: =ROUNDUP(+I77*$Z$4,-2) -> 0 | K77: =ROUNDUP(+J77*$Z$4,-2) -> 0 | L77: =ROUNDUP(+K77*$Z$4,-2) -> 0
A78: Supplement to research administration operations DCE | B78: DCE | C78: 0 | D78: =ROUNDUP(+C78*$Z$4,-2) -> 0 | E78: =ROUNDUP(+D78*$Z$4,-2) -> 0 | F78: =ROUNDUP(+E78*$Z$4,-2) -> 0 | G78: =ROUNDUP(+F78*$Z$4,-2) -> 0 | H78: =ROUNDUP(+G78*$Z$4,-2) -> 0 | I78: =ROUNDUP(+H78*$Z$4,-2) -> 0 | J78: =ROUNDUP(+I78*$Z$4,-2) -> 0 | K78: =ROUNDUP(+J78*$Z$4,-2) -> 0 | L78: =ROUNDUP(+K78*$Z$4,-2) -> 0
A79: Supplement to research administration operations ECE | B79: ECE | C79: 0 | D79: =ROUNDUP(+C79*$Z$4,-2) -> 0 | E79: =ROUNDUP(+D79*$Z$4,-2) -> 0 | F79: =ROUNDUP(+E79*$Z$4,-2) -> 0 | G79: =ROUNDUP(+F79*$Z$4,-2) -> 0 | H79: =ROUNDUP(+G79*$Z$4,-2) -> 0 | I79: =ROUNDUP(+H79*$Z$4,-2) -> 0 | J79: =ROUNDUP(+I79*$Z$4,-2) -> 0 | K79: =ROUNDUP(+J79*$Z$4,-2) -> 0 | L79: =ROUNDUP(+K79*$Z$4,-2) -> 0
A80: Supplement to research administration operations ECOS | B80: ECOS | C80: 0 | D80: =ROUNDUP(+C80*$Z$4,-2) -> 0 | E80: =ROUNDUP(+D80*$Z$4,-2) -> 0 | F80: =ROUNDUP(+E80*$Z$4,-2) -> 0 | G80: =ROUNDUP(+F80*$Z$4,-2) -> 0 | H80: =ROUNDUP(+G80*$Z$4,-2) -> 0 | I80: =ROUNDUP(+H80*$Z$4,-2) -> 0 | J80: =ROUNDUP(+I80*$Z$4,-2) -> 0 | K80: =ROUNDUP(+J80*$Z$4,-2) -> 0 | L80: =ROUNDUP(+K80*$Z$4,-2) -> 0
A81: Supplement to research administration operations ENVS | B81: ENVS | C81: 0 | D81: =ROUNDUP(+C81*$Z$4,-2) -> 0 | E81: =ROUNDUP(+D81*$Z$4,-2) -> 0 | F81: =ROUNDUP(+E81*$Z$4,-2) -> 0 | G81: =ROUNDUP(+F81*$Z$4,-2) -> 0 | H81: =ROUNDUP(+G81*$Z$4,-2) -> 0 | I81: =ROUNDUP(+H81*$Z$4,-2) -> 0 | J81: =ROUNDUP(+I81*$Z$4,-2) -> 0 | K81: =ROUNDUP(+J81*$Z$4,-2) -> 0 | L81: =ROUNDUP(+K81*$Z$4,-2) -> 0
A82: Supplement to research administration operations ICROFS | B82: ICROFS | C82: 0 | D82: =ROUNDUP(+C82*$Z$4,-2) -> 0 | E82: =ROUNDUP(+D82*$Z$4,-2) -> 0 | F82: =ROUNDUP(+E82*$Z$4,-2) -> 0 | G82: =ROUNDUP(+F82*$Z$4,-2) -> 0 | H82: =ROUNDUP(+G82*$Z$4,-2) -> 0 | I82: =ROUNDUP(+H82*$Z$4,-2) -> 0 | J82: =ROUNDUP(+I82*$Z$4,-2) -> 0 | K82: =ROUNDUP(+J82*$Z$4,-2) -> 0 | L82: =ROUNDUP(+K82*$Z$4,-2) -> 0
A83: Supplement to research administration operations MPE | B83: MPE | C83: 0 | D83: =ROUNDUP(+C83*$Z$4,-2) -> 0 | E83: =ROUNDUP(+D83*$Z$4,-2) -> 0 | F83: =ROUNDUP(+E83*$Z$4,-2) -> 0 | G83: =ROUNDUP(+F83*$Z$4,-2) -> 0 | H83: =ROUNDUP(+G83*$Z$4,-2) -> 0 | I83: =ROUNDUP(+H83*$Z$4,-2) -> 0 | J83: =ROUNDUP(+I83*$Z$4,-2) -> 0 | K83: =ROUNDUP(+J83*$Z$4,-2) -> 0 | L83: =ROUNDUP(+K83*$Z$4,-2) -> 0
A84: Bench Fee | C84: 8000 | D84: =+C84 -> 8000 | E84: =+D84 -> 8000 | F84: =+E84 -> 8000 | G84: =+F84 -> 8000 | H84: =+G84 -> 8000 | I84: =+H84 -> 8000 | J84: =+I84 -> 8000 | K84: =+J84 -> 8000 | L84: =+K84 -> 8000
A85: Project supplement | C85: 257000 | D85: =+C85 -> 257000 | E85: =+D85 -> 257000 | F85: =+E85 -> 257000 | G85: =+F85 -> 257000 | H85: =+G85 -> 257000 | I85: =+H85 -> 257000 | J85: =+I85 -> 257000 | K85: =+J85 -> 257000 | L85: =+K85 -> 257000

Sheet GrantSource
A1: GrantSource | B1: GrantSourceExtra | C1: GrantSourceUdvidet
A2: 15. Juni Fonden | C2: 15. Juni Fonden ()
A3: A.J. Andersen og Hustrus Fond | C3: A.J. Andersen og Hustrus Fond ()
A4: A.P. Møller og Hustrus Fond | B4: A.P. Møller and Wife's Foundation | C4: A.P. Møller og Hustrus Fond (A.P. Møller and Wife's Foundation)
A5: ASC Utrecht University | C5: ASC Utrecht University ()
A6: AU strategiske midler | B6: Aarhus University strategic funds | C6: AU strategiske midler (Aarhus University strategic funds)
A7: Aage V. Jensen Naturfond | C7: Aage V. Jensen Naturfond ()
A8: Aage V. Jensens Fonde | C8: Aage V. Jensens Fonde ()
A9: Aage og Johanne Louis-Hansens Fond | C9: Aage og Johanne Louis-Hansens Fond ()
A10: Aarhus Institute of Advanced Studies | B10: AIAS | C10: Aarhus Institute of Advanced Studies (AIAS)
A11: Aarhus Kommune | C11: Aarhus Kommune ()
A12: Aarhus Universitet | B12: AU | C12: Aarhus Universitet (AU)
A13: Aarhus Universitets Forskningsfond | B13: Aarhus University Research Foundation, AUFF | C13: Aarhus Universitets Forskningsfond (Aarhus University Research Foundation, AUFF)
A14: Aarhus Universitetshospital | B14: Aarhus University Hospital | C14: Aarhus Universitetshospital (Aarhus University Hospital)
A15: Aase og Ejnar Danielsens Fond | C15: Aase og Ejnar Danielsens Fond ()
A16: Actinobac Biomed Inc. | C16: Actinobac Biomed Inc. ()
A17: Advanced Research Invention Agency | B17: ARIA | C17: Advanced Research Invention Agency (ARIA)
A18: Agouron Institute | C18: Agouron Institute ()
A19: Agria | C19: Agria ()
A20: Agro Business Park A/S | C20: Agro Business Park A/S ()
A21: AgroParisTech | C21: AgroParisTech ()
A22: Aktieselskabet Dampskibsselskabet Orients Fond | C22: Aktieselskabet Dampskibsselskabet Orients Fond ()
A23: Alexion Pharmaceuticals | C23: Alexion Pharmaceuticals ()
A24: AlgeCenter Danmark | C24: AlgeCenter Danmark ()
A25: Aliophtha A/S | C25: Aliophtha A/S ()
A26: Alzheimer's Association | C26: Alzheimer's Association ()
A27: Angely Yeast | C27: Angely Yeast ()
A28: Apple EMEIA Accounts payable | C28: Apple EMEIA Accounts payable ()
A29: Arcedi Biotech ApS | C29: Arcedi Biotech ApS ()
... A31: Arts & Humanities Research Council | C31: Arts & Humanities Research Council ()
A32: Arvid Nilssons Fond | B32: The Arvid Nilssons Foundation | C32: Arvid Nilssons Fond (The Arvid Nilssons Foundation)
A33: Augustinus Fonden | B33: The Augustinus Foundation | C33: Augustinus Fonden (The Augustinus Foundation)
A34: Autism Speaks | C34: Autism Speaks ()
A35: Axel Muusfeldts Fond | C35: Axel Muusfeldts Fond ()
A36: BASF A/S | C36: BASF A/S ()
A37: BETA.HEALTH - AUH | C37: BETA.HEALTH - AUH ()
A38: BONUS Science for a better | C38: BONUS Science for a better ()
A39: BRGM | C39: BRGM ()
A40: Bayer A/S | C40: Bayer A/S ()
A41: Bayer AB | C41: Bayer AB ()
A42: Bill and Melinda Gates Foundation | C42: Bill and Melinda Gates Foundation ()
A43: Biosolutions Zealand | C43: Biosolutions Zealand ()
A44: Bodil Pedersen Fonden | C44: Bodil Pedersen Fonden ()
A45: Brain&Behavior Research Found | C45: Brain&Behavior Research Found ()
A46: Brødrene Hartmanns fond | B46: The Brothers Hartmann's Foundation | C46: Brødrene Hartmanns fond (The Brothers Hartmann's Foundation)
A47: Børnecancerfonden | B47: Children's Cancer Foundation | C47: Børnecancerfonden (Children's Cancer Foundation)
A48: CGIAR | C48: CGIAR ()
A49: CIMO | C49: CIMO ()
A50: CNIEL | B50: Centre National Interprofessionnel de L’économie Laitière | C50: CNIEL (Centre National Interprofessionnel de L’économie Laitière)
A51: COWIfonden | B51: The COWI Foundation | C51: COWIfonden (The COWI Foundation)
A52: Cargill | C52: Cargill ()
A53: Carl og Ellen Hertz' legat til Dansk Læge- og Naturvidenskab | C53: Carl og Ellen Hertz' legat til Dansk Læge- og Naturvidenskab ()
A54: Carlsberg Laboratory | C54: Carlsberg Laboratory ()
A55: Carlsbergfondet | B55: The Carlsberg Foundation | C55: Carlsbergfondet (The Carlsberg Foundation)
A56: CenSec | C56: CenSec ()
A57: Choise Pharma | C57: Choise Pharma ()
A58: Civilingeniør Frode V. Nyegaard og Hustrus Fond | C58: Civilingeniør Frode V. Nyegaard og Hustrus Fond ()
A59: Civilstyrelsen | B59: Department of Civil Affairs | C59: Civilstyrelsen (Department of Civil Affairs)
A60: Clean air fund | C60: Clean air fund ()
A61: Climate Change AI | C61: Climate Change AI ()
A62: Cobb-Vantress Incorporated | C62: Cobb-Vantress Incorporated ()
A63: Coefficient Giving | C63: Coefficient Giving ()
A64: Colgate-Palmolive A/S | C64: Colgate-Palmolive A/S ()
A65: Collie Health Foundation | C65: Collie Health Foundation ()
A66: DARA | C66: DARA ()
A67: DERMADIS | C67: DERMADIS ()
A68: DIREC | B68: Digital Research Centre Denmark | C68: DIREC (Digital Research Centre Denmark)
A69: DLG Food Oil | C69: DLG Food Oil ()
A70: DONG A/S | C70: DONG A/S ()
A71: DOW AgroSciences | C71: DOW AgroSciences ()
A72: Dagmar Marshalls Fond | B72: The DAGMAR accordingly, Dr Marshall Fund | C72: Dagmar Marshalls Fond (The DAGMAR accordingly, Dr Marshall Fund)
A73: Danida | B73: Danish International Development Assistance | C73: Danida (Danish International Development Assistance)
A74: Danida Fellowship Centre | C74: Danida Fellowship Centre ()
A75: Danida Green Business Partnerships | B75: DGBP | C75: Danida Green Business Partnerships (DGBP)
A76: Danida Knowledge and Innovation Partnerships | C76: Danida Knowledge and Innovation Partnerships ()
A77: Danish 3R-Center | C77: Danish 3R-Center ()
A78: Danish Cardiovascular Academy | C78: Danish Cardiovascular Academy ()
A79: Danish Data Science Academy | C79: Danish Data Science Academy ()
A80: Danish Diabetes Academy | C80: Danish Diabetes Academy ()
A81: Danish e-infrastructure | C81: Danish e-infrastructure ()
A82: Danmarks Grundforskningsfond | B82: Danish National Research Foundation | C82: Danmarks Grundforskningsfond (Danish National Research Foundation)
A83: Danmarks Jægerforbund | B83: The Danish Hunters Association | C83: Danmarks Jægerforbund (The Danish Hunters Association)
A84: Danmarks Lungeforening | C84: Danmarks Lungeforening ()
A85: Danmarks Naturfredningsforening | C85: Danmarks Naturfredningsforening ()
A86: Danmarks Tekniske Universitet | B86: Technical University of Denmark | C86: Danmarks Tekniske Universitet (Technical University of Denmark)
A87: Dansk Akvakultur | B87: Danish Aquaculture | C87: Dansk Akvakultur (Danish Aquaculture)
A88: Dansk Center for Havforskning | C88: Dansk Center for Havforskning ()
A89: Dansk Energi Net | C89: Dansk Energi Net ()
A90: Dansk Gartneri | C90: Dansk Gartneri ()
A91: Dansk Hydraulisk Institut | B91: DHI | C91: Dansk Hydraulisk Institut (DHI)
A92: Dansk Kræftforskningsfond | C92: Dansk Kræftforskningsfond ()
A93: Danske Dyrlægers Forsikringsforening | C93: Danske Dyrlægers Forsikringsforening ()
A94: Danske Regioner | B94: Danish Regions | C94: Danske Regioner (Danish Regions)
A95: Den Danske Maritime Fond | C95: Den Danske Maritime Fond ()
A96: Den Grønlandske Fond | C96: Den Grønlandske Fond ()
A97: Dentosolve | C97: Dentosolve ()
A98: Det Obelske Familiefond | B98: The Obel Family Foundation | C98: Det Obelske Familiefond (The Obel Family Foundation)
A99: Det danske SDC-sekretariat | B99: The Danish SDC secretariat | C99: Det danske SDC-sekretariat (The Danish SDC secretariat)
A100: Diabetesforeningen | B100: The Danish Diabetes Association | C100: Diabetesforeningen (The Danish Diabetes Association)
A101: Diet4life ApS | C101: Diet4life ApS ()
...

Sheet Instrument
A1: GrantSource | B1: GrantSourcesExtra | C1: GrantSourceUdvidet | D1: Instrument
A2: Aarhus Kommune | C2: Aarhus Kommune ()
A3: Aarhus Universitet | B3: AU | C3: Aarhus Universitet (AU) | D3: AU Connect | F3: {=IFERROR(_xlfn.UNIQUE(_xlfn._xlws.FILTER(D:D,C:C='Cover letter'!C7)&_xlfn._xlws.FILTER(D:D,C:C='Cover letter ECE_MPE'!C7)),"")} | G3: <- denne formel bruges til at finde unikke instruments pba. valgt grant source i CL
A4: Aarhus Universitet | B4: AU | C4: Aarhus Universitet (AU) | D4: Bridge4Water
A5: Aarhus Universitet | B5: AU | C5: Aarhus Universitet (AU) | D5: CellFood
A6: Aarhus Universitet | B6: AU | C6: Aarhus Universitet (AU) | D6: CO2 Research Center, CORC
A7: Aarhus Universitet | B7: AU | C7: Aarhus Universitet (AU) | D7: Health-Tech Network Innovation Funding
A8: Danmarks Grundforskningsfond | B8: Danish National Research Foundation | C8: Danmarks Grundforskningsfond (Danish National Research Foundation) | D8: Centres of Excellence
A9: Danmarks Grundforskningsfond | B9: Danish National Research Foundation | C9: Danmarks Grundforskningsfond (Danish National Research Foundation) | D9: GROW
A10: Danmarks Grundforskningsfond | B10: Danish National Research Foundation | C10: Danmarks Grundforskningsfond (Danish National Research Foundation) | D10: Chair
A11: Forskningsrådet for Natur og Univers | B11: Danmarks Frie Forskningsråd, The Danish Research Council for Natural Sciences, DFF FNU | C11: Forskningsrådet for Natur og Univers (Danmarks Frie Forskningsråd, The Danish Research Council for Natural Sciences, DFF FNU) | D11: Danish ERC-programme
A12: Forskningsrådet for Natur og Univers | B12: Danmarks Frie Forskningsråd, The Danish Research Council for Natural Sciences, DFF FNU | C12: Forskningsrådet for Natur og Univers (Danmarks Frie Forskningsråd, The Danish Research Council for Natural Sciences, DFF FNU) | D12: Research projects 1
A13: Forskningsrådet for Natur og Univers | B13: Danmarks Frie Forskningsråd, The Danish Research Council for Natural Sciences, DFF FNU | C13: Forskningsrådet for Natur og Univers (Danmarks Frie Forskningsråd, The Danish Research Council for Natural Sciences, DFF FNU) | D13: Research projects 2
A14: Forskningsrådet for Natur og Univers | B14: Danmarks Frie Forskningsråd, The Danish Research Council for Natural Sciences, DFF FNU | C14: Forskningsrådet for Natur og Univers (Danmarks Frie Forskningsråd, The Danish Research Council for Natural Sciences, DFF FNU) | D14: Inge Lehmann
A15: Forskningsrådet for Natur og Univers | B15: Danmarks Frie Forskningsråd, The Danish Research Council for Natural Sciences, DFF FNU | C15: Forskningsrådet for Natur og Univers (Danmarks Frie Forskningsråd, The Danish Research Council for Natural Sciences, DFF FNU) | D15: International Postdoc
... A68: InnovationsFonden | B68: Innovation Fund Denmark | C68: InnovationsFonden (Innovation Fund Denmark) | D68: Innomission
A69: Civilstyrelsen | B69: Department of Civil Affairs | C69: Civilstyrelsen (Department of Civil Affairs)
A70: Danida | B70: Danish International Development Assistance | C70: Danida (Danish International Development Assistance)
A71: Danida Fellowship Centre | C71: Danida Fellowship Centre ()
A72: Danida Green Business Partnerships | B72: DGBP | C72: Danida Green Business Partnerships (DGBP)
A73: Danida Knowledge and Innovation Partnerships | C73: Danida Knowledge and Innovation Partnerships ()
A74: Danish Diabetes Academy | C74: Danish Diabetes Academy () | D74: PhD Scholarships
A75: Danish Diabetes Academy | C75: Danish Diabetes Academy () | D75: Postdoctoral Fellowships
A76: Danish Diabetes Academy | C76: Danish Diabetes Academy () | D76: Visiting Professorships
A77: Danish Diabetes Academy | C77: Danish Diabetes Academy () | D77: Workshops
A78: Danish e-infrastructure | C78: Danish e-infrastructure ()
A79: Dansk Center for Havforskning | C79: Dansk Center for Havforskning ()
A80: Planteafgiftsfonden | C80: Planteafgiftsfonden ()
A81: Danmarks Tekniske Universitet | B81: Technical University of Denmark | C81: Danmarks Tekniske Universitet (Technical University of Denmark)
A82: Danske Regioner | B82: Danish Regions | C82: Danske Regioner (Danish Regions)
A83: Det danske SDC-sekretariat | B83: The Danish SDC secretariat | C83: Det danske SDC-sekretariat (The Danish SDC secretariat)
A84: DIREC | B84: Digital Research Centre Denmark | C84: DIREC (Digital Research Centre Denmark)
A85: Energinet.dk | C85: Energinet.dk ()
A86: Energistyrelsen | B86: Danish Energy Agency | C86: Energistyrelsen (Danish Energy Agency)
A87: Erhvervsstyrelsen | B87: The Danish Business Authority | C87: Erhvervsstyrelsen (The Danish Business Authority)
A88: Erhvervsfremmestyrelsen | B88: the Danish Board of Business Development | C88: Erhvervsfremmestyrelsen (the Danish Board of Business Development) | D88: Biosolutions Zealand
A89: Erhvervsfremmestyrelsen | B89: the Danish Board of Business Development | C89: Erhvervsfremmestyrelsen (the Danish Board of Business Development) | D89: Food & Bio Cluster Denmark
A90: Erhvervsfremmestyrelsen | B90: the Danish Board of Business Development | C90: Erhvervsfremmestyrelsen (the Danish Board of Business Development) | D90: Klyngeprogram 2025-2028 Lifestyle and Design Cluster
A91: EUDP – Det Energiteknologiske Udviklings- og Demonstrationsprogram | B91: The EUDP secretariat | C91: EUDP – Det Energiteknologiske Udviklings- og Demonstrationsprogram (The EUDP secretariat)
A92: Fjerkræafgiftsfonden | B92: Danish Poultry Levy Fund | C92: Fjerkræafgiftsfonden (Danish Poultry Levy Fund)
A93: Fonden for Økologisk Landbrug | B93: The Danish Fund for Organic Farming | C93: Fonden for Økologisk Landbrug (The Danish Fund for Organic Farming)
A94: Frøafgiftsfonden | B94: Danish Seeds Levy Fund | C94: Frøafgiftsfonden (Danish Seeds Levy Fund)
A95: Fødevarestyrelsen | B95: Danish Veterinary and Food Administration | C95: Fødevarestyrelsen (Danish Veterinary and Food Administration) | D95: Videncenter for Dyrevelfærd
A96: GEUS | B96: Geological Survey of Denmark and Greenland | C96: GEUS (Geological Survey of Denmark and Greenland)
A97: GUDP | B97: Grønt Udviklings- og Demonstrationsprogram | C97: GUDP (Grønt Udviklings- og Demonstrationsprogram)
A98: Grønlands Naturinstitut | B98: The Greenland Institute of Natural Resources | C98: Grønlands Naturinstitut (The Greenland Institute of Natural Resources)
A99: Holbæk Kommune | C99: Holbæk Kommune ()
A100: It-Vest | C100: It-Vest ()
A101: Kartoffelafgiftsfonden | B101: Danish Potato Levy Fund | C101: Kartoffelafgiftsfonden (Danish Potato Levy Fund)
A102: Klima-, Energi- og Forsyningsministeriet | B102: Danish Ministry of Climate, Energy and Utilities | C102: Klima-, Energi- og Forsyningsministeriet (Danish Ministry of Climate, Energy and Utilities)
A103: Kulturarvsstyrelsen | B103: Agency for Culture and Palaces | C103: Kulturarvsstyrelsen (Agency for Culture and Palaces)
A104: Kvægafgiftsfonden | B104: Danish Cattle Levy Fund | C104: Kvægafgiftsfonden (Danish Cattle Levy Fund)
A105: Københavns Kommune | C105: Københavns Kommune ()
A106: Københavns Universitet | B106: University of Copenhagen | C106: Københavns Universitet (University of Copenhagen)
A107: Landbrug & Fødevarer | C107: Landbrug & Fødevarer () | D107: Brancheudvalget for Frø
A108: Landbrugs- og Fiskeristyrelsen | B108: The Danish Agrifish Agency | C108: Landbrugs- og Fiskeristyrelsen (The Danish Agrifish Agency) | D108: Plantefonden
A109: Landbrugs- og Fiskeristyrelsen | B109: The Danish Agrifish Agency | C109: Landbrugs- og Fiskeristyrelsen (The Danish Agrifish Agency) | D109: Grønt Program 2025
A110: Lyngby-Taarbæk Kommune | C110: Lyngby-Taarbæk Kommune ()
A111: Middelfart Kommune | C111: Middelfart Kommune ()
A112: Miljøfonden | B112: Avatangiisinut Aningaasaateqarfik | C112: Miljøfonden (Avatangiisinut Aningaasaateqarfik)
A113: Miljø- og Fødevareministeriet | B113: Ministry of Environment and Food of Denmark | C113: Miljø- og Fødevareministeriet (Ministry of Environment and Food of Denmark)
A114: Miljø- og Ligestillingsministeriet | B114: Ministry of Environment and Gender Equality of Denmark | C114: Miljø- og Ligestillingsministeriet (Ministry of Environment and Gender Equality of Denmark) | D114: Miljøteknologisk Udviklings- og Demonstrationsprogram
A115: Miljøstyrelsen | B115: Danish Environmental Protection Agency | C115: Miljøstyrelsen (Danish Environmental Protection Agency)
A116: Mælkeafgiftsfonden | B116: Danish Milk Levy Fund | C116: Mælkeafgiftsfonden (Danish Milk Levy Fund)
A117: Nationalt Center for Klimaforskning | B117: NCKF-DMI | C117: Nationalt Center for Klimaforskning (NCKF-DMI)
A118: Nationalt Forsvarsteknologisk Center | B118: National Defence Technology Centre (NFC) | C118: Nationalt Forsvarsteknologisk Center (National Defence Technology Centre (NFC))
A119: Naturstyrelsen | B119: National Forest and Nature Agency | C119: Naturstyrelsen (National Forest and Nature Agency)
A120: Nordfyns Kommune | C120: Nordfyns Kommune ()
A121: Odense Universitetshospital | B121: Odense University Hospital | C121: Odense Universitetshospital (Odense University Hospital)
A122: Pelsdyrafgiftsfonden | B122: Danish Fur Levy Fund | C122: Pelsdyrafgiftsfonden (Danish Fur Levy Fund)
A123: Plantefonden | B123: Fonden for plantebaserede fødevarer | C123: Plantefonden (Fonden for plantebaserede fødevarer)
A124: Promilleafgiftsfonden for landbrug | B124: Danish Promille Levy Fund | C124: Promilleafgiftsfonden for landbrug (Danish Promille Levy Fund)
A125: Region Midtjylland | B125: Central Denmark Region | C125: Region Midtjylland (Central Denmark Region) | D125: Research projects and research positions
A126: Region Midtjylland | B126: Central Denmark Region | C126: Region Midtjylland (Central Denmark Region) | D126: Brief scholarships
A127: Region Midtjylland | B127: Central Denmark Region | C127: Region Midtjylland (Central Denmark Region) | D127: Senior scholarships
A128: Region Midtjylland | B128: Central Denmark Region | C128: Region Midtjylland (Central Denmark Region) | D128: Pre-graduate scholarships
A129: Region Nordjylland | B129: The North Denmark Region | C129: Region Nordjylland (The North Denmark Region)
A130: Regionshospitalet Herning | B130: Herning Regional Hospital | C130: Regionshospitalet Herning (Herning Regional Hospital)
A131: Region Syddanmark | B131: The Region of Southern Denmark | C131: Region Syddanmark (The Region of Southern Denmark)
A132: Roskilde Kommune | C132: Roskilde Kommune ()
A133: Råstofdirektoratet | B133: The Bureau of Minerals | C133: Råstofdirektoratet (The Bureau of Minerals)
A134: Statens serum institut | B134: Statens Serum Institut | C134: Statens serum institut (Statens Serum Institut)
A135: Styrelsen for Grøn Arealomlægning og Vandmiljø | B135: SGAV | C135: Styrelsen for Grøn Arealomlægning og Vandmiljø (SGAV) | D135: Klimatiltagsprogrammet 2026-2029
A136: Styrelsen for Grøn Arealomlægning og Vandmiljø | B136: SGAV | C136: Styrelsen for Grøn Arealomlægning og Vandmiljø (SGAV) | D136: Klimatiltagsprogrammet 2027-2030
A137: Sukkerroeafgiftsfonden | C137: Sukkerroeafgiftsfonden ()
A138: Sundheds- og ældreministeriet | B138: Ministry of Health | C138: Sundheds- og ældreministeriet (Ministry of Health)
A139: Svineafgiftsfonden | B139: Danish Pig Levy Fund | C139: Svineafgiftsfonden (Danish Pig Levy Fund)
A140: Syddansk Universitet | B140: University of Southern Denmark | C140: Syddansk Universitet (University of Southern Denmark)
A141: Sygesikringen Danmark | C141: Sygesikringen Danmark ()
A142: Uddannelses- og Forskningsministeriet | B142: Ministry for Higher Education and Science | C142: Uddannelses- og Forskningsministeriet (Ministry for Higher Education and Science) | D142: EUopSTART
A143: Udenrigsministeriet | B143: Danish Ministry of Foreign Affairs of Denmark | C143: Udenrigsministeriet (Danish Ministry of Foreign Affairs of Denmark)
A144: Undervisningsministeriet | B144: Danish Ministry of Education | C144: Undervisningsministeriet (Danish Ministry of Education)
A145: Vejdirektoratet | C145: Vejdirektoratet ()
A146: Via University College | B146: Via University College | C146: Via University College (Via University College)
A147: Videreuddannelsregion Nord | C147: Videreuddannelsregion Nord ()
A148: Vækstforum Sjælland | B148: The Zealand Growth Forum | C148: Vækstforum Sjælland (The Zealand Growth Forum)
A149: Aarhus Universitetshospital | B149: Aarhus University Hospital | C149: Aarhus Universitetshospital (Aarhus University Hospital)
A150: Aarhus Universitets Forskningsfond | B150: Aarhus University Research Foundation, AUFF | C150: Aarhus Universitets Forskningsfond (Aarhus University Research Foundation, AUFF) | D150: Flagship
A151: Aarhus Universitets Forskningsfond | B151: Aarhus University Research Foundation, AUFF | C151: Aarhus Universitets Forskningsfond (Aarhus University Research Foundation, AUFF) | D151: Fleksible ph.d.-forløb
A152: Aarhus Universitets Forskningsfond | B152: Aarhus University Research Foundation, AUFF | C152: Aarhus Universitets Forskningsfond (Aarhus University Research Foundation, AUFF) | D152: Forskningsophold i Møllehuset og Husumgade
...

Sheet Section Cover letter ING
A1: Department | B1: Section
A2: CS | B2: ADA | E2: {=_xlfn.UNIQUE(_xlfn._xlws.FILTER(B:B,A:A='Cover letter ECE_MPE'!E5))} -> 0 | F2: <- denne formel bruges til at finde unikke sektioner pba. valgt institut i CL
A3: CS | B3: CRC
A4: CS | B4: HCC
A5: CS | B5: PLS
A6: MBG | B6: Protein Sciences
A7: MBG | B7: RNA Biology and Innovation
A8: MBG | B8: Plant Molecular Biology
A9: MBG | B9: Neurobiology
A10: MBG | B10: Molecular Health
A11: MBG | B11: BiRC
A12: QGG | B12: Admin
A13: QGG | B13: AgroBioDiversity
A14: QGG | B14: Animal
... A20: QGG | B20: Phenomics
A21: GEO
A22: BIO
A23: PHYS
A24: CHEM
A25: MATH
A26: INANO
A27: AGRO | B27: ABD
A28: AGRO | B28: CGB
A29: AGRO | B29: CROP
A30: AGRO | B30: JORD
A31: AGRO | B31: JORNÆR
A32: AGRO | B32: KLIMA
A33: AGRO | B33: Land-CRAFT
A34: AGRO | B34: PLANMIK
A35: AGRO | B35: SYSTEM
A36: AGRO | B36: STAB
A37: ENVS | B37: ATMI
A38: ENVS | B38: ATMO
... A47: ANIVET | B47: CAF
A48: FOOD
A49: ECOS | B49: WildEco
A50: ECOS | B50: MarMam
A51: ECOS | B51: ArcEnv
A52: ECOS | B52: BioCon
A53: ECOS | B53: CatchEnv
A54: ECOS | B54: TerEco
A55: ECOS | B55: MarEco
A56: ECOS | B56: AppMar
A57: ECOS | B57: LakeEco
A58: ECOS | B58: ArcEco
A59: ECOS | B59: MarDiv
A60: DCE
A61: DCA
A62: ICROFS
A63: BCE | B63: Air Quality and Emission Engineering
A64: BCE | B64: Bioprocess Engineering
A65: BCE | B65: Chemical Process Engineering
A66: BCE | B66: Energy Conversion Technology
A67: BCE | B67: Functional Materials
A68: BCE | B68: Molecular and Cellular Biotechnology
A69: BCE | B69: Partnerships and External Relations
A70: BCE | B70: Water Technology
A71: ECE | B71: Electronics and Photonics
A72: ECE | B72: Software Engineering and Computing Systems
A73: ECE | B73: Communication, Control and Automation
A74: ECE | B74: Signal Processing and Machine Learning
... A85: MPE | B85: INSTITUT

Sheet Section Cover letter
A1: Department | B1: Section
A2: CS | B2: ADA | E2: {=_xlfn.UNIQUE(_xlfn._xlws.FILTER(B:B,A:A='Cover letter'!E5))} -> 0 | F2: <- denne formel bruges til at finde unikke sektioner pba. valgt institut i CL
A3: CS | B3: CRC
A4: CS | B4: HCC
A5: CS | B5: PLS
A6: MBG | B6: Protein Sciences
A7: MBG | B7: RNA Biology and Innovation
A8: MBG | B8: Plant Molecular Biology
A9: MBG | B9: Neurobiology
A10: MBG | B10: Molecular Health
A11: MBG | B11: BiRC
A12: QGG | B12: Admin
A13: QGG | B13: AgroBioDiversity
A14: QGG | B14: Animal
... A20: QGG | B20: Phenomics
A21: GEO
A22: BIO
A23: PHYS
A24: CHEM
A25: MATH
A26: INANO
A27: AGRO | B27: ABD
A28: AGRO | B28: CGB
A29: AGRO | B29: CROP
A30: AGRO | B30: JORD
A31: AGRO | B31: JORNÆR
A32: AGRO | B32: KLIMA
A33: AGRO | B33: Land-CRAFT
A34: AGRO | B34: PLANMIK
A35: AGRO | B35: SYSTEM
A36: AGRO | B36: STAB
A37: ENVS | B37: ATMI
A38: ENVS | B38: ATMO
... A47: ANIVET | B47: CAF
A48: FOOD
A49: ECOS | B49: WildEco
A50: ECOS | B50: MarMam
A51: ECOS | B51: ArcEnv
A52: ECOS | B52: BioCon
A53: ECOS | B53: CatchEnv
A54: ECOS | B54: TerEco
A55: ECOS | B55: MarEco
A56: ECOS | B56: AppMar
A57: ECOS | B57: LakeEco
A58: ECOS | B58: ArcEco
A59: ECOS | B59: MarDiv
A60: DCE
A61: DCA
A62: ICROFS
A63: BCE | B63: Air Quality and Emission Engineering
A64: BCE | B64: Bioprocess Engineering
A65: BCE | B65: Chemical Process Engineering
A66: BCE | B66: Energy Conversion Technology
A67: BCE | B67: Functional Materials
A68: BCE | B68: Molecular and Cellular Biotechnology
A69: BCE | B69: Partnerships and External Relations
A70: BCE | B70: Water Technology
A71: ECE | B71: Electronics and Photonics
A72: ECE | B72: Software Engineering and Computing Systems
A73: ECE | B73: Communication, Control and Automation
A74: ECE | B74: Signal Processing and Machine Learning
... A85: MPE | B85: INSTITUT

Sheet Economists
A1: AUID | B1: Name
A2: au82350 | B2: Anne Cathrine Lund Petersen
A3: au783390 | B3: Adis Ramic
A4: au813887 | B4: Akbar Arian
A5: au223105 | B5: Alice Mørup
A6: au505985 | B6: Allan Bøge Ochwat
A7: au526752 | B7: Alexia Lessing
A8: au401197 | B8: Anette Holm Lundgren
A9: au401218 | B9: Allan Otto Wagner
A10: au247341 | B10: Anita Porsdal
A11: au512150 | B11: Astrid Hulgaard Jørgensen
A12: au236849 | B12: Britt Sønberg Vilstrup
... A83: au759774 | B83: Trine Rom Engholm

Sheet Lister
A1: Rullelister
A3: Institute | B3: Long name | D3: Overhead calculated on | F3: Yearly hours | G3: Description | I3: Supplement to research administration calculated by | K3: Currency | M3: Operations | O3: Project-supplement/Bench Fee
A4: AGRO | B4: Department of Agroecology | D4: Salary | F4: 1300 | I4: Salary | K4: DKK | M4: Choose type of operations | O4: Project-supplement
A5: ANIVET | B5: Department of Animal and Veterinary Sciences | D5: Salary and operations | F5: 1460 | G5: AU Standard (to be used unless other is stated) | I5: Operations | K5: EUR | M5: Misc. Operation/purchases/Consumables | O5: Bench Fee
A6: BCE | B6: Department of Biological and Chemical Engineering | D6: Salary and operations excl. External assistance/consultants | F6: 1485 | G6: EU | I6: Salary and operations | M6: Travel | O6: None
A7: CAE | B7: Department of Civil and Architectural Engineering | D7: Salary and operations excl. Procurements and External assistance/consultants | F7: 1642 | G7: GUDP | I7: None | M7: Procurements
A8: DCA | B8: Danish Centre for Food and Agriculture | D8: Salary, operations and Bench Fee | F8: 15xx | G8: Interreg | M8: Depreciations
A9: DCE | B9: Danish Centre for Environment and Energy | D9: Operations | F9: 1460 | G9: Grand Solutions | M9: Scrap-value
A10: ECE | B10: Department of Electrical and Computer Engineering | F10: 1642 | G10: NIFA | M10: External assistance/consultants
A11: ECOS | B11: Department of Ecoscience | M11: Ph.D. Tuition Fee
A12: ENVS | B12: Department of Environmental Science | M12: Analysis external
A13: FOOD | B13: Department of Food Science | M13: Analysis internal
A14: ICROFS | B14: International Centre for Research in Organic Food Systems | M14: Field operations, Research stations
A15: MPE | B15: Department of Mechanical and Production Engineering | M15: Livestock/stable operations
A16: QGG | B16: Center for Quantitative Genetics and Genomics | M16: Other
M17: Audit
I18: De 6 tabeller hænger sammen og må ikke sorteres enkeltvis
A19: Job functions | B19: Column1 | D19: Currency | F19: Rate | I19: Funder | K19: Yearly hours | M19: OH rate | O19: Project-supplement | Q19: OH calculation basis | S19: Technical ass calculation basis
A20: PhD - High Rate | B20: PhD | D20: DKK | F20: 1 | I20: 15. Juni Fonden | K20: 1460 | M20: 0 | O20: None | Q20: Salary and operations | S20: Salary and operations
A21: PhD - Avr. Rate | B21: PhD | D21: EUR | F21: 7.45 | I21: ARLA | K21: 1460 | M21: 20 | O21: None | Q21: Salary and operations | S21: Salary and operations
A22: Research Assistent - avr. Rate | D22: SEK | F22: 0.67 | I22: AUFF - Aarhus Universitets Forskningsfond | K22: 1460 | M22: 20 | O22: None | Q22: Salary and operations | S22: Salary and operations
A23: Research Assistent - low rate | D23: NOK | F23: 0.68 | I23: Carlsbergfondet | K23: 1460 | M23: 0 | O23: Project-supplement | Q23: None | S23: None
A24: TAP/Other masters degree | B24: TAP/Other Masters degree | D24: USD | F24: 7.02 | I24: Danida | K24: 1460 | M24: 44 | O24: None | Q24: Salary and operations excl. External assistance/consultants | S24: Salary and operations
A25: Laboratory technician - high rate | B25: Laboratory technician | D25: Optional currency | F25: 0 | I25: DFF - Danmarks Frie Forskningsfond | K25: 1460 | M25: 44 | O25: None | Q25: Salary and operations | S25: Salary and operations
A26: Laboratory technician - avr. rate | B26: Laboratory technician | I26: EDF - European Defence Fund | K26: 1460 | M26: 0 | O26: None
A27: Laboratory technician - low rate | B27: Laboratory technician | I27: EIT - European Institute of Innovation & Technology | K27: 1485 | M27: 25 | O27: None | Q27: Salary and operations
A28: Technician - high rate | B28: Technician | D28: Type of budget | I28: EUDP - Energistyrelsen | K28: 1642 | M28: 44 | O28: None | Q28: Salary and operations | S28: Salary and operations
A29: Technician - avr. rate | B29: Technician | D29: External funding | I29: FRØ - Frøafgiftsfonden | K29: 1460 | M29: 44 | O29: None | Q29: Salary and operations excl. External assistance/consultants | S29: Operations
A30: Technician - low rate | B30: Technician | D30: Coverage | I30: GUDP - Landbrugsstyrelsen | K30: 1642 | M30: 44 | O30: None | Q30: Salary and operations | S30: Salary and operations
A31: Post Doc. - low rate | D31: Co-financing covered by department | I31: Plantefonden | K31: 1642 | M31: 44 | O31: None | Q31: Salary and operations | S31: Salary and operations
A32: Post Doc. - high rate | D32: Co-financing covered by other external funding | I32: H2020 | K32: 1485 | M32: 25 | O32: None | Q32: Salary and operations
A33: Senior advisor - high rate | I33: Horizon Europe | K33: 1485 | M33: 25 | O33: None | Q33: Salary and operations
A34: Senior advisor - avr. rate | I34: IFD - Innovationsfonden | K34: 1460 | M34: 44 | O34: None | Q34: Salary and operations | S34: Salary and operations
A35: Post Doc abroad (Applicant, no project supplement) - high rate | I35: Klimastøtte - Energistyrelsen | K35: 1642 | M35: 44 | O35: None | Q35: Salary and operations | S35: Salary and operations
A36: Post Doc abroad (Applicant, no project supplement) - low rate | D36: Overheadsrate | I36: LEO Foundation | K36: 1460 | M36: 0 | O36: Project-supplement | Q36: None | S36: None
D37: 0 | I37: Lundbeck Fonden | K37: 1460 | M37: 0 | O37: Project-supplement | Q37: None | S37: None
D38: 5 | I38: MAF - Mælkeafgiftsfonden | K38: 1460 | M38: 44 | O38: None | Q38: Salary and operations excl. External assistance/consultants | S38: Operations
A39: GDPR Related | D39: 10 | I39: Miljøstøtte - Miljøstyrelsen | K39: 1460 | M39: 44 | O39: None | Q39: Salary and operations | S39: Salary and operations
A40: Yes | D40: 15 | I40: MUDP - Miljøstyrelsen | K40: 1642 | M40: 44 | O40: None | Q40: Salary | S40: Salary and operations
A41: No | D41: 20 | I41: NIFA - LBST | K41: 1642 | M41: 44 | O41: None | Q41: Salary and operations | S41: Salary and operations
D42: 25 | I42: NNF - Novo Nordisk Fonden | K42: 1460 | M42: 0 | O42: Project-supplement | Q42: None | S42: None
D43: 44 | I43: SAF - Svineafgiftsfonden | K43: 1460 | M43: 44 | O43: None | Q43: Salary and operations excl. External assistance/consultants | S43: Operations
A44: Supplement to research administration Operations | D44: 45 | F44: IV fra-dato | G44: Overhead | I44: Villum Fonden | K44: 1460 | M44: 0 | O44: Project-supplement | Q44: None | S44: None
A45: Laboratory technician | F45: 45292 | G45: 110 | I45: Velux Fonden | K45: 1460 | M45: 0 | O45: Project-supplement | Q45: None | S45: None
A46: Technician | F46: 46023 | G46: 105 | I46: Aage V. Jensen Fonden | K46: 1460 | M46: 25 | O46: None | Q46: Salary and operations | S46: Salary and operations
I47: Fonden for økologisk landbrug | K47: 1460 | M47: 44 | O47: None | Q47: Salary and operations excl. External assistance/consultants | S47: Operations
A48: IV | I48: Fjerkræafgiftsfonden | K48: 1460 | M48: 44 | O48: None | Q48: Salary and operations excl. External assistance/consultants | S48: Operations
I49: Hesteafgiftsfonden | K49: 1460 | M49: 44 | O49: None | Q49: Salary and operations excl. External assistance/consultants | S49: Operations
A50: 2 | I50: Kvægafgiftsfonden | K50: 1460 | M50: 44 | O50: None | Q50: Salary and operations excl. External assistance/consultants | S50: Operations
I51: Planteafgiftsfonden | K51: 1460 | M51: 44 | O51: None | Q51: Salary and operations excl. External assistance/consultants | S51: Operations
A52: EBIT | I52: Promilleafgiftsfonden | K52: 1460 | M52: 44 | O52: None | Q52: Salary and operations excl. External assistance/consultants | S52: Operations
A53: 10
A54: 3.6
A56: Projekttillæg Ja/Nej
A57: Yes
A58: No
A60: Laboratory Support Ja/Nej
A61: Yes
A62: No
A64: Time registration
A65: Yes
A66: No
A68: URIS Guideline
A69: Yes
A70: No

Sheet Guide
A1: Guide to "Internal Application Form"
A2: General
A3: Fill out your budget in B1-B5 | B3: Start by filling out your budget in the blue sheet 'B1'. If you need to enter more budgets - for example, because the project needs to be divided into WPs or there are multiple participants in the project, the next budgets can be entered in the blue sheets 'B2-B5'. If you need to budget beyond the 6 years, send the form to your FC/PC who will extend it by an additional 4 years. | C3: Start med at udfylde dit budget i det blå ark "B1". Har du brug for at indtaste flere budgetter - eks. fordi projektet skal deles op i WP eller I er flere deltagere i projektet kan de næste budgetter tastes de blå ark "B2-B5". Har du brug for at budgetlægge udover de 6 år så send skemaet til din FC/PC som vil udvide med ydereligere 4 år.
A4: Total budget | B4: You can see the total budget in the sheet "Total" which is a summation of "B1-B5" | C4: Du kan se det totale budget i arket "Total" som er en sammentælling af "B1-B5"
A5: Another valuta | B5: If you want your budget converted into another currency you can enter the currency in the sheet 'Total Other Currency' | C5: Hvis du ønsker dit budget omregnet i en anden valuta kan du taste valutaen i arket "Total Other Currency"
A6: PE | B6: The sheet 'PE' is used by the project controllers | C6: Arket "PE" anvendes af projektcontrollerne
A7: Add new grant source | B7: The sheet 'Add new grant source' is activated when you press the 'Add new' button in the Cover letters | C7: Arket "Add new grant source" aktiveres når man trykker på knappen "Add new" i Cover letteret.
A8: Cover Letter | B8: When you have completed your budget, you must fill out the current Cover Letter. It is up to the individual institute whether to use 'Cover Letter ECE' or 'Cover Letter | C8: Når du har udfyldt dit budget skal du udfylde det aktuelle Cover Letter. Det er op til det enkelte institut hvorvidt der benyttes "Cover Letter ECE" eller "Cover letter".
A9: Budget review | B9: Once you have completed the Cover Letter, send the application budget template to your business controller or project controller. They will check your budget according to the applicable guidelines for the grant provider and your department. Further approval of the budget and application must follow your department’s guidelines | C9: Når du er færdig med at udfylde Cover Letter sender du ansøgningsbudgetskabelonen til din forretningscontroller eller projektcontroller. De vil tjekke dit budget ifølge gældende retningslinjer for bevillingsgiver og dit institut. Ydereligere godkendelse af budget og ansøgning skal følge dit instituts retningslinjer
A10: Final application is sent to | B10: Once you have sent your application to the grant source you must send this along with the application budget template to the mailbox 'Nat-Tech Finance Application (nat-tech.finance.application@au.dk)' from where the application will be entered into ReAp and forwarded to your business controller/project controller | C10: Når du har sendt din ansøgning til bevillingsgiver skal du sende denne samt ansøgningsbudgetskabelonen til postkassen "Nat-Tech Finance Application (nat-tech.finance.application@au.dk)" hvorfra ansøgningen vil blive lagt i ReAp og videresendt til din forretningscontroller/projektcontroller
A11: Additional guidance | B11: For additional guidance, see the description of the individual fields below. You are also always welcome to ask the business controller or project controller | C11: For øvrig vejledning se beskrivelse af de enkelte felter nedenfor. Du er også altid velkommen til at spørge den forretningscontroller eller projektcontroller
A13: Description of the individual fields
A14: Field | B14: Description | C14: Beskrivelse
A15: Department | B15: A department must be selected from the list. It is possible to enter a department that is not on the list - in that case, the fields dependent on the department will be counted with value = 0 | C15: Der skal vælges et institut fra listen. Man kan godt skrive et institut, der ikke findes på listen - så vil de felter, der er afhængig af feltet blot regnes med værdi = 0.
A16: Projecttitle and acronym | B16: The project title must be filled in for the cover letter to be correctly completed | C16: Projekttitel skal udfyldes, så cover letter udfyldes korrekt.
A17: Grant holder | B17: The grant holder must be filled in for the cover letter to be correctly completed. | C17: Grant holder skal udfyldes, så cover letter udfyldes korrekt.
A18: Grant Source | B18: When a 'Grant Source' is selected from the list, information about the overhead rate and hourly standard is automatically filled in. If a 'Grant Source' not on the list is entered, you must fill in the fields correctly yourself. | C18: Når man vælger "Grant Source" fra listen, udfyldes oplysninger om overheadsats og timenorm. Hvis man skriver en "Grant Source", der ikke er på listen, skal man selv udfylde felterne korrekt. Oplysninger om overhead sats og timenorm kan findes i arket Lister.
A19: Insert overheads rate | B19: The field is automatically filled based on 'Grant Source'. You can overwrite the field with a different overhead rate or choose one from the list. However, note that if you overwrite or select another, the automatic correct filling function will be disabled. The calculation of overhead in the total budget depends on this field | C19: Feltet udfyldes automatisk pba "Grant Source". Man kan godt overskrive feltet med en anden overhead sats, eller man kan vælge en fra listen. Bemærk dog, at overskriver man eller vælger en anden, så forsvinder funktionen med at den automatisk udfyldes korrekt. Udregning af overhead i total budgettet er afhængigt af dette felt.
A20: Insert yearly count of hours | B20: The field is automatically filled based on 'Grant Source'. You can overwrite the field with a different number of hours or choose one from the list. However, note that if you overwrite or select another, the automatic correct filling function will be disabled. The field affects the calculation of Total hours | C20: Feltet udfyldes automatisk pba "Grant Source". Man kan godt overskrive feltet med et andet timetal, eller man kan vælge et fra listen. Bemærk dog, at overskriver man eller vælger et andet, så forsvinder funktionen med at den automatisk udfyldes korrekt. Feltet påvirker udregningen af Total hours
A21: Project supplement or Bench Fee | B21: The field is automatically filled with the project supplement based on 'Grant Source'. Novo Nordisk, Villum, Velux, Carlsberg, Lundbeck, and Leo provide project supplements. You can choose Bench fee from the list if the call indicates that a bench fee should be applied for instead of a project supplement. Note that if none of the foundations that provide project supplements or bench fees are selected, ensure that the field is filled with none | C21: Feltet udfyldes automatisk med projekttillæg pba "Grant Source". Det er Novo Nordisk, Villum, Velux, Carlsberg, Lundbeck og Leo der bevilliger projekttillæg. Man kan vælge Bench fee fra listen, hvis call'et angiver, at der skal søges om bench fee og ikke projekttillæg. Bemærk hvis der ikke er valgt en af de fonde, der giver projekttillæg eller bench fee, skal man sikre sig at feltet er udfyldt med none.
A22: Overhead calculation basis | B22: It is always pre-filled with Salary and operations. This has implications for which fields are used to calculate overhead. Currently, it is manually changed if it needs to be different. | C22: Er altid forudfyldt med Salary and operations. Har betydning for hvilke felter, der beregnes overhead af. Ændres p.t. manuelt hvis det skal være anderledes.
A23: Calculate tehcnical assis | B23: It is always pre-filled with Salary and operations. This affects whether supplements for technical assistance and lab rent, etc., are calculated. Currently, it is manually changed if it needs to be different | C23: Er altid forudfyldt med Salary and operations. Har betydning for om der beregnes tillæg til technical ass. and lab rent m.m. Ændres p.t. manuelt hvis det skal være anderledes.
A24: Is the project GDPR related | B24: The field is filled with yes or no. The information is used in the cover letter | C24: Feltet udfyldes med ja eller nej. Oplysningen bruges på cover letter.
A25: If Project Kind is Indtægtsdækket Virksomhed choose 2 | B25: If the project is a sub-account 2 project 'Commercial Activity', the field must be filled with the value 2, otherwise it should be left blank | C25: Hvis projektet er et delregnskab 2 projekt "Indtægtsdækket Virksomhed", skal feltet udfyldes med værdien 2, ellers skal den være blank.
... A41: Avg. hourly rate | B41: Total salary/total hours | C41: Total løn/total hours
A42: Total Cost
A43: - VIP-salary total | B43: The total sum of VIP salary | C43: Summen af VIP salary
A44: - TAP-salary total | B44: The total sum of TAP salary | C44: Summen af TAP salary
A45: - Operations total | B45: The total sum of operations | C45: Summen af operations
A46: - Overhead | B46: Overhead is calculated based on the choices made in 'Grant Source' + 'Insert overhead rate' + 'Overhead Calculation basis | C46: Overhead regnes pba de valg, der er foretaget i "Grant Source"+"Insert overhead rate"+"Overhead Calculation basis"
A47: - Bench fee | B47: Bench fee is calculated based on the choices made in 'Project supplement and Bench Fee'. A bench fee is calculated for all VIP months *8000 | C47: Bench fee regnes pba de valg, der er foretaget i "Project supplement and Bench Fee". Der beregnes bench fee af alle VIP-mdr. *8000
A48: - Project supplement | B48: Project supplement is calculated based on the choices made in 'Project supplement and Bench Fee'. Project supplements are given to Postdoc, PhD, and Research Assistant. Note: only from external funding and coverage. | C48: Project supplement regnes pba de valg, der er foretaget I "Project supplement and Bench Fee". Der gives projekt supplement til Postdoc, PhD og Research assistant. Bemærk kun af den eksterne finansiering og inddækning
A49: - EBIT | B49: EBIT is calculated based on the choices made in the 'EBIT' field | C49: EBIT regnes pba de valg, der er foretaget I feltet "EBIT"
A50: External funding (incl. coverage)
A51: - VIP-salary total | B51: The sum of VIP salary where 'external funding' or 'Coverage' is selected in the 'Type of budget | C51: Summen af VIP salary, hvor der I Type of budget er valgt external funding or Coverage
A52: - TAP-salary total | B52: The sum of TAP salary where 'external funding' or 'Coverage' is selected in the 'Type of budget | C52: Summen af TAP salary, hvor der I Type of budget er valgt external funding or Coverage
A53: - Operations total | B53: The sum of operations total where 'external funding' or 'Coverage' is selected in the 'Type of budget | C53: Summen af opreations total, hvor der I Type of budget er valgt external funding or Coverage
A54: - Overhead | B54: Overhead is calculated based on the choices made in 'Grant Source' + 'Insert overhead rate' + 'Overhead Calculation basis | C54: Overhead regnes pba de valg, der er foretaget i "Grant Source"+"Insert overhead rate"+"Overhead Calculation basis"
A55: - Bench fee | B55: Bench fee is calculated based on the choices made in 'Project supplement and Bench Fee'. A bench fee is calculated for all VIP months * 8000 | C55: Bench fee regnes pba de valg, der er foretaget i "Project supplement and Bench Fee". Der bergnes bench fee af alle VIP-mdr. *8000
A56: - Project supplement | B56: Project supplement is calculated based on the choices made in 'Project supplement and Bench Fee'. Project supplements are given to Postdoc, PhD, and Research Assistant. Note: only from external funding | C56: Project supplement regnes pba de valg, der er foretaget I "Project supplement and Bench Fee". Der gives projekt supplement til Postdoc, PhD og Research assistant. Bemærk kun af den eksterne finansiering
A57: - EBIT | B57: EBIT is calculated based on the choices made in the 'EBIT' field | C57: EBIT regnes pba de valg, der er foretaget I feltet "EBIT"
A58: Co-Financing(department and external)
A59: - VIP-salary total | B59: The sum of VIP salary where 'co-financing by department' or 'co-financing by external funding' is selected in the 'Type of budget' | C59: Summen af VIP salary, hvor der I Type of budget er valgt co-financing by department of co-financing by external funding
A60: - TAP-salary total | B60: The sum of TAP salary where 'co-financing by department' or 'co-financing by external funding' is selected in the 'Type of budget | C60: Summen af TAP salary, hvor der I Type of budget er valgt co-financing by department of co-financing by external funding
A61: - Operations total | B61: The sum of operations total where 'co-financing by department' or 'co-financing by external funding' is selected in the 'Type of budget | C61: Summen af opreations total, hvor der I Type of budget er valgt co-financing by department of co-financing by external funding
A62: - Overhead | B62: Overhead is calculated based on the choices made in 'Grant Source' + 'Insert overhead rate' + 'Overhead Calculation basis | C62: Overhead regnes pba de valg, der er foretaget i "Grant Source"+"Insert overhead rate"+"Overhead Calculation basis"
A63: - Bench fee | B63: Bench fee is calculated based on the choices made in 'Project supplement and Bench Fee'. A bench fee is calculated for all VIP months * 8000 | C63: Bench fee regnes pba de valg, der er foretaget i "Project supplement and Bench Fee". Der bergnes bench fee af alle VIP-mdr. *8000
A64: - Project supplement | B64: No project supplement is calculated from co-financing | C64: Der beregnes ikke project suppleent af co-financing
A65: - EBIT | B65: Co-financing is not allowed on revenue-funded activities, so EBIT is not calculated | C65: Der må ikke medfinansieres på indtægtsdækket virksomhed, så EBIT regnes ikke
A66: Coverage
A67: - VIP-salary total | B67: The sum of VIP salary where 'coverage' is selected in the 'Type of budget | C67: Summen af VIP salary, hvor der I Type of budget er valgt coverage
A68: - TAP-salary total | B68: The sum of TAP salary where 'coverage' is selected in the 'Type of budget | C68: Summen af TAP salary, hvor der I Type of budget er valgt coverage
A69: - Operations total | B69: The sum of operations total where 'coverage' is selected in the 'Type of budget | C69: Summen af opreations total, hvor der I Type of budget er valgt coverage
A70: - Overhead | B70: Overhead is calculated based on the choices made in 'Grant Source' + 'Insert overhead rate' + 'Overhead Calculation basis | C70: Overhead regnes pba de valg, der er foretaget i "Grant Source"+"Insert overhead rate"+"Overhead Calculation basis"
A71: - Bench fee | B71: Bench fee is calculated based on the choices made in 'Project supplement and Bench Fee'. A bench fee is calculated for all VIP months * 8000 | C71: Bench fee regnes pba de valg, der er foretaget i "Project supplement and Bench Fee". Der bergnes bench fee af alle VIP-mdr. *8000
A72: - Project supplement | B72: Project supplement is calculated based on the choices made in 'Project supplement and Bench Fee'. Project supplements are given to Postdoc, PhD, and Research Assistant. Note: only from external funding | C72: Project supplement regnes pba de valg, der er foretaget I "Project supplement and Bench Fee". Der gives projekt supplement til Postdoc, PhD og Research assistant. Bemærk kun af den eksterne finansiering
A73: - EBIT | B73: EBIT is calculated based on the choices made in the 'EBIT' field | C73: EBIT regnes pba de valg, der er foretaget I feltet "EBIT"
A74: Co-Financing from department
A75: - VIP-salary total | B75: The sum of VIP salary where 'co-financing by department' is selected in the 'Type of budget | C75: Summen af VIP salary, hvor der I Type of budget er valgt co-financing by department
A76: - TAP-salary total | B76: The sum of TAP salary where 'co-financing by department' is selected in the 'Type of budget | C76: Summen af TAP salary, hvor der I Type of budget er valgt co-financing by department
A77: - Operations total | B77: The sum of operations total where 'co-financing by department' is selected in the 'Type of budget | C77: Summen af opreations total, hvor der I Type of budget er valgt co-financing by department
A78: - Overhead | B78: Overhead is calculated based on the choices made in 'Grant Source' + 'Insert overhead rate' + 'Overhead Calculation basis | C78: Overhead regnes pba de valg, der er foretaget i "Grant Source"+"Insert overhead rate"+"Overhead Calculation basis"
A79: - Bench fee | B79: Bench fee is calculated based on the choices made in 'Project supplement and Bench Fee'. A bench fee is calculated for all VIP months * 8000 | C79: Bench fee regnes pba de valg, der er foretaget i "Project supplement and Bench Fee". Der bergnes bench fee af alle VIP-mdr. *8000
A80: - Project supplement | B80: No project supplement is calculated from co-financing | C80: Der beregnes ikke project suppleent af co-financing
A81: - EBIT | B81: Co-financing is not allowed on revenue-funded activities, so EBIT is not calculated. | C81: Der må ikke medfinansieres på indtægtsdækket virksomhed, så EBIT regnes ikke
A82: Cover Letter
A83: Applicant name | B83: Retrieved from B1 | C83: Hentes fra B1
A84: Department | B84: Retrieved from B1 | C84: Hentes fra B1
A85: Section | B85: The rolling list is retrieved from ReAp. If there are missing fields in the list, they should be added to the list in ReAp | C85: Rulleliste hentes fra ReAp. Hvis der mangler felter på listen, skal den tilføjes listen i ReAp.
A86: AU-ID | B86: Entered Manually | C86: Tastes
A87: Projecttitle and acronym | B87: Retrieved from B1 | C87: Hentes fra B1
A88: Grant Source | B88: The rolling list from ReAp. If there are missing fields in the list, they should be added to ReAp | C88: Rullelisten fra ReAp. Hvis der mangler felter på listen, skal den tilføjes ReAp.
A89: Instrument | B89: The rolling list from ReAp. If there are missing fields in the list, they should be added to ReAp | C89: Rulleliste hentes fra ReAp. Hvis der mangler felter på listen, skal den tilføjes ReAp
A90: GDPR-related | B90: Retrieved from B1 | C90: Hentes fra B1
A91: Are the URIS guidelines being followed? | B91: Is there involvement in the project from a country (as of 01.01.2025 Russia, China, Iran, Saudi Arabia, Turkey, Armenia, Azerbaijan, Georgia, Kazakhstan, USA...) that constitutes a threat (e.g. espionage) to Denmark according to the guidelines from URIS (Committee on Guidelines for International Research and Innovation Collaboration): https://pet.dk/en/-/media/mediefiler/pet/dokumenter/analyser-og-vurderinger/vurdering-af-spionagetruslen-mod-danmark/vurdering-af-spionagetruslen-mod-danmark-2023_uk_web.pdf | C91: Er der i projektet involvering fra et land (pr. 01.01.2025 Rusland, Kina, Iran, Saudi-Arabien, Tyrkiet, Armenien, Azerbaijan, Georgien, Kasakhstan, USA...) der udgør en trussel (eks. Spionage) mod Danmark ifølge retningslinjerne fra URIS (Udvalg om retningslinjer for internationalt forsknings- og innovationssamarbejde) : https://pet.dk/en/-/media/mediefiler/pet/dokumenter/analyser-og-vurderinger/vurdering-af-spionagetruslen-mod-danmark/vurdering-af-spionagetruslen-mod-danmark-2023_uk_web.pdf
A92: Special remarks to budget | B92: If there are any comments on the budget that you would like the head of the department to consider, they should be written here. The comment will be transferred to the note field in ReAp | C92: Hvis man evt. Har kommentarer til budgettet, som man ønsker institutleder skal forholde sig til, så skrives de her. Kommentaren overføres til note feltet i ReAp
A93: Applied amount total incl. partners and overheadq | B93: The grant holder must indicate the total amount requested from the grant provider. It should only be the external funding but for all partners | C93: Bevillingshaver skal angive det totale beløb, der søges af bevillingsgiver. Det skal kun være den eksterne finansiering, men for alle partnere.
A94: Total budget to the dept | B94: Sum of the total budget including co-financing of the B, where the same department as in B1 is selected | C94: Sum af total budget incl. medfinansering af de B, hvor der er valgt samme institut som I B1
... A110: Cost Coverage Ratio (Project Level) | B110: This indicator includes both the coverage for permanent VIP/TAP staff and co-financing for permanent VIP/TAP staff Formlen: (Overhead/Projectsupplement/BenchFee+Cost Coverage Salary+Cost Coverage Others+PhDtuitionFee to department-Dept. co-financing others-Cofinancing of the difference in hours-Depreciation covered by dept...)/Applied amount to the dept. incl. overhead | C110: This indicator includes both the coverage for permanent VIP/TAP staff and co-financing for permanent VIP/TAP staff Formlen: (Overhead/Projectsupplement/BenchFee+Cost Coverage Salary+Cost Coverage Others+PhDtuitionFee to department-Dept. co-financing others-Cofinancing of the difference in hours-Depreciation covered by dept...)/Applied amount to the dept. incl. overhead
A113: Andet
A114: Kostpriser | B114: "AU's cost prices are used. As a starting point, 1 cost price per job category is used. Where it makes sense, 2 are used. As a starting point, the average rate and the high rate are used. But they are always compared to TECH's current calculated average rates, and where it makes sense, e.g., low and average rates can be used. Rates are updated once a year when they are received from AU Accounting (during March) | C114: Der anvendes AU's kostpriser. Der anvendes som udgangspkt. 1 kostpris pr. Stillingskategori. Hvor det giver mening anvendes der 2. Som udgangspkt. anvendes gennemsnitssatsen og den høje satsen. Men der samlignes altid til TECH's aktuelle beregnede gennemsnitssatser og hvor det giver mening kan eks anvendes lav og gennemsnitssats. Satserne ajourføres 1 gang om året når de modtages fra AU Regnskab(i løbet af marts måned)

Sheet Cover letter ECE_MPE
B2: Cover letter for management for externally funded projects The green fields are to be filled in by the grant holder The grey fields retrieve information from the WPs that have the same department as in E5
B3: ReAp control | D3: =IFERROR(IF(AND(I5<>"", OR(C7<>"", LEN(TRIM(J7))>0), G5<>"", C9<>0, C12<>0, C13<>"", F12<>0, F13<>"", D20<>"", D22<>0, H35<>""), "✅ ReAp fields are completed", "❌ ReAp fields are missing data – Please fill in the yellow cells"), "❌ ReAp fields are missing data – Please fill in the yellow cells") -> ❌ ReAp fields are missing data – Please fill in the yellow cells
B5: Applicant name | C5: =+'B1'!C4 -> 0 | D5: Department | E5: =+'B1'!C2 -> 0 | F5: Section | H5: AUID | K5: =IF(OR('Cover letter'!I5>0,LEN(I5)<3),1,0) -> 1
B6: Projecttitle and acronym | C6: =+'B1'!C3 -> 0
B7: Grant source | J7: {=IF(IF(IF(C7="",Tabel21[Grant source])=0,"",IF(C7="",Tabel21[Grant source]))=FALSE,"",IF(IF(C7="",Tabel21[Grant source])=0,"",IF(C7="",Tabel21[Grant source])))} | K7: =IF(ISBLANK(C7),J7,_xlfn.XLOOKUP(C7,GrantSource!C:C,GrantSource!A:A))
B8: Instrument | J8: {=IF(IF(IF(C8="",Tabel21[Instrument])=0,"",IF(C8="",Tabel21[Instrument]))=FALSE,"",IF(IF(C8="",Tabel21[Instrument])=0,"",IF(C8="",Tabel21[Instrument])))} | K8: =IF(ISBLANK(C8),J8,C8)
B9: GDPR-related | C9: =+'B1'!H8 -> 0 | D9: Is there involvement from a country that poses a threat to Denmark according to URIS guidelines? | G9: Specify country:
B10: Participants from the dept.
B11: Is Applicant main coordinator of the project | D11: If no, please type the name of the coordinator
B12: Project start (dd.mm.yyyy) | C12: =+'B1'!C9 -> 0 | D12: Project end (dd.mm.yyyy) | F12: =+'B1'!H9 -> 0
B13: Deadline for application (dd-mm-yyyy) | D13: Next update expected (dd-mm-yyyy)
B14: Short project description
B15: Partners within AU(name and dept.)
B16: Partners outside AU
B17: Planned new recruitment of named scientific staff (CV enclosed)
B18: BUDGET
B19: Special remarks to budget
B20: Applied amount total incl. partners and overhead
B21: Total budget to the dept. (incl. co-financing) | D21: =+IF('B1'!C2='Cover letter ECE_MPE'!E5,'B1'!AC73,0)+IF('B2'!C2='Cover letter ECE_MPE'!E5,'B2'!AC73,0)+IF('B3'!C2='Cover letter ECE_MPE'!E5,'B3'!AC73,0)+IF('B4'!C2='Cover letter ECE_MPE'!E5,'B4'!AC73,0)+IF('B5'!C2='Cover letter ECE_MPE'!E5,'B5'!AC73,0) -> 0
B22: Applied amount to the dept. incl. overhead | D22: =+IF(E5='B1'!C2,'B1'!AC89,0)+IF(E5='B2'!C2,'B2'!AC89,0)+IF(E5='B3'!C2,'B3'!AC89,0)+IF(E5='B4'!C2,'B4'!AC89,0)+IF(E5='B5'!C2,'B5'!AC89,0) -> 0
B23: Overhead/project supplement/BenchFee/EBIT | D23: =+IF(E5='B1'!C2,SUM('B1'!AC85:AC88),0)+IF(E5='B2'!C2,SUM('B2'!AC85:AC88),0)+IF(E5='B3'!C2,SUM('B3'!AC85:AC88),0)+IF(E5='B4'!C2,SUM('B4'!AC85:AC88),0)+IF(E5='B5'!C2,SUM('B5'!AC85:AC88),0) -> 0
B24: Cost Coverage salary | D24: =+IF('B1'!C2='Cover letter ECE_MPE'!E5,SUMIF('B1'!O20:O55,Lister!D30,'B1'!AC20:AC56),0)+IF('B2'!C2='Cover letter ECE_MPE'!E5,SUMIF('B2'!O20:O55,Lister!D30,'B2'!AC20:AC56),0)+IF('B3'!C2='Cover letter ECE_MPE'!E5,SUMIF('B3'!O20:O55,Lister!D30,'B3'!AC20:AC56),0)+IF('B4'!C2='Cover letter ECE_MPE'!E5,SUMIF('B4'!O20:O55,Lister!D30,'B4'!AC20:AC56),0)+IF('B5'!C2='Cover letter ECE_MPE'!E5,SUMIF('B5'!O20:O55,Lister!D30,'B5'!AC20:AC56),0) -> 0
B25: Cost Coverage others | D25: =(IF('B1'!C2='Cover letter ECE_MPE'!E5,SUMIF('B1'!O62:O74,Lister!D30,'B1'!M62:M74),0)+IF('B2'!C2='Cover letter ECE_MPE'!E5,SUMIF('B2'!O62:O74,Lister!D30,'B2'!M62:M74),0)+IF('B3'!C2='Cover letter ECE_MPE'!E5,SUMIF('B3'!O62:O74,Lister!D30,'B3'!M62:M74),0)+IF('B4'!C2='Cover letter ECE_MPE'!E5,SUMIF('B4'!O62:O74,Lister!D30,'B4'!M62:M74),0)+IF('B5'!C2='Cover letter ECE_MPE'!E5,SUMIF('B5'!O62:O74,Lister!D30,'B5'!M62:M74),0)) -> 0
B26: Department co-financing salary | D26: =+IF('B1'!C2='Cover letter ECE_MPE'!E5,SUMIF('B1'!O20:O55,Lister!D31,'B1'!AC20:AC56),0)+IF('B2'!C2='Cover letter ECE_MPE'!E5,SUMIF('B2'!O20:O55,Lister!D31,'B2'!AC20:AC56),0)+IF('B3'!C2='Cover letter ECE_MPE'!E5,SUMIF('B3'!O20:O55,Lister!D31,'B3'!AC20:AC56),0)+IF('B4'!C2='Cover letter ECE_MPE'!E5,SUMIF('B4'!O20:O55,Lister!D31,'B4'!AC20:AC56),0)+IF('B5'!C2='Cover letter ECE_MPE'!E5,SUMIF('B5'!O20:O55,Lister!D31,'B5'!AC20:AC56),0) -> 0 | F26: Department co-financing | G26: =+(D26+D27)/D21 -> #DIV/0!
B27: Department co-financing others | D27: =+IF('B1'!C2='Cover letter ECE_MPE'!E5,SUMIF('B1'!O62:O74,Lister!D31,'B1'!M62:M74),0)+IF('B2'!C2='Cover letter ECE_MPE'!E5,SUMIF('B2'!O62:O74,Lister!D31,'B2'!M62:M74),0)+IF('B3'!C2='Cover letter ECE_MPE'!E5,SUMIF('B3'!O62:O74,Lister!D31,'B3'!M62:M74),0)+IF('B4'!C2='Cover letter ECE_MPE'!E5,SUMIF('B4'!O62:O74,Lister!D31,'B4'!M62:M74),0)+IF('B5'!C2='Cover letter ECE_MPE'!E5,SUMIF('B5'!O62:O74,Lister!D31,'B5'!M62:M74),0) -> 0
B28: Co-financing external funded | D28: =+IF('B1'!C2='Cover letter ECE_MPE'!E5,SUMIF('B1'!O20:O55,Lister!D32,'B1'!AC20:AC56),0)+IF('B2'!C2='Cover letter ECE_MPE'!E5,SUMIF('B2'!O20:O55,Lister!D32,'B2'!AC20:AC56),0)+IF('B3'!C2='Cover letter ECE_MPE'!E5,SUMIF('B3'!O20:O55,Lister!D32,'B3'!AC20:AC56),0)+IF('B4'!C2='Cover letter ECE_MPE'!E5,SUMIF('B4'!O20:O55,Lister!D32,'B4'!AC20:AC56),0)+IF('B5'!C2='Cover letter ECE_MPE'!E5,SUMIF('B5'!O20:O55,Lister!D32,'B5'!AC20:AC56),0)+IF('B1'!C2='Cover letter ECE_MPE'!E5,SUMIF('B1'!O62:O74,Lister!D32,'B1'!M62:M74),0)+IF('B2'!C2='Cover letter ECE_MPE'!E5,SUMIF('B2'!O62:O74,Lister!D32,'B2'!M62:M74),0)+IF('B3'!C2='Cover letter ECE_MPE'!E5,SUMIF('B3'!O62:O74,Lister!D32,'B3'!M62:M74),0)+IF('B4'!C2='Cover letter ECE_MPE'!E5,SUMIF('B4'!O62:O74,Lister!D32,'B4'!M62:M74),0)+IF('B5'!C2='Cover letter ECE_MPE'!E5,SUMIF('B5'!O62:O74,Lister!D32,'B5'!M62:M74),0) -> 0 | F28: Source of co-financing (name projects)
B29: PhD Tuition Fee share to dept. | D29: =IF('B1'!C2=E5,(SUMIFS('B1'!M62:M72,'B1'!A62:A72,Lister!M11,'B1'!O62:O72,Lister!D29)+SUMIFS('B1'!M62:M72,'B1'!A62:A72,Lister!M11,'B1'!O62:O72,Lister!D30))-((SUMIF('B1'!A20:A29,Lister!A20,'B1'!M20:M29)+SUMIF('B1'!A20:A29,Lister!A21,'B1'!M20:M29))/12*30000),0)+IF('B2'!C2=E5,(SUMIFS('B2'!M62:M72,'B2'!A62:A72,Lister!M11,'B2'!O62:O72,Lister!D29)+SUMIFS('B2'!M62:M72,'B2'!A62:A72,Lister!M11,'B2'!O62:O72,Lister!D30))-((SUMIF('B2'!A20:A29,Lister!A20,'B2'!M20:M29)+SUMIF('B2'!A20:A29,Lister!A21,'B2'!M20:M29))/12*30000),0)+IF('B3'!C2=E5,(SUMIFS('B3'!M62:M72,'B3'!A62:A72,Lister!M11,'B3'!O62:O72,Lister!D29)+SUMIFS('B3'!M62:M72,'B3'!A62:A72,Lister!M11,'B3'!O62:O72,Lister!D30))-((SUMIF('B3'!A20:A29,Lister!A20,'B3'!M20:M29)+SUMIF('B3'!A20:A29,Lister!A21,'B3'!M20:M29))/12*30000),0)*IF('B4'!C2=E5,(SUMIFS('B4'!M62:M72,'B4'!A62:A72,Lister!M11,'B4'!O62:O72,Lister!D29)+SUMIFS('B4'!M62:M72,'B1'!A62:A72,Lister!M11,'B4'!O62:O72,Lister!D30))-((SUMIF('B4'!A20:A29,Lister!A20,'B4'!M20:M29)+SUMIF('B4'!A20:A29,Lister!A21,'B4'!M20:M29))/12*30000),0)+IF('B5'!C2=E5,(SUMIFS('B5'!M62:M72,'B5'!A62:A72,Lister!M11,'B5'!O62:O72,Lister!D29)+SUMIFS('B5'!M62:M72,'B5'!A62:A72,Lister!M11,'B5'!O62:O72,Lister!D30))-((SUMIF('B5'!A20:A29,Lister!A20,'B5'!M20:M29)+SUMIF('B5'!A20:A29,Lister!A21,'B5'!M20:M29))/12*30000),0) -> 0
B30: Procurement external funding | D30: =SUMIFS('B1'!M62:M72,'B1'!A62:A72,Lister!M7,'B1'!O62:O72,Lister!D29)+SUMIFS('B2'!M62:M72,'B2'!A62:A72,Lister!M7,'B2'!O62:O72,Lister!D29)+SUMIFS('B3'!M62:M72,'B3'!A62:A72,Lister!M7,'B3'!O62:O72,Lister!D29)+SUMIFS('B4'!M62:M72,'B4'!A62:A72,Lister!M7,'B4'!O62:O72,Lister!D29)+SUMIFS('B5'!M62:M72,'B5'!A62:A72,Lister!M7,'B5'!O62:O72,Lister!D29) -> 0 | F30: Depreciation covered by dept. due to exp. of project period | G30: =+ABS(SUMIF('B1'!A62:A72,Lister!M9,'B1'!M62:M72))+ABS(SUMIF('B2'!A62:A72,Lister!M9,'B2'!M62:M72))+ABS(SUMIF('B3'!A62:A72,Lister!M9,'B3'!M62:M72))+ABS(SUMIF('B4'!A62:A72,Lister!M9,'B4'!M62:M72))+ABS(SUMIF('B5'!A62:A72,Lister!M9,'B5'!M62:M72)) -> 0 | H30: Cost Coverage depreciation | I30: =SUMIFS('B1'!M62:M72,'B1'!A62:A72,Lister!M8,'B1'!O62:O72,Lister!D30)+SUMIFS('B2'!M62:M72,'B2'!A62:A72,Lister!M8,'B2'!O62:O72,Lister!D30)+SUMIFS('B3'!M62:M72,'B3'!A62:A72,Lister!M8,'B3'!O62:O72,Lister!D30)+SUMIFS('B4'!M62:M72,'B4'!A62:A72,Lister!M8,'B4'!O62:O72,Lister!D30)+SUMIFS('B5'!M62:M72,'B5'!A62:A72,Lister!M8,'B5'!O62:O72,Lister!D30) -> 0
B31: Experiements(Fields, Barn, Workshops)- budget cleared with manager (Yes/No)
B32: Core Project Ratio This indicator focuses solely on the project's core budget | D32: =+(D23+D29-D26-D27-G30)/D22 -> #DIV/0!
B33: Cost Coverage Ratio (Department Level) This indicator includes both the coverage for permanent VIP/TAP staff and co-financing for permanent VIP/TAP staff | D33: =+(D23+D24+D25+D29-D26-D27-G30)/D22 -> #DIV/0!
B34: Cost Coverage Ratio (Project Level) This indicator includes coverage for permanent VIP/TAP staff but excludes co-financing for permanent VIP/TAP staff | D34: =+(D23+D24+D25+D29-D27-G30)/D22 -> #DIV/0!
B35: Budget controlled by controller(date and name) and name of the controller to be assigned to the project in ReAp | D35: Date: | G35: Name(ReAp)
B36: Other relevant information
B37: Workzone number (if already created)
B38: Documents for signature(yes/no) | D38: Yes | F38: Indicate page number(please list if more than one)
B39: Head of Department approval of PhDs student's work obligation of IFD projects | D39: The PhD students for which funding is applied will only work on tasks directly related to the project during their work obligation. | G39: No | H39: Number of months

Sheet Cover letter
B2: Cover letter for management for externally funded projects The green fields are to be filled in by the grant holder The grey fields retrieve information from the WPs that have the same department as in E5
B3: ReAp control | D3: =IFERROR(IF(AND(I5<>"", OR(C7<>"", LEN(TRIM(J7))>0), G5<>"", C9<>0, C12<>0, C13<>"", F12<>0, F13<>"", D20<>"", D22<>0, H33<>""), "✅ ReAp fields are completed", "❌ ReAp fields are missing data – Please fill in the yellow cells"), "❌ ReAp fields are missing data – Please fill in the yellow cells") -> ❌ ReAp fields are missing data – Please fill in the yellow cells
B5: Applicant name | C5: =+'B1'!C4 -> 0 | D5: Department | E5: =+'B1'!C2 -> 0 | F5: Section | H5: AUID | K5: =IF(OR('Cover letter ECE_MPE'!I5>0,LEN(I5)<3),1,0) -> 1
B6: Projecttitle and acronym | C6: =+'B1'!C3 -> 0
B7: Grant source | J7: {=IF(IF(IF(C7="",Tabel21[Grant source])=0,"",IF(C7="",Tabel21[Grant source]))=FALSE,"",IF(IF(C7="",Tabel21[Grant source])=0,"",IF(C7="",Tabel21[Grant source])))} | K7: =IF(ISBLANK(C7),J7,_xlfn.XLOOKUP(C7,GrantSource!C:C,GrantSource!A:A))
B8: Instrument | J8: {=IF(IF(IF(C8="",Tabel21[Instrument])=0,"",IF(C8="",Tabel21[Instrument]))=FALSE,"",IF(IF(C8="",Tabel21[Instrument])=0,"",IF(C8="",Tabel21[Instrument])))} | K8: =IF(ISBLANK(C8),J8,C8)
B9: GDPR-related | C9: =+'B1'!H8 -> 0 | D9: Is there involvement from a country that poses a threat to Denmark according to URIS guidelines? | G9: Specify country:
B10: Participants from the dept.
B11: Is Applicant main coordinator of the project | D11: If no, please type the name of the coordinator
B12: Project start (dd-mm-yyyy) | C12: =+'B1'!C9 -> 0 | D12: Project end (dd.mm.yyyy) | F12: =+'B1'!H9 -> 0
B13: Deadline for application (dd-mm-yyyy) | D13: Next update expected (dd-mm-yyyy)
B14: Short project description
B15: Partners within AU(name and dept.)
B16: Partners outside AU
B17: Planned new recruitment of named scientific staff (CV enclosed)
B18: BUDGET
B19: Special remarks to budget
B20: Applied amount total incl. partners and overhead
B21: Total budget to the dept. (incl. co-financing) | D21: =+IF(E5='B1'!C2,'B1'!AC73,0)+IF(E5='B2'!C2,'B2'!AC73,0)+IF(E5='B3'!C2,'B3'!AC73,0)+IF(E5='B4'!C2,'B4'!AC73,0)+IF(E5='B5'!C2,'B5'!AC73,0) -> 0
B22: Applied amount to the dept. incl. overhead | D22: =+IF(E5='B1'!C2,'B1'!AC89,0)+IF(E5='B2'!C2,'B2'!AC89,0)+IF(E5='B3'!C2,'B3'!AC89,0)+IF(E5='B4'!C2,'B4'!AC89,0)+IF(E5='B5'!C2,'B5'!AC89,0) -> 0
B23: Overhead/project supplement/BenchFee/EBIT | D23: =+IF(E5='B1'!C2,SUM('B1'!AC85:AC88),0)+IF(E5='B2'!C2,SUM('B2'!AC85:AC88),0)+IF(E5='B3'!C2,SUM('B3'!AC85:AC88),0)+IF(E5='B4'!C2,SUM('B4'!AC85:AC88),0)+IF(E5='B5'!C2,SUM('B5'!AC85:AC88),0) -> 0
B24: Cost Coverage salary | D24: =+IF('B1'!C2='Cover letter'!E5,SUMIF('B1'!O20:O55,Lister!D30,'B1'!AC20:AC56),0)+IF('B2'!C2='Cover letter'!E5,SUMIF('B2'!O20:O55,Lister!D30,'B2'!AC20:AC56),0)+IF('B3'!C2='Cover letter'!E5,SUMIF('B3'!O20:O55,Lister!D30,'B3'!AC20:AC56),0)+IF('B4'!C2='Cover letter'!E5,SUMIF('B4'!O20:O55,Lister!D30,'B4'!AC20:AC56),0)+IF('B5'!C2='Cover letter'!E5,SUMIF('B5'!O20:O55,Lister!D30,'B5'!AC20:AC56),0) -> 0
B25: Cost Coverage others | D25: =(IF('B1'!C2='Cover letter'!E5,SUMIF('B1'!O62:O74,Lister!D30,'B1'!M62:M74),0)+IF('B2'!C2='Cover letter'!E5,SUMIF('B2'!O62:O74,Lister!D30,'B2'!M62:M74),0)+IF('B3'!C2='Cover letter'!E5,SUMIF('B3'!O62:O74,Lister!D30,'B3'!M62:M74),0)+IF('B4'!C2='Cover letter'!E5,SUMIF('B4'!O62:O74,Lister!D30,'B4'!M62:M74),0)+IF('B5'!C2='Cover letter'!E5,SUMIF('B5'!O62:O74,Lister!D30,'B5'!M62:M74),0)) -> 0
B26: Department co-financing salary | D26: =+IF('B1'!C2='Cover letter'!E5,SUMIF('B1'!O20:O55,Lister!D31,'B1'!AC20:AC56),0)+IF('B2'!C2='Cover letter'!E5,SUMIF('B2'!O20:O55,Lister!D31,'B2'!AC20:AC56),0)+IF('B3'!C2='Cover letter'!E5,SUMIF('B3'!O20:O55,Lister!D31,'B3'!AC20:AC56),0)+IF('B4'!C2='Cover letter'!E5,SUMIF('B4'!O20:O55,Lister!D31,'B4'!AC20:AC56),0)+IF('B5'!C2='Cover letter'!E5,SUMIF('B5'!O20:O55,Lister!D31,'B5'!AC20:AC56),0) -> 0 | F26: Department co-financing | G26: =+(D26+D27)/D21 -> #DIV/0!
B27: Department co-financing others | D27: =+IF('B1'!C2='Cover letter'!E5,SUMIF('B1'!O62:O74,Lister!D31,'B1'!M62:M74),0)+IF('B2'!C2='Cover letter'!E5,SUMIF('B2'!O62:O74,Lister!D31,'B2'!M62:M74),0)+IF('B3'!C2='Cover letter'!E5,SUMIF('B3'!O62:O74,Lister!D31,'B3'!M62:M74),0)+IF('B4'!C2='Cover letter'!E5,SUMIF('B4'!O62:O74,Lister!D31,'B4'!M62:M74),0)+IF('B5'!C2='Cover letter'!E5,SUMIF('B5'!O62:O74,Lister!D31,'B5'!M62:M74),0) -> 0
B28: Co-financing external funded | D28: =+IF('B1'!C2='Cover letter'!E5,SUMIF('B1'!O20:O55,Lister!D32,'B1'!AC20:AC56),0)+IF('B2'!C2='Cover letter'!E5,SUMIF('B2'!O20:O55,Lister!D32,'B2'!AC20:AC56),0)+IF('B3'!C2='Cover letter'!E5,SUMIF('B3'!O20:O55,Lister!D32,'B3'!AC20:AC56),0)+IF('B4'!C2='Cover letter'!E5,SUMIF('B4'!O20:O55,Lister!D32,'B4'!AC20:AC56),0)+IF('B5'!C2='Cover letter'!E5,SUMIF('B5'!O20:O55,Lister!D32,'B5'!AC20:AC56),0)+IF('B1'!C2='Cover letter'!E5,SUMIF('B1'!O62:O74,Lister!D32,'B1'!M62:M74),0)+IF('B2'!C2='Cover letter'!E5,SUMIF('B2'!O62:O74,Lister!D32,'B2'!M62:M74),0)+IF('B3'!C2='Cover letter'!E5,SUMIF('B3'!O62:O74,Lister!D32,'B3'!M62:M74),0)+IF('B4'!C2='Cover letter'!E5,SUMIF('B4'!O62:O74,Lister!D32,'B4'!M62:M74),0)+IF('B5'!C2='Cover letter'!E5,SUMIF('B5'!O62:O74,Lister!D32,'B5'!M62:M74),0) -> 0 | F28: Source of co-financing (name projects)
B29: PhD Tuition Fee share to dept. | D29: =IF('B1'!C2=E5,(SUMIFS('B1'!M62:M72,'B1'!A62:A72,Lister!M11,'B1'!O62:O72,Lister!D29)+SUMIFS('B1'!M62:M72,'B1'!A62:A72,Lister!M11,'B1'!O62:O72,Lister!D30))-((SUMIF('B1'!A20:A29,Lister!A20,'B1'!M20:M29)+SUMIF('B1'!A20:A29,Lister!A21,'B1'!M20:M29))/12*30000),0)+IF('B2'!C2=E5,(SUMIFS('B2'!M62:M72,'B2'!A62:A72,Lister!M11,'B2'!O62:O72,Lister!D29)+SUMIFS('B2'!M62:M72,'B2'!A62:A72,Lister!M11,'B2'!O62:O72,Lister!D30))-((SUMIF('B2'!A20:A29,Lister!A20,'B2'!M20:M29)+SUMIF('B2'!A20:A29,Lister!A21,'B2'!M20:M29))/12*30000),0)+IF('B3'!C2=E5,(SUMIFS('B3'!M62:M72,'B3'!A62:A72,Lister!M11,'B3'!O62:O72,Lister!D29)+SUMIFS('B3'!M62:M72,'B3'!A62:A72,Lister!M11,'B3'!O62:O72,Lister!D30))-((SUMIF('B3'!A20:A29,Lister!A20,'B3'!M20:M29)+SUMIF('B3'!A20:A29,Lister!A21,'B3'!M20:M29))/12*30000),0)*IF('B4'!C2=E5,(SUMIFS('B4'!M62:M72,'B4'!A62:A72,Lister!M11,'B4'!O62:O72,Lister!D29)+SUMIFS('B4'!M62:M72,'B1'!A62:A72,Lister!M11,'B4'!O62:O72,Lister!D30))-((SUMIF('B4'!A20:A29,Lister!A20,'B4'!M20:M29)+SUMIF('B4'!A20:A29,Lister!A21,'B4'!M20:M29))/12*30000),0)+IF('B5'!C2=E5,(SUMIFS('B5'!M62:M72,'B5'!A62:A72,Lister!M11,'B5'!O62:O72,Lister!D29)+SUMIFS('B5'!M62:M72,'B5'!A62:A72,Lister!M11,'B5'!O62:O72,Lister!D30))-((SUMIF('B5'!A20:A29,Lister!A20,'B5'!M20:M29)+SUMIF('B5'!A20:A29,Lister!A21,'B5'!M20:M29))/12*30000),0) -> 0
B30: Procurement external funding | D30: =SUMIFS('B1'!M62:M72,'B1'!A62:A72,Lister!M7,'B1'!O62:O72,Lister!D29)+SUMIFS('B2'!M62:M72,'B2'!A62:A72,Lister!M7,'B2'!O62:O72,Lister!D29)+SUMIFS('B3'!M62:M72,'B3'!A62:A72,Lister!M7,'B3'!O62:O72,Lister!D29)+SUMIFS('B4'!M62:M72,'B4'!A62:A72,Lister!M7,'B4'!O62:O72,Lister!D29)+SUMIFS('B5'!M62:M72,'B5'!A62:A72,Lister!M7,'B5'!O62:O72,Lister!D29) -> 0 | F30: Depreciation covered by dept. due to exp. of project period | G30: =+ABS(SUMIF('B1'!A62:A72,Lister!M9,'B1'!M62:M72))+ABS(SUMIF('B2'!A62:A72,Lister!M9,'B2'!M62:M72))+ABS(SUMIF('B3'!A62:A72,Lister!M9,'B3'!M62:M72))+ABS(SUMIF('B4'!A62:A72,Lister!M9,'B4'!M62:M72))+ABS(SUMIF('B5'!A62:A72,Lister!M9,'B5'!M62:M72)) -> 0 | H30: Cost Coverage depreciation | I30: =SUMIFS('B1'!M62:M72,'B1'!A62:A72,Lister!M8,'B1'!O62:O72,Lister!D30)+SUMIFS('B2'!M62:M72,'B2'!A62:A72,Lister!M8,'B2'!O62:O72,Lister!D30)+SUMIFS('B3'!M62:M72,'B3'!A62:A72,Lister!M8,'B3'!O62:O72,Lister!D30)+SUMIFS('B4'!M62:M72,'B4'!A62:A72,Lister!M8,'B4'!O62:O72,Lister!D30)+SUMIFS('B5'!M62:M72,'B5'!A62:A72,Lister!M8,'B5'!O62:O72,Lister!D30) -> 0
B31: Experiements(Fields, Barn, Workshops)- budget cleared with manager (Yes/No) (Only relevant for ANIVET and AGRO)
B32: Project Overhead & Cost Coverage This indicator focuses solely on the project's core budget | D32: =IFERROR((D23+D24+D25-D26-D27)/(D22-D23-D24-D25+D26+D27),0) -> 0
B33: Budget controlled by controller (date and name) and name of the controller to be assigned to the project in ReAp | D33: Date/Name: | G33: Name (ReAp)
B34: Other relevant information
B35: Advise in project (Commercial projects), i.e. a report(yes/no)
B36: Is the project description/quotation quality assured by DCE/DCA(yes/no)
B37: Review of application internal in the dept. (name and date) | D37: Date: | G37: Name
B38: Legal Review(yes/no) If yes:
B39: - Contract/agremment review by | D39: Date: | G39: Name
B40: - Special legal remark, if any
B41: Workzone number (if already created)
B42: Documents for signature(yes/no) | F42: Indicate page number(please list if more than one)
B43: Head of Department approval of PhDs student's work obligation of IFD projects | D43: The PhD students for which funding is applied will only work on tasks directly related to the project during their work obligation. | G43: No | H43: Number of months

Sheet Currency
A1: currency.code | B1: currency.name | C1: currency.rate | D1: LastUpdated
A2: AUD | B2: Australian dollars | C2: 463 | D2: 46288
A3: BRL | B3: Brazilian real | C3: 127.65 | D3: 46288
A4: CAD | B4: Canadian dollars | C4: 464.99 | D4: 46288
A5: CNY | B5: Chinese yuan renminbi | C5: 97.67 | D5: 46288
A6: CZK | B6: Czech koruny | C6: 30.66 | D6: 46288
A7: EUR | B7: Euro | C7: 747.56 | D7: 46288
A8: HKD | B8: Hong Kong dollars | C8: 83.52 | D8: 46288
A9: HUF | B9: Hungarian forints | C9: 2.052 | D9: 46288
A10: ISK | B10: Icelandic kronur | C10: 5.417 | D10: 46288
A11: INR | B11: Indian rupee | C11: 6.84 | D11: 46288
A12: IDR | B12: Indonesian rupiah | C12: 0.0368 | D12: 46288
A13: ILS | B13: Israeli shekel | C13: 217.21 | D13: 46288
... A31: USD | B31: US dollars | C31: 655.12 | D31: 46288

Sheet GrantSourceCategory
A1: GrantSourceCategory | B1: GrantSource | C1: GrantSourceExtra | D1: GrantSourceUdvidet
A2: Danish public | B2: Aarhus Kommune | D2: Aarhus Kommune ()
A3: Danish public | B3: Aarhus Universitet | C3: AU | D3: Aarhus Universitet (AU)
A4: Danish public | B4: Danmarks Grundforskningsfond | C4: Danish National Research Foundation | D4: Danmarks Grundforskningsfond (Danish National Research Foundation)
A5: Danish public | B5: Forskningsrådet for Natur og Univers | C5: Danmarks Frie Forskningsråd, The Danish Research Council for Natural Sciences, DFF FNU | D5: Forskningsrådet for Natur og Univers (Danmarks Frie Forskningsråd, The Danish Research Council for Natural Sciences, DFF FNU)
A6: Danish public | B6: Forskningsrådet for Sundhed og Sygdom | C6: Danmarks Frie Forskningsråd, The Danish Research Council for Medical Sciences, DFF FSS | D6: Forskningsrådet for Sundhed og Sygdom (Danmarks Frie Forskningsråd, The Danish Research Council for Medical Sciences, DFF FSS)
A7: Danish public | B7: Forskningsrådet for Teknologi og Produktion | C7: Danmarks Frie Forskningsråd, The Danish Research Council for Technology and Production Sciences, DFF FTP | D7: Forskningsrådet for Teknologi og Produktion (Danmarks Frie Forskningsråd, The Danish Research Council for Technology and Production Sciences, DFF FTP)
A8: Danish public | B8: Forskningsrådet for Samfund og Erhverv | C8: Danmarks Frie Forskningsråd, The Danish Research Council for Social Sciences, DFF FSE | D8: Forskningsrådet for Samfund og Erhverv (Danmarks Frie Forskningsråd, The Danish Research Council for Social Sciences, DFF FSE)
A9: Danish public | B9: Forskningsrådet for Kultur og Kommunikation | C9: Danmarks Frie Forskningsråd, The Danish Research Council for Humanities, DFF FKK | D9: Forskningsrådet for Kultur og Kommunikation (Danmarks Frie Forskningsråd, The Danish Research Council for Humanities, DFF FKK)
A10: Danish public | B10: Tematisk Forskning | C10: Danmarks Frie Forskningsråd, Thematic Research, DFF | D10: Tematisk Forskning (Danmarks Frie Forskningsråd, Thematic Research, DFF)
A11: Danish public | B11: International Centre for Research in Organic Food Systems | C11: ICROFS | D11: International Centre for Research in Organic Food Systems (ICROFS)
A12: Danish public | B12: InnovationsFonden | C12: Innovation Fund Denmark | D12: InnovationsFonden (Innovation Fund Denmark)
A13: Danish public | B13: Civilstyrelsen | C13: Department of Civil Affairs | D13: Civilstyrelsen (Department of Civil Affairs)
A14: Danish public | B14: Danida | C14: Danish International Development Assistance | D14: Danida (Danish International Development Assistance)
A15: Danish public | B15: Danida Fellowship Centre | D15: Danida Fellowship Centre ()
A16: Danish public | B16: Danida Green Business Partnerships | C16: DGBP | D16: Danida Green Business Partnerships (DGBP)
A17: Danish public | B17: Danida Knowledge and Innovation Partnerships | D17: Danida Knowledge and Innovation Partnerships ()
A18: Danish public | B18: Danish Diabetes Academy | D18: Danish Diabetes Academy ()
A19: Danish public | B19: Danish e-infrastructure | D19: Danish e-infrastructure ()
A20: Danish public | B20: Dansk Center for Havforskning | D20: Dansk Center for Havforskning ()
A21: Danish public | B21: Planteafgiftsfonden | D21: Planteafgiftsfonden ()
A22: Danish public | B22: Danmarks Tekniske Universitet | C22: Technical University of Denmark | D22: Danmarks Tekniske Universitet (Technical University of Denmark)
A23: Danish public | B23: Danske Regioner | C23: Danish Regions | D23: Danske Regioner (Danish Regions)
A24: Danish public | B24: Det danske SDC-sekretariat | C24: The Danish SDC secretariat | D24: Det danske SDC-sekretariat (The Danish SDC secretariat)
A25: Danish public | B25: DIREC | C25: Digital Research Centre Denmark | D25: DIREC (Digital Research Centre Denmark)
A26: Danish public | B26: Energinet.dk | D26: Energinet.dk ()
A27: Danish public | B27: Energistyrelsen | C27: Danish Energy Agency | D27: Energistyrelsen (Danish Energy Agency)
A28: Danish public | B28: Erhvervsstyrelsen | C28: The Danish Business Authority | D28: Erhvervsstyrelsen (The Danish Business Authority)
A29: Danish public | B29: Erhvervsfremmestyrelsen | C29: the Danish Board of Business Development | D29: Erhvervsfremmestyrelsen (the Danish Board of Business Development)
A30: Danish public | B30: EUDP – Det Energiteknologiske Udviklings- og Demonstrationsprogram | C30: The EUDP secretariat | D30: EUDP – Det Energiteknologiske Udviklings- og Demonstrationsprogram (The EUDP secretariat)
A31: Danish public | B31: Fjerkræafgiftsfonden | C31: Danish Poultry Levy Fund | D31: Fjerkræafgiftsfonden (Danish Poultry Levy Fund)
A32: Danish public | B32: Fonden for Økologisk Landbrug | C32: The Danish Fund for Organic Farming | D32: Fonden for Økologisk Landbrug (The Danish Fund for Organic Farming)
A33: Danish public | B33: Frøafgiftsfonden | C33: Danish Seeds Levy Fund | D33: Frøafgiftsfonden (Danish Seeds Levy Fund)
A34: Danish public | B34: Fødevarestyrelsen | C34: Danish Veterinary and Food Administration | D34: Fødevarestyrelsen (Danish Veterinary and Food Administration)
A35: Danish public | B35: GEUS | C35: Geological Survey of Denmark and Greenland | D35: GEUS (Geological Survey of Denmark and Greenland)
A36: Danish public | B36: GUDP | C36: Grønt Udviklings- og Demonstrationsprogram | D36: GUDP (Grønt Udviklings- og Demonstrationsprogram)
A37: Danish public | B37: Grønlands Naturinstitut | C37: The Greenland Institute of Natural Resources | D37: Grønlands Naturinstitut (The Greenland Institute of Natural Resources)
A38: Danish public | B38: Holbæk Kommune | D38: Holbæk Kommune ()
A39: Danish public | B39: It-Vest | D39: It-Vest ()
A40: Danish public | B40: Kartoffelafgiftsfonden | C40: Danish Potato Levy Fund | D40: Kartoffelafgiftsfonden (Danish Potato Levy Fund)
A41: Danish public | B41: Klima-, Energi- og Forsyningsministeriet | C41: Danish Ministry of Climate, Energy and Utilities | D41: Klima-, Energi- og Forsyningsministeriet (Danish Ministry of Climate, Energy and Utilities)
A42: Danish public | B42: Kulturarvsstyrelsen | C42: Agency for Culture and Palaces | D42: Kulturarvsstyrelsen (Agency for Culture and Palaces)
A43: Danish public | B43: Kvægafgiftsfonden | C43: Danish Cattle Levy Fund | D43: Kvægafgiftsfonden (Danish Cattle Levy Fund)
A44: Danish public | B44: Københavns Kommune | D44: Københavns Kommune ()
A45: Danish public | B45: Københavns Universitet | C45: University of Copenhagen | D45: Københavns Universitet (University of Copenhagen)
A46: Danish public | B46: Landbrug & Fødevarer | D46: Landbrug & Fødevarer ()
A47: Danish public | B47: Landbrugs- og Fiskeristyrelsen | C47: The Danish Agrifish Agency | D47: Landbrugs- og Fiskeristyrelsen (The Danish Agrifish Agency)
A48: Danish public | B48: Lyngby-Taarbæk Kommune | D48: Lyngby-Taarbæk Kommune ()
A49: Danish public | B49: Middelfart Kommune | D49: Middelfart Kommune ()
A50: Danish public | B50: Miljøfonden | C50: Avatangiisinut Aningaasaateqarfik | D50: Miljøfonden (Avatangiisinut Aningaasaateqarfik)
A51: Danish public | B51: Miljø- og Fødevareministeriet | C51: Ministry of Environment and Food of Denmark | D51: Miljø- og Fødevareministeriet (Ministry of Environment and Food of Denmark)
A52: Danish public | B52: Miljø- og Ligestillingsministeriet | C52: Ministry of Environment and Gender Equality of Denmark | D52: Miljø- og Ligestillingsministeriet (Ministry of Environment and Gender Equality of Denmark)
A53: Danish public | B53: Miljøstyrelsen | C53: Danish Environmental Protection Agency | D53: Miljøstyrelsen (Danish Environmental Protection Agency)
A54: Danish public | B54: Mælkeafgiftsfonden | C54: Danish Milk Levy Fund | D54: Mælkeafgiftsfonden (Danish Milk Levy Fund)
A55: Danish public | B55: Nationalt Center for Klimaforskning | C55: NCKF-DMI | D55: Nationalt Center for Klimaforskning (NCKF-DMI)
A56: Danish public | B56: Nationalt Forsvarsteknologisk Center | C56: National Defence Technology Centre (NFC) | D56: Nationalt Forsvarsteknologisk Center (National Defence Technology Centre (NFC))
A57: Danish public | B57: Naturstyrelsen | C57: National Forest and Nature Agency | D57: Naturstyrelsen (National Forest and Nature Agency)
A58: Danish public | B58: Nordfyns Kommune | D58: Nordfyns Kommune ()
A59: Danish public | B59: Odense Universitetshospital | C59: Odense University Hospital | D59: Odense Universitetshospital (Odense University Hospital)
A60: Danish public | B60: Pelsdyrafgiftsfonden | C60: Danish Fur Levy Fund | D60: Pelsdyrafgiftsfonden (Danish Fur Levy Fund)
A61: Danish public | B61: Plantefonden | C61: Fonden for plantebaserede fødevarer | D61: Plantefonden (Fonden for plantebaserede fødevarer)
A62: Danish public | B62: Promilleafgiftsfonden for landbrug | C62: Danish Promille Levy Fund | D62: Promilleafgiftsfonden for landbrug (Danish Promille Levy Fund)
A63: Danish public | B63: Region Midtjylland | C63: Central Denmark Region | D63: Region Midtjylland (Central Denmark Region)
A64: Danish public | B64: Region Nordjylland | C64: The North Denmark Region | D64: Region Nordjylland (The North Denmark Region)
A65: Danish public | B65: Regionshospitalet Herning | C65: Herning Regional Hospital | D65: Regionshospitalet Herning (Herning Regional Hospital)
A66: Danish public | B66: Region Syddanmark | C66: The Region of Southern Denmark | D66: Region Syddanmark (The Region of Southern Denmark)
A67: Danish public | B67: Roskilde Kommune | D67: Roskilde Kommune ()
A68: Danish public | B68: Råstofdirektoratet | C68: The Bureau of Minerals | D68: Råstofdirektoratet (The Bureau of Minerals)
A69: Danish public | B69: Statens serum institut | C69: Statens Serum Institut | D69: Statens serum institut (Statens Serum Institut)
A70: Danish public | B70: Styrelsen for Grøn Arealomlægning og Vandmiljø | C70: SGAV | D70: Styrelsen for Grøn Arealomlægning og Vandmiljø (SGAV)
A71: Danish public | B71: Sukkerroeafgiftsfonden | D71: Sukkerroeafgiftsfonden ()
A72: Danish public | B72: Sundheds- og ældreministeriet | C72: Ministry of Health | D72: Sundheds- og ældreministeriet (Ministry of Health)
A73: Danish public | B73: Svineafgiftsfonden | C73: Danish Pig Levy Fund | D73: Svineafgiftsfonden (Danish Pig Levy Fund)
A74: Danish public | B74: Syddansk Universitet | C74: University of Southern Denmark | D74: Syddansk Universitet (University of Southern Denmark)
A75: Danish public | B75: Sygesikringen Danmark | D75: Sygesikringen Danmark ()
A76: Danish public | B76: Uddannelses- og Forskningsministeriet | C76: Ministry for Higher Education and Science | D76: Uddannelses- og Forskningsministeriet (Ministry for Higher Education and Science)
A77: Danish public | B77: Udenrigsministeriet | C77: Danish Ministry of Foreign Affairs of Denmark | D77: Udenrigsministeriet (Danish Ministry of Foreign Affairs of Denmark)
A78: Danish public | B78: Undervisningsministeriet | C78: Danish Ministry of Education | D78: Undervisningsministeriet (Danish Ministry of Education)
A79: Danish public | B79: Vejdirektoratet | D79: Vejdirektoratet ()
A80: Danish public | B80: Via University College | C80: Via University College | D80: Via University College (Via University College)
A81: Danish public | B81: Videreuddannelsregion Nord | D81: Videreuddannelsregion Nord ()
A82: Danish public | B82: Vækstforum Sjælland | C82: The Zealand Growth Forum | D82: Vækstforum Sjælland (The Zealand Growth Forum)
A83: Danish public | B83: Aarhus Universitetshospital | C83: Aarhus University Hospital | D83: Aarhus Universitetshospital (Aarhus University Hospital)
A84: Danish private | B84: Aarhus Universitets Forskningsfond | C84: Aarhus University Research Foundation, AUFF | D84: Aarhus Universitets Forskningsfond (Aarhus University Research Foundation, AUFF)
A85: Danish private | B85: Agria | D85: Agria ()
A86: Danish private | B86: Aktieselskabet Dampskibsselskabet Orients Fond | D86: Aktieselskabet Dampskibsselskabet Orients Fond ()
A87: Danish private | B87: AlgeCenter Danmark | D87: AlgeCenter Danmark ()
A88: Danish private | B88: AU strategiske midler | C88: Aarhus University strategic funds | D88: AU strategiske midler (Aarhus University strategic funds)
A89: Danish private | B89: ST strategiske midler | C89: Science and Technology strategic funds | D89: ST strategiske midler (Science and Technology strategic funds)
A90: Danish private | B90: Aarhus Institute of Advanced Studies | C90: AIAS | D90: Aarhus Institute of Advanced Studies (AIAS)
A91: Danish private | B91: 15. Juni Fonden | D91: 15. Juni Fonden ()
A92: Danish private | B92: aerbio | D92: aerbio ()
A93: Danish private | B93: A.J. Andersen og Hustrus Fond | D93: A.J. Andersen og Hustrus Fond ()
A94: Danish private | B94: A.P. Møller og Hustrus Fond | C94: A.P. Møller and Wife's Foundation | D94: A.P. Møller og Hustrus Fond (A.P. Møller and Wife's Foundation)
A95: Danish private | B95: Arvid Nilssons Fond | C95: The Arvid Nilssons Foundation | D95: Arvid Nilssons Fond (The Arvid Nilssons Foundation)
A96: Danish private | B96: Augustinus Fonden | C96: The Augustinus Foundation | D96: Augustinus Fonden (The Augustinus Foundation)
A97: Danish private | B97: Axel Muusfeldts Fond | D97: Axel Muusfeldts Fond ()
A98: Danish private | B98: BETA.HEALTH - AUH | D98: BETA.HEALTH - AUH ()
A99: Danish private | B99: Biosolutions Zealand | D99: Biosolutions Zealand ()
A100: Danish private | B100: Bodil Pedersen Fonden | D100: Bodil Pedersen Fonden ()
...

Sheet My Notes

Sheet B1
A1: Budgeting helping sheet for grant financed projects | E1: PLEASE FILL THE GREEN CELLS
A2: Department:* | E2: * = MUST BE FILLED TO CALCULATE SHEET CORRECT | M2: Please make sure that all cells in "PE" are filled, befored getting approval
A3: Projecttitle and acronym:*
A4: Applicant:* | N4: Project Overhead & Cost Coverage | O4: =IFERROR((R89-R84+R112-R126)/(R84-R112+R126),0) -> 0
A5: Grant Source:* | N5: Department Co-financing (excl. overhead) | O5: =IFERROR((AC126/AC68),0) -> 0
A6: Insert overheads rate:* | C6: 0 | D6: Overhead calculation basis:* | G6: =IF(C8="Bench Fee","Salary, operations and Bench Fee",IFERROR(VLOOKUP(C5,Lister!I19:S52,9,FALSE),"Salary and operations")) -> Salary and operations | N6: Project Co-financing | O6: =IFERROR(AC103/AC73,0) -> 0
A7: Insert yearly count of hours:* | C7: =IFERROR(IF(C12=Lister!A50,1460,VLOOKUP(C5,Lister!I20:M52,3,FALSE)),0) -> 0 | D7: Calculate technical ass. basis:* | G7: =IFERROR(VLOOKUP(C5,Lister!I19:S52,11,FALSE),"Salary and operations") -> Salary and operations
A8: Project supplement or Bench Fee:* | C8: =IFERROR((VLOOKUP(C5,Lister!I20:O52,7,FALSE)),"None") -> None | E8: Is the project GDPR related*
A9: Project start date (DD-MM-YYYY)* | G9: Project end date (DD-MM-YYYY)*
A10: Calculate laboratory support* | C10: =+IF(OR(C2="FOOD",C2="BCE"),"Yes","No") -> No | G10: Time registration needed:*
A11: The fields (row 11-15) below are to be filled out only if the project kind is a commercial activity (Indtægtsdækket virksomhed)
A12: If Project Kind is commercial activity choose 2
A13: EBIT | C13: =+IF(C12=2,10,0) -> 0
A14: Does AU have a monopoly on the activity | D14: If yes, provide a brief explanation of why AU has a monopoly on the activity. EBIT is changed to 0%
A15: Has the activity been put out to tender
A16: Is the activity a direct extension of the departments core activity? | D16: Briefly describe how the activity is a natural extension of the department's core activities
V18: Salary budget VIP/TAP | AE18: Total hours | AF18: Avg. hourly rate | AH18: Total hours | AI18: Avg. hourly rate | AK18: Total hours | AL18: Avg. hourly rate | AN18: Total hours | AO18: Avg. hourly rate | AQ18: Total hours | AR18: Avg. hourly rate | AT18: Total hours | AU18: Avg. hourly rate | AW18: Total hours | AX18: Avg. hourly rate | AZ18: Total hours | BA18: Avg. hourly rate | BC18: Total hours | BD18: Avg. hourly rate | BF18: Total hours | BG18: Avg. hourly rate | BI18: Total hours | BJ18: Avg. hourly rate
A19: Choose VIP and insert count of months | C19: =+Takstblad!C3 -> 2026 | D19: =+C19+1 -> 2027 | E19: =+D19+1 -> 2028 | F19: =+E19+1 -> 2029 | G19: =+F19+1 -> 2030 | H19: =+G19+1 -> 2031 | I19: =+H19+1 -> 2032 | J19: =+I19+1 -> 2033 | K19: =+J19+1 -> 2034 | L19: =+K19+1 -> 2035 | M19: Total | N19: Comment | O19: Type of budget | Q19: VIP-salary | R19: Total | S19: =+C19 -> 2026 | T19: =+D19 -> 2027 | U19: =+E19 -> 2028 | V19: =+F19 -> 2029 | W19: =+G19 -> 2030 | X19: =+H19 -> 2031 | Y19: =+I19 -> 2032 | Z19: =+J19 -> 2033 | ... AB19: =+L19 -> 2035 | AC19: Total | AE19: Total | AH19: =+S19 -> 2026 | AK19: =+T19 -> 2027 | AN19: =+U19 -> 2028 | AQ19: =+V19 -> 2029 | AT19: =+W19 -> 2030 | AW19: =+X19 -> 2031 | AZ19: =Y19 -> 2032 | BC19: =+Z19 -> 2033 | BF19: =+AA19 -> 2034 | BI19: =+AB19 -> 2035
A20: "Choose job position" | B20: =+VLOOKUP(A20,Takstblad!$A$5:$B$30,2,FALSE) | M20: =SUM(C20:L20) -> 0 | O20: External funding | R20: =+AC20 -> 0 | S20: =+IFERROR(IF(S$19=Takstblad!C$3,VLOOKUP($A20,takstblad,3,FALSE)*C20,"fejl i år"),0) -> 0 | T20: =+IFERROR(IF(T$19=Takstblad!D$3,VLOOKUP($A20,takstblad,4,FALSE)*D20,"fejl i år"),0) -> 0 | U20: =+IFERROR(IF(U$19=Takstblad!E$3,VLOOKUP($A20,takstblad,5,FALSE)*E20,"fejl i år"),0) -> 0 | V20: =+IFERROR(IF(V$19=Takstblad!F$3,VLOOKUP($A20,takstblad,6,FALSE)*F20,"fejl i år"),0) -> 0 | W20: =+IFERROR(IF(W$19=Takstblad!G$3,VLOOKUP($A20,takstblad,7,FALSE)*G20,"fejl i år"),0) -> 0 | X20: =+IFERROR(IF(X$19=Takstblad!H$3,VLOOKUP($A20,takstblad,8,FALSE)*H20,"fejl i år"),0) -> 0 | Y20: =+IFERROR(IF(Y$19=Takstblad!I$3,VLOOKUP($A20,takstblad,9,FALSE)*I20,"fejl i år"),0) -> 0 | Z20: =+IFERROR(IF(Z$19=Takstblad!J$3,VLOOKUP($A20,takstblad,10,FALSE)*J20,"fejl i år"),0) -> 0 | AA20: =+IFERROR(IF(AA$19=Takstblad!K$3,VLOOKUP($A20,takstblad,11,FALSE)*K20,"fejl i år"),0) -> 0 | AB20: =+IFERROR(IF(AB$19=Takstblad!L$3,VLOOKUP($A20,takstblad,12,FALSE)*L20,"fejl i år"),0) -> 0 | AC20: =SUM(S20:AB20) -> 0 | AE20: =+M20*($C$7/12) -> 0 | AF20: =IFERROR(AC20/AE20,0) -> 0 | AH20: =+C20*($C$7/12) -> 0 | AI20: =IFERROR(S20/AH20,0) -> 0 | AK20: =+D20*($C$7/12) -> 0 | AL20: =IFERROR(T20/AK20,0) -> 0 | AN20: =+E20*($C$7/12) -> 0 | AO20: =IFERROR(U20/AN20,0) -> 0 | AQ20: =+F20*($C$7/12) -> 0 | AR20: =IFERROR(V20/AQ20,0) -> 0 | AT20: =+G20*($C$7/12) -> 0 | AU20: =IFERROR(W20/AT20,0) -> 0 | AW20: =+H20*($C$7/12) -> 0 | AX20: =IFERROR(X20/AW20,0) -> 0 | AZ20: =+I20*($C$7/12) -> 0 | BA20: =IFERROR(Y20/AZ20,0) -> 0 | BC20: =+J20*($C$7/12) -> 0 | BD20: =IFERROR(Z20/BC20,0) -> 0 | BF20: =+K20*($C$7/12) -> 0 | BG20: =IFERROR(AA20/BF20,0) -> 0 | BI20: =+L20*($C$7/12) -> 0 | BJ20: =IFERROR(AB20/BI20,0) -> 0
A21: "Choose job position" | B21: =+VLOOKUP(A21,Takstblad!$A$5:$B$30,2,FALSE) | M21: =SUM(C21:L21) -> 0 | O21: External funding | R21: =+AC21 -> 0 | S21: =+IFERROR(IF(S$19=Takstblad!C$3,VLOOKUP($A21,takstblad,3,FALSE)*C21,"fejl i år"),0) -> 0 | T21: =+IFERROR(IF(T$19=Takstblad!D$3,VLOOKUP($A21,takstblad,4,FALSE)*D21,"fejl i år"),0) -> 0 | U21: =+IFERROR(IF(U$19=Takstblad!E$3,VLOOKUP($A21,takstblad,5,FALSE)*E21,"fejl i år"),0) -> 0 | V21: =+IFERROR(IF(V$19=Takstblad!F$3,VLOOKUP($A21,takstblad,6,FALSE)*F21,"fejl i år"),0) -> 0 | W21: =+IFERROR(IF(W$19=Takstblad!G$3,VLOOKUP($A21,takstblad,7,FALSE)*G21,"fejl i år"),0) -> 0 | X21: =+IFERROR(IF(X$19=Takstblad!H$3,VLOOKUP($A21,takstblad,8,FALSE)*H21,"fejl i år"),0) -> 0 | Y21: =+IFERROR(IF(Y$19=Takstblad!I$3,VLOOKUP($A21,takstblad,9,FALSE)*I21,"fejl i år"),0) -> 0 | Z21: =+IFERROR(IF(Z$19=Takstblad!J$3,VLOOKUP($A21,takstblad,10,FALSE)*J21,"fejl i år"),0) -> 0 | AA21: =+IFERROR(IF(AA$19=Takstblad!K$3,VLOOKUP($A21,takstblad,11,FALSE)*K21,"fejl i år"),0) -> 0 | AB21: =+IFERROR(IF(AB$19=Takstblad!L$3,VLOOKUP($A21,takstblad,12,FALSE)*L21,"fejl i år"),0) -> 0 | AC21: =SUM(S21:AB21) -> 0 | AE21: =+M21*($C$7/12) -> 0 | AF21: =IFERROR(AC21/AE21,0) -> 0 | AH21: =+C21*($C$7/12) -> 0 | AI21: =IFERROR(S21/AH21,0) -> 0 | AK21: =+D21*($C$7/12) -> 0 | AL21: =IFERROR(T21/AK21,0) -> 0 | AN21: =+E21*($C$7/12) -> 0 | AO21: =IFERROR(U21/AN21,0) -> 0 | AQ21: =+F21*($C$7/12) -> 0 | AR21: =IFERROR(V21/AQ21,0) -> 0 | AT21: =+G21*($C$7/12) -> 0 | AU21: =IFERROR(W21/AT21,0) -> 0 | AW21: =+H21*($C$7/12) -> 0 | AX21: =IFERROR(X21/AW21,0) -> 0 | AZ21: =+I21*($C$7/12) -> 0 | BA21: =IFERROR(Y21/AZ21,0) -> 0 | BC21: =+J21*($C$7/12) -> 0 | BD21: =IFERROR(Z21/BC21,0) -> 0 | BF21: =+K21*($C$7/12) -> 0 | BG21: =IFERROR(AA21/BF21,0) -> 0 | BI21: =+L21*($C$7/12) -> 0 | BJ21: =IFERROR(AB21/BI21,0) -> 0
A22: "Choose job position" | B22: =+VLOOKUP(A22,Takstblad!$A$5:$B$30,2,FALSE) | M22: =SUM(C22:L22) -> 0 | O22: External funding | R22: =+AC22 -> 0 | S22: =+IFERROR(IF(S$19=Takstblad!C$3,VLOOKUP($A22,takstblad,3,FALSE)*C22,"fejl i år"),0) -> 0 | T22: =+IFERROR(IF(T$19=Takstblad!D$3,VLOOKUP($A22,takstblad,4,FALSE)*D22,"fejl i år"),0) -> 0 | U22: =+IFERROR(IF(U$19=Takstblad!E$3,VLOOKUP($A22,takstblad,5,FALSE)*E22,"fejl i år"),0) -> 0 | V22: =+IFERROR(IF(V$19=Takstblad!F$3,VLOOKUP($A22,takstblad,6,FALSE)*F22,"fejl i år"),0) -> 0 | W22: =+IFERROR(IF(W$19=Takstblad!G$3,VLOOKUP($A22,takstblad,7,FALSE)*G22,"fejl i år"),0) -> 0 | X22: =+IFERROR(IF(X$19=Takstblad!H$3,VLOOKUP($A22,takstblad,8,FALSE)*H22,"fejl i år"),0) -> 0 | Y22: =+IFERROR(IF(Y$19=Takstblad!I$3,VLOOKUP($A22,takstblad,9,FALSE)*I22,"fejl i år"),0) -> 0 | Z22: =+IFERROR(IF(Z$19=Takstblad!J$3,VLOOKUP($A22,takstblad,10,FALSE)*J22,"fejl i år"),0) -> 0 | AA22: =+IFERROR(IF(AA$19=Takstblad!K$3,VLOOKUP($A22,takstblad,11,FALSE)*K22,"fejl i år"),0) -> 0 | AB22: =+IFERROR(IF(AB$19=Takstblad!L$3,VLOOKUP($A22,takstblad,12,FALSE)*L22,"fejl i år"),0) -> 0 | AC22: =SUM(S22:AB22) -> 0 | AE22: =+M22*($C$7/12) -> 0 | AF22: =IFERROR(AC22/AE22,0) -> 0 | AH22: =+C22*($C$7/12) -> 0 | AI22: =IFERROR(S22/AH22,0) -> 0 | AK22: =+D22*($C$7/12) -> 0 | AL22: =IFERROR(T22/AK22,0) -> 0 | AN22: =+E22*($C$7/12) -> 0 | AO22: =IFERROR(U22/AN22,0) -> 0 | AQ22: =+F22*($C$7/12) -> 0 | AR22: =IFERROR(V22/AQ22,0) -> 0 | AT22: =+G22*($C$7/12) -> 0 | AU22: =IFERROR(W22/AT22,0) -> 0 | AW22: =+H22*($C$7/12) -> 0 | AX22: =IFERROR(X22/AW22,0) -> 0 | AZ22: =+I22*($C$7/12) -> 0 | BA22: =IFERROR(Y22/AZ22,0) -> 0 | BC22: =+J22*($C$7/12) -> 0 | BD22: =IFERROR(Z22/BC22,0) -> 0 | BF22: =+K22*($C$7/12) -> 0 | BG22: =IFERROR(AA22/BF22,0) -> 0 | BI22: =+L22*($C$7/12) -> 0 | BJ22: =IFERROR(AB22/BI22,0) -> 0
A23: "Choose job position" | B23: =+VLOOKUP(A23,Takstblad!$A$5:$B$30,2,FALSE) | M23: =SUM(C23:L23) -> 0 | O23: External funding | R23: =+AC23 -> 0 | S23: =+IFERROR(IF(S$19=Takstblad!C$3,VLOOKUP($A23,takstblad,3,FALSE)*C23,"fejl i år"),0) -> 0 | T23: =+IFERROR(IF(T$19=Takstblad!D$3,VLOOKUP($A23,takstblad,4,FALSE)*D23,"fejl i år"),0) -> 0 | U23: =+IFERROR(IF(U$19=Takstblad!E$3,VLOOKUP($A23,takstblad,5,FALSE)*E23,"fejl i år"),0) -> 0 | V23: =+IFERROR(IF(V$19=Takstblad!F$3,VLOOKUP($A23,takstblad,6,FALSE)*F23,"fejl i år"),0) -> 0 | W23: =+IFERROR(IF(W$19=Takstblad!G$3,VLOOKUP($A23,takstblad,7,FALSE)*G23,"fejl i år"),0) -> 0 | X23: =+IFERROR(IF(X$19=Takstblad!H$3,VLOOKUP($A23,takstblad,8,FALSE)*H23,"fejl i år"),0) -> 0 | Y23: =+IFERROR(IF(Y$19=Takstblad!I$3,VLOOKUP($A23,takstblad,9,FALSE)*I23,"fejl i år"),0) -> 0 | Z23: =+IFERROR(IF(Z$19=Takstblad!J$3,VLOOKUP($A23,takstblad,10,FALSE)*J23,"fejl i år"),0) -> 0 | AA23: =+IFERROR(IF(AA$19=Takstblad!K$3,VLOOKUP($A23,takstblad,11,FALSE)*K23,"fejl i år"),0) -> 0 | AB23: =+IFERROR(IF(AB$19=Takstblad!L$3,VLOOKUP($A23,takstblad,12,FALSE)*L23,"fejl i år"),0) -> 0 | AC23: =SUM(S23:AB23) -> 0 | AE23: =+M23*($C$7/12) -> 0 | AF23: =IFERROR(AC23/AE23,0) -> 0 | AH23: =+C23*($C$7/12) -> 0 | AI23: =IFERROR(S23/AH23,0) -> 0 | AK23: =+D23*($C$7/12) -> 0 | AL23: =IFERROR(T23/AK23,0) -> 0 | AN23: =+E23*($C$7/12) -> 0 | AO23: =IFERROR(U23/AN23,0) -> 0 | AQ23: =+F23*($C$7/12) -> 0 | AR23: =IFERROR(V23/AQ23,0) -> 0 | AT23: =+G23*($C$7/12) -> 0 | AU23: =IFERROR(W23/AT23,0) -> 0 | AW23: =+H23*($C$7/12) -> 0 | AX23: =IFERROR(X23/AW23,0) -> 0 | AZ23: =+I23*($C$7/12) -> 0 | BA23: =IFERROR(Y23/AZ23,0) -> 0 | BC23: =+J23*($C$7/12) -> 0 | BD23: =IFERROR(Z23/BC23,0) -> 0 | BF23: =+K23*($C$7/12) -> 0 | BG23: =IFERROR(AA23/BF23,0) -> 0 | BI23: =+L23*($C$7/12) -> 0 | BJ23: =IFERROR(AB23/BI23,0) -> 0
A24: "Choose job position" | B24: =+VLOOKUP(A24,Takstblad!$A$5:$B$30,2,FALSE) | M24: =SUM(C24:L24) -> 0 | O24: External funding | R24: =+AC24 -> 0 | S24: =+IFERROR(IF(S$19=Takstblad!C$3,VLOOKUP($A24,takstblad,3,FALSE)*C24,"fejl i år"),0) -> 0 | T24: =+IFERROR(IF(T$19=Takstblad!D$3,VLOOKUP($A24,takstblad,4,FALSE)*D24,"fejl i år"),0) -> 0 | U24: =+IFERROR(IF(U$19=Takstblad!E$3,VLOOKUP($A24,takstblad,5,FALSE)*E24,"fejl i år"),0) -> 0 | V24: =+IFERROR(IF(V$19=Takstblad!F$3,VLOOKUP($A24,takstblad,6,FALSE)*F24,"fejl i år"),0) -> 0 | W24: =+IFERROR(IF(W$19=Takstblad!G$3,VLOOKUP($A24,takstblad,7,FALSE)*G24,"fejl i år"),0) -> 0 | X24: =+IFERROR(IF(X$19=Takstblad!H$3,VLOOKUP($A24,takstblad,8,FALSE)*H24,"fejl i år"),0) -> 0 | Y24: =+IFERROR(IF(Y$19=Takstblad!I$3,VLOOKUP($A24,takstblad,9,FALSE)*I24,"fejl i år"),0) -> 0 | Z24: =+IFERROR(IF(Z$19=Takstblad!J$3,VLOOKUP($A24,takstblad,10,FALSE)*J24,"fejl i år"),0) -> 0 | AA24: =+IFERROR(IF(AA$19=Takstblad!K$3,VLOOKUP($A24,takstblad,11,FALSE)*K24,"fejl i år"),0) -> 0 | AB24: =+IFERROR(IF(AB$19=Takstblad!L$3,VLOOKUP($A24,takstblad,12,FALSE)*L24,"fejl i år"),0) -> 0 | AC24: =SUM(S24:AB24) -> 0 | AE24: =+M24*($C$7/12) -> 0 | AF24: =IFERROR(AC24/AE24,0) -> 0 | AH24: =+C24*($C$7/12) -> 0 | AI24: =IFERROR(S24/AH24,0) -> 0 | AK24: =+D24*($C$7/12) -> 0 | AL24: =IFERROR(T24/AK24,0) -> 0 | AN24: =+E24*($C$7/12) -> 0 | AO24: =IFERROR(U24/AN24,0) -> 0 | AQ24: =+F24*($C$7/12) -> 0 | AR24: =IFERROR(V24/AQ24,0) -> 0 | AT24: =+G24*($C$7/12) -> 0 | AU24: =IFERROR(W24/AT24,0) -> 0 | AW24: =+H24*($C$7/12) -> 0 | AX24: =IFERROR(X24/AW24,0) -> 0 | AZ24: =+I24*($C$7/12) -> 0 | BA24: =IFERROR(Y24/AZ24,0) -> 0 | BC24: =+J24*($C$7/12) -> 0 | BD24: =IFERROR(Z24/BC24,0) -> 0 | BF24: =+K24*($C$7/12) -> 0 | BG24: =IFERROR(AA24/BF24,0) -> 0 | BI24: =+L24*($C$7/12) -> 0 | BJ24: =IFERROR(AB24/BI24,0) -> 0
A25: "Choose job position" | B25: =+VLOOKUP(A25,Takstblad!$A$5:$B$30,2,FALSE) | M25: =SUM(C25:L25) -> 0 | O25: External funding | R25: =+AC25 -> 0 | S25: =+IFERROR(IF(S$19=Takstblad!C$3,VLOOKUP($A25,takstblad,3,FALSE)*C25,"fejl i år"),0) -> 0 | T25: =+IFERROR(IF(T$19=Takstblad!D$3,VLOOKUP($A25,takstblad,4,FALSE)*D25,"fejl i år"),0) -> 0 | U25: =+IFERROR(IF(U$19=Takstblad!E$3,VLOOKUP($A25,takstblad,5,FALSE)*E25,"fejl i år"),0) -> 0 | V25: =+IFERROR(IF(V$19=Takstblad!F$3,VLOOKUP($A25,takstblad,6,FALSE)*F25,"fejl i år"),0) -> 0 | W25: =+IFERROR(IF(W$19=Takstblad!G$3,VLOOKUP($A25,takstblad,7,FALSE)*G25,"fejl i år"),0) -> 0 | X25: =+IFERROR(IF(X$19=Takstblad!H$3,VLOOKUP($A25,takstblad,8,FALSE)*H25,"fejl i år"),0) -> 0 | Y25: =+IFERROR(IF(Y$19=Takstblad!I$3,VLOOKUP($A25,takstblad,9,FALSE)*I25,"fejl i år"),0) -> 0 | Z25: =+IFERROR(IF(Z$19=Takstblad!J$3,VLOOKUP($A25,takstblad,10,FALSE)*J25,"fejl i år"),0) -> 0 | AA25: =+IFERROR(IF(AA$19=Takstblad!K$3,VLOOKUP($A25,takstblad,11,FALSE)*K25,"fejl i år"),0) -> 0 | AB25: =+IFERROR(IF(AB$19=Takstblad!L$3,VLOOKUP($A25,takstblad,12,FALSE)*L25,"fejl i år"),0) -> 0 | AC25: =SUM(S25:AB25) -> 0 | AE25: =+M25*($C$7/12) -> 0 | AF25: =IFERROR(AC25/AE25,0) -> 0 | AH25: =+C25*($C$7/12) -> 0 | AI25: =IFERROR(S25/AH25,0) -> 0 | AK25: =+D25*($C$7/12) -> 0 | AL25: =IFERROR(T25/AK25,0) -> 0 | AN25: =+E25*($C$7/12) -> 0 | AO25: =IFERROR(U25/AN25,0) -> 0 | AQ25: =+F25*($C$7/12) -> 0 | AR25: =IFERROR(V25/AQ25,0) -> 0 | AT25: =+G25*($C$7/12) -> 0 | AU25: =IFERROR(W25/AT25,0) -> 0 | AW25: =+H25*($C$7/12) -> 0 | AX25: =IFERROR(X25/AW25,0) -> 0 | AZ25: =+I25*($C$7/12) -> 0 | BA25: =IFERROR(Y25/AZ25,0) -> 0 | BC25: =+J25*($C$7/12) -> 0 | BD25: =IFERROR(Z25/BC25,0) -> 0 | BF25: =+K25*($C$7/12) -> 0 | BG25: =IFERROR(AA25/BF25,0) -> 0 | BI25: =+L25*($C$7/12) -> 0 | BJ25: =IFERROR(AB25/BI25,0) -> 0
A26: "Choose job position" | B26: =+VLOOKUP(A26,Takstblad!$A$5:$B$30,2,FALSE) | M26: =SUM(C26:L26) -> 0 | O26: External funding | R26: =+AC26 -> 0 | S26: =+IFERROR(IF(S$19=Takstblad!C$3,VLOOKUP($A26,takstblad,3,FALSE)*C26,"fejl i år"),0) -> 0 | T26: =+IFERROR(IF(T$19=Takstblad!D$3,VLOOKUP($A26,takstblad,4,FALSE)*D26,"fejl i år"),0) -> 0 | U26: =+IFERROR(IF(U$19=Takstblad!E$3,VLOOKUP($A26,takstblad,5,FALSE)*E26,"fejl i år"),0) -> 0 | V26: =+IFERROR(IF(V$19=Takstblad!F$3,VLOOKUP($A26,takstblad,6,FALSE)*F26,"fejl i år"),0) -> 0 | W26: =+IFERROR(IF(W$19=Takstblad!G$3,VLOOKUP($A26,takstblad,7,FALSE)*G26,"fejl i år"),0) -> 0 | X26: =+IFERROR(IF(X$19=Takstblad!H$3,VLOOKUP($A26,takstblad,8,FALSE)*H26,"fejl i år"),0) -> 0 | Y26: =+IFERROR(IF(Y$19=Takstblad!I$3,VLOOKUP($A26,takstblad,9,FALSE)*I26,"fejl i år"),0) -> 0 | Z26: =+IFERROR(IF(Z$19=Takstblad!J$3,VLOOKUP($A26,takstblad,10,FALSE)*J26,"fejl i år"),0) -> 0 | AA26: =+IFERROR(IF(AA$19=Takstblad!K$3,VLOOKUP($A26,takstblad,11,FALSE)*K26,"fejl i år"),0) -> 0 | AB26: =+IFERROR(IF(AB$19=Takstblad!L$3,VLOOKUP($A26,takstblad,12,FALSE)*L26,"fejl i år"),0) -> 0 | AC26: =SUM(S26:AB26) -> 0 | AE26: =+M26*($C$7/12) -> 0 | AF26: =IFERROR(AC26/AE26,0) -> 0 | AH26: =+C26*($C$7/12) -> 0 | AI26: =IFERROR(S26/AH26,0) -> 0 | AK26: =+D26*($C$7/12) -> 0 | AL26: =IFERROR(T26/AK26,0) -> 0 | AN26: =+E26*($C$7/12) -> 0 | AO26: =IFERROR(U26/AN26,0) -> 0 | AQ26: =+F26*($C$7/12) -> 0 | AR26: =IFERROR(V26/AQ26,0) -> 0 | AT26: =+G26*($C$7/12) -> 0 | AU26: =IFERROR(W26/AT26,0) -> 0 | AW26: =+H26*($C$7/12) -> 0 | AX26: =IFERROR(X26/AW26,0) -> 0 | AZ26: =+I26*($C$7/12) -> 0 | BA26: =IFERROR(Y26/AZ26,0) -> 0 | BC26: =+J26*($C$7/12) -> 0 | BD26: =IFERROR(Z26/BC26,0) -> 0 | BF26: =+K26*($C$7/12) -> 0 | BG26: =IFERROR(AA26/BF26,0) -> 0 | BI26: =+L26*($C$7/12) -> 0 | BJ26: =IFERROR(AB26/BI26,0) -> 0
A27: "Choose job position" | B27: =+VLOOKUP(A27,Takstblad!$A$5:$B$30,2,FALSE) | M27: =SUM(C27:L27) -> 0 | O27: External funding | R27: =+AC27 -> 0 | S27: =+IFERROR(IF(S$19=Takstblad!C$3,VLOOKUP($A27,takstblad,3,FALSE)*C27,"fejl i år"),0) -> 0 | T27: =+IFERROR(IF(T$19=Takstblad!D$3,VLOOKUP($A27,takstblad,4,FALSE)*D27,"fejl i år"),0) -> 0 | U27: =+IFERROR(IF(U$19=Takstblad!E$3,VLOOKUP($A27,takstblad,5,FALSE)*E27,"fejl i år"),0) -> 0 | V27: =+IFERROR(IF(V$19=Takstblad!F$3,VLOOKUP($A27,takstblad,6,FALSE)*F27,"fejl i år"),0) -> 0 | W27: =+IFERROR(IF(W$19=Takstblad!G$3,VLOOKUP($A27,takstblad,7,FALSE)*G27,"fejl i år"),0) -> 0 | X27: =+IFERROR(IF(X$19=Takstblad!H$3,VLOOKUP($A27,takstblad,8,FALSE)*H27,"fejl i år"),0) -> 0 | Y27: =+IFERROR(IF(Y$19=Takstblad!I$3,VLOOKUP($A27,takstblad,9,FALSE)*I27,"fejl i år"),0) -> 0 | Z27: =+IFERROR(IF(Z$19=Takstblad!J$3,VLOOKUP($A27,takstblad,10,FALSE)*J27,"fejl i år"),0) -> 0 | AA27: =+IFERROR(IF(AA$19=Takstblad!K$3,VLOOKUP($A27,takstblad,11,FALSE)*K27,"fejl i år"),0) -> 0 | AB27: =+IFERROR(IF(AB$19=Takstblad!L$3,VLOOKUP($A27,takstblad,12,FALSE)*L27,"fejl i år"),0) -> 0 | AC27: =SUM(S27:AB27) -> 0 | AE27: =+M27*($C$7/12) -> 0 | AF27: =IFERROR(AC27/AE27,0) -> 0 | AH27: =+C27*($C$7/12) -> 0 | AI27: =IFERROR(S27/AH27,0) -> 0 | AK27: =+D27*($C$7/12) -> 0 | AL27: =IFERROR(T27/AK27,0) -> 0 | AN27: =+E27*($C$7/12) -> 0 | AO27: =IFERROR(U27/AN27,0) -> 0 | AQ27: =+F27*($C$7/12) -> 0 | AR27: =IFERROR(V27/AQ27,0) -> 0 | AT27: =+G27*($C$7/12) -> 0 | AU27: =IFERROR(W27/AT27,0) -> 0 | AW27: =+H27*($C$7/12) -> 0 | AX27: =IFERROR(X27/AW27,0) -> 0 | AZ27: =+I27*($C$7/12) -> 0 | BA27: =IFERROR(Y27/AZ27,0) -> 0 | BC27: =+J27*($C$7/12) -> 0 | BD27: =IFERROR(Z27/BC27,0) -> 0 | BF27: =+K27*($C$7/12) -> 0 | BG27: =IFERROR(AA27/BF27,0) -> 0 | BI27: =+L27*($C$7/12) -> 0 | BJ27: =IFERROR(AB27/BI27,0) -> 0
A28: "Choose job position" | B28: =+VLOOKUP(A28,Takstblad!$A$5:$B$30,2,FALSE) | M28: =SUM(C28:L28) -> 0 | O28: External funding | R28: =+AC28 -> 0 | S28: =+IFERROR(IF(S$19=Takstblad!C$3,VLOOKUP($A28,takstblad,3,FALSE)*C28,"fejl i år"),0) -> 0 | T28: =+IFERROR(IF(T$19=Takstblad!D$3,VLOOKUP($A28,takstblad,4,FALSE)*D28,"fejl i år"),0) -> 0 | U28: =+IFERROR(IF(U$19=Takstblad!E$3,VLOOKUP($A28,takstblad,5,FALSE)*E28,"fejl i år"),0) -> 0 | V28: =+IFERROR(IF(V$19=Takstblad!F$3,VLOOKUP($A28,takstblad,6,FALSE)*F28,"fejl i år"),0) -> 0 | W28: =+IFERROR(IF(W$19=Takstblad!G$3,VLOOKUP($A28,takstblad,7,FALSE)*G28,"fejl i år"),0) -> 0 | X28: =+IFERROR(IF(X$19=Takstblad!H$3,VLOOKUP($A28,takstblad,8,FALSE)*H28,"fejl i år"),0) -> 0 | Y28: =+IFERROR(IF(Y$19=Takstblad!I$3,VLOOKUP($A28,takstblad,9,FALSE)*I28,"fejl i år"),0) -> 0 | Z28: =+IFERROR(IF(Z$19=Takstblad!J$3,VLOOKUP($A28,takstblad,10,FALSE)*J28,"fejl i år"),0) -> 0 | AA28: =+IFERROR(IF(AA$19=Takstblad!K$3,VLOOKUP($A28,takstblad,11,FALSE)*K28,"fejl i år"),0) -> 0 | AB28: =+IFERROR(IF(AB$19=Takstblad!L$3,VLOOKUP($A28,takstblad,12,FALSE)*L28,"fejl i år"),0) -> 0 | AC28: =SUM(S28:AB28) -> 0 | AE28: =+M28*($C$7/12) -> 0 | AF28: =IFERROR(AC28/AE28,0) -> 0 | AH28: =+C28*($C$7/12) -> 0 | AI28: =IFERROR(S28/AH28,0) -> 0 | AK28: =+D28*($C$7/12) -> 0 | AL28: =IFERROR(T28/AK28,0) -> 0 | AN28: =+E28*($C$7/12) -> 0 | AO28: =IFERROR(U28/AN28,0) -> 0 | AQ28: =+F28*($C$7/12) -> 0 | AR28: =IFERROR(V28/AQ28,0) -> 0 | AT28: =+G28*($C$7/12) -> 0 | AU28: =IFERROR(W28/AT28,0) -> 0 | AW28: =+H28*($C$7/12) -> 0 | AX28: =IFERROR(X28/AW28,0) -> 0 | AZ28: =+I28*($C$7/12) -> 0 | BA28: =IFERROR(Y28/AZ28,0) -> 0 | BC28: =+J28*($C$7/12) -> 0 | BD28: =IFERROR(Z28/BC28,0) -> 0 | BF28: =+K28*($C$7/12) -> 0 | BG28: =IFERROR(AA28/BF28,0) -> 0 | BI28: =+L28*($C$7/12) -> 0 | BJ28: =IFERROR(AB28/BI28,0) -> 0
A29: "Choose job position" | B29: =+VLOOKUP(A29,Takstblad!$A$5:$B$30,2,FALSE) | M29: =SUM(C29:L29) -> 0 | O29: External funding | R29: =+AC29 -> 0 | S29: =+IFERROR(IF(S$19=Takstblad!C$3,VLOOKUP($A29,takstblad,3,FALSE)*C29,"fejl i år"),0) -> 0 | T29: =+IFERROR(IF(T$19=Takstblad!D$3,VLOOKUP($A29,takstblad,4,FALSE)*D29,"fejl i år"),0) -> 0 | U29: =+IFERROR(IF(U$19=Takstblad!E$3,VLOOKUP($A29,takstblad,5,FALSE)*E29,"fejl i år"),0) -> 0 | V29: =+IFERROR(IF(V$19=Takstblad!F$3,VLOOKUP($A29,takstblad,6,FALSE)*F29,"fejl i år"),0) -> 0 | W29: =+IFERROR(IF(W$19=Takstblad!G$3,VLOOKUP($A29,takstblad,7,FALSE)*G29,"fejl i år"),0) -> 0 | X29: =+IFERROR(IF(X$19=Takstblad!H$3,VLOOKUP($A29,takstblad,8,FALSE)*H29,"fejl i år"),0) -> 0 | Y29: =+IFERROR(IF(Y$19=Takstblad!I$3,VLOOKUP($A29,takstblad,9,FALSE)*I29,"fejl i år"),0) -> 0 | Z29: =+IFERROR(IF(Z$19=Takstblad!J$3,VLOOKUP($A29,takstblad,10,FALSE)*J29,"fejl i år"),0) -> 0 | AA29: =+IFERROR(IF(AA$19=Takstblad!K$3,VLOOKUP($A29,takstblad,11,FALSE)*K29,"fejl i år"),0) -> 0 | AB29: =+IFERROR(IF(AB$19=Takstblad!L$3,VLOOKUP($A29,takstblad,12,FALSE)*L29,"fejl i år"),0) -> 0 | AC29: =SUM(S29:AB29) -> 0 | AE29: =+M29*($C$7/12) -> 0 | AF29: =IFERROR(AC29/AE29,0) -> 0 | AH29: =+C29*($C$7/12) -> 0 | AI29: =IFERROR(S29/AH29,0) -> 0 | AK29: =+D29*($C$7/12) -> 0 | AL29: =IFERROR(T29/AK29,0) -> 0 | AN29: =+E29*($C$7/12) -> 0 | AO29: =IFERROR(U29/AN29,0) -> 0 | AQ29: =+F29*($C$7/12) -> 0 | AR29: =IFERROR(V29/AQ29,0) -> 0 | AT29: =+G29*($C$7/12) -> 0 | AU29: =IFERROR(W29/AT29,0) -> 0 | AW29: =+H29*($C$7/12) -> 0 | AX29: =IFERROR(X29/AW29,0) -> 0 | AZ29: =+I29*($C$7/12) -> 0 | BA29: =IFERROR(Y29/AZ29,0) -> 0 | BC29: =+J29*($C$7/12) -> 0 | BD29: =IFERROR(Z29/BC29,0) -> 0 | BF29: =+K29*($C$7/12) -> 0 | BG29: =IFERROR(AA29/BF29,0) -> 0 | BI29: =+L29*($C$7/12) -> 0 | BJ29: =IFERROR(AB29/BI29,0) -> 0
A30: "Choose job position" | B30: =+VLOOKUP(A30,Takstblad!$A$5:$B$30,2,FALSE) | M30: =SUM(C30:L30) -> 0 | O30: External funding | R30: =+AC30 -> 0 | S30: =+IFERROR(IF(S$19=Takstblad!C$3,VLOOKUP($A30,takstblad,3,FALSE)*C30,"fejl i år"),0) -> 0 | T30: =+IFERROR(IF(T$19=Takstblad!D$3,VLOOKUP($A30,takstblad,4,FALSE)*D30,"fejl i år"),0) -> 0 | U30: =+IFERROR(IF(U$19=Takstblad!E$3,VLOOKUP($A30,takstblad,5,FALSE)*E30,"fejl i år"),0) -> 0 | V30: =+IFERROR(IF(V$19=Takstblad!F$3,VLOOKUP($A30,takstblad,6,FALSE)*F30,"fejl i år"),0) -> 0 | W30: =+IFERROR(IF(W$19=Takstblad!G$3,VLOOKUP($A30,takstblad,7,FALSE)*G30,"fejl i år"),0) -> 0 | X30: =+IFERROR(IF(X$19=Takstblad!H$3,VLOOKUP($A30,takstblad,8,FALSE)*H30,"fejl i år"),0) -> 0 | Y30: =+IFERROR(IF(Y$19=Takstblad!I$3,VLOOKUP($A30,takstblad,9,FALSE)*I30,"fejl i år"),0) -> 0 | Z30: =+IFERROR(IF(Z$19=Takstblad!J$3,VLOOKUP($A30,takstblad,10,FALSE)*J30,"fejl i år"),0) -> 0 | AA30: =+IFERROR(IF(AA$19=Takstblad!K$3,VLOOKUP($A30,takstblad,11,FALSE)*K30,"fejl i år"),0) -> 0 | AB30: =+IFERROR(IF(AB$19=Takstblad!L$3,VLOOKUP($A30,takstblad,12,FALSE)*L30,"fejl i år"),0) -> 0 | AC30: =SUM(S30:AB30) -> 0 | AE30: =+M30*($C$7/12) -> 0 | AF30: =IFERROR(AC30/AE30,0) -> 0 | AH30: =+C30*($C$7/12) -> 0 | AI30: =IFERROR(S30/AH30,0) -> 0 | AK30: =+D30*($C$7/12) -> 0 | AL30: =IFERROR(T30/AK30,0) -> 0 | AN30: =+E30*($C$7/12) -> 0 | AO30: =IFERROR(U30/AN30,0) -> 0 | AQ30: =+F30*($C$7/12) -> 0 | AR30: =IFERROR(V30/AQ30,0) -> 0 | AT30: =+G30*($C$7/12) -> 0 | AU30: =IFERROR(W30/AT30,0) -> 0 | AW30: =+H30*($C$7/12) -> 0 | AX30: =IFERROR(X30/AW30,0) -> 0 | AZ30: =+I30*($C$7/12) -> 0 | BA30: =IFERROR(Y30/AZ30,0) -> 0 | BC30: =+J30*($C$7/12) -> 0 | BD30: =IFERROR(Z30/BC30,0) -> 0 | BF30: =+K30*($C$7/12) -> 0 | BG30: =IFERROR(AA30/BF30,0) -> 0 | BI30: =+L30*($C$7/12) -> 0 | BJ30: =IFERROR(AB30/BI30,0) -> 0
A31: "Choose job position" | B31: =+VLOOKUP(A31,Takstblad!$A$5:$B$30,2,FALSE) | M31: =SUM(C31:L31) -> 0 | O31: External funding | R31: =+AC31 -> 0 | S31: =+IFERROR(IF(S$19=Takstblad!C$3,VLOOKUP($A31,takstblad,3,FALSE)*C31,"fejl i år"),0) -> 0 | T31: =+IFERROR(IF(T$19=Takstblad!D$3,VLOOKUP($A31,takstblad,4,FALSE)*D31,"fejl i år"),0) -> 0 | U31: =+IFERROR(IF(U$19=Takstblad!E$3,VLOOKUP($A31,takstblad,5,FALSE)*E31,"fejl i år"),0) -> 0 | V31: =+IFERROR(IF(V$19=Takstblad!F$3,VLOOKUP($A31,takstblad,6,FALSE)*F31,"fejl i år"),0) -> 0 | W31: =+IFERROR(IF(W$19=Takstblad!G$3,VLOOKUP($A31,takstblad,7,FALSE)*G31,"fejl i år"),0) -> 0 | X31: =+IFERROR(IF(X$19=Takstblad!H$3,VLOOKUP($A31,takstblad,8,FALSE)*H31,"fejl i år"),0) -> 0 | Y31: =+IFERROR(IF(Y$19=Takstblad!I$3,VLOOKUP($A31,takstblad,9,FALSE)*I31,"fejl i år"),0) -> 0 | Z31: =+IFERROR(IF(Z$19=Takstblad!J$3,VLOOKUP($A31,takstblad,10,FALSE)*J31,"fejl i år"),0) -> 0 | AA31: =+IFERROR(IF(AA$19=Takstblad!K$3,VLOOKUP($A31,takstblad,11,FALSE)*K31,"fejl i år"),0) -> 0 | AB31: =+IFERROR(IF(AB$19=Takstblad!L$3,VLOOKUP($A31,takstblad,12,FALSE)*L31,"fejl i år"),0) -> 0 | AC31: =SUM(S31:AB31) -> 0 | AE31: =+M31*($C$7/12) -> 0 | AF31: =IFERROR(AC31/AE31,0) -> 0 | AH31: =+C31*($C$7/12) -> 0 | AI31: =IFERROR(S31/AH31,0) -> 0 | AK31: =+D31*($C$7/12) -> 0 | AL31: =IFERROR(T31/AK31,0) -> 0 | AN31: =+E31*($C$7/12) -> 0 | AO31: =IFERROR(U31/AN31,0) -> 0 | AQ31: =+F31*($C$7/12) -> 0 | AR31: =IFERROR(V31/AQ31,0) -> 0 | AT31: =+G31*($C$7/12) -> 0 | AU31: =IFERROR(W31/AT31,0) -> 0 | AW31: =+H31*($C$7/12) -> 0 | AX31: =IFERROR(X31/AW31,0) -> 0 | AZ31: =+I31*($C$7/12) -> 0 | BA31: =IFERROR(Y31/AZ31,0) -> 0 | BC31: =+J31*($C$7/12) -> 0 | BD31: =IFERROR(Z31/BC31,0) -> 0 | BF31: =+K31*($C$7/12) -> 0 | BG31: =IFERROR(AA31/BF31,0) -> 0 | BI31: =+L31*($C$7/12) -> 0 | BJ31: =IFERROR(AB31/BI31,0) -> 0
... A39: "Choose job position" | B39: =+VLOOKUP(A39,Takstblad!$A$5:$B$30,2,FALSE) | M39: =SUM(C39:L39) -> 0 | O39: External funding | R39: =+AC39 -> 0 | S39: =+IFERROR(IF(S$19=Takstblad!C$3,VLOOKUP($A39,takstblad,3,FALSE)*C39,"fejl i år"),0) -> 0 | T39: =+IFERROR(IF(T$19=Takstblad!D$3,VLOOKUP($A39,takstblad,4,FALSE)*D39,"fejl i år"),0) -> 0 | U39: =+IFERROR(IF(U$19=Takstblad!E$3,VLOOKUP($A39,takstblad,5,FALSE)*E39,"fejl i år"),0) -> 0 | V39: =+IFERROR(IF(V$19=Takstblad!F$3,VLOOKUP($A39,takstblad,6,FALSE)*F39,"fejl i år"),0) -> 0 | W39: =+IFERROR(IF(W$19=Takstblad!G$3,VLOOKUP($A39,takstblad,7,FALSE)*G39,"fejl i år"),0) -> 0 | X39: =+IFERROR(IF(X$19=Takstblad!H$3,VLOOKUP($A39,takstblad,8,FALSE)*H39,"fejl i år"),0) -> 0 | Y39: =+IFERROR(IF(Y$19=Takstblad!I$3,VLOOKUP($A39,takstblad,9,FALSE)*I39,"fejl i år"),0) -> 0 | Z39: =+IFERROR(IF(Z$19=Takstblad!J$3,VLOOKUP($A39,takstblad,10,FALSE)*J39,"fejl i år"),0) -> 0 | AA39: =+IFERROR(IF(AA$19=Takstblad!K$3,VLOOKUP($A39,takstblad,11,FALSE)*K39,"fejl i år"),0) -> 0 | AB39: =+IFERROR(IF(AB$19=Takstblad!L$3,VLOOKUP($A39,takstblad,12,FALSE)*L39,"fejl i år"),0) -> 0 | AC39: =SUM(S39:AB39) -> 0 | AE39: =+M39*($C$7/12) -> 0 | AF39: =IFERROR(AC39/AE39,0) -> 0 | AH39: =+C39*($C$7/12) -> 0 | AI39: =IFERROR(S39/AH39,0) -> 0 | AK39: =+D39*($C$7/12) -> 0 | AL39: =IFERROR(T39/AK39,0) -> 0 | AN39: =+E39*($C$7/12) -> 0 | AO39: =IFERROR(U39/AN39,0) -> 0 | AQ39: =+F39*($C$7/12) -> 0 | AR39: =IFERROR(V39/AQ39,0) -> 0 | AT39: =+G39*($C$7/12) -> 0 | AU39: =IFERROR(W39/AT39,0) -> 0 | AW39: =+H39*($C$7/12) -> 0 | AX39: =IFERROR(X39/AW39,0) -> 0 | AZ39: =+I39*($C$7/12) -> 0 | BA39: =IFERROR(Y39/AZ39,0) -> 0 | BC39: =+J39*($C$7/12) -> 0 | BD39: =IFERROR(Z39/BC39,0) -> 0 | BF39: =+K39*($C$7/12) -> 0 | BG39: =IFERROR(AA39/BF39,0) -> 0 | BI39: =+L39*($C$7/12) -> 0 | BJ39: =IFERROR(AB39/BI39,0) -> 0
A40: Total VIP-months | C40: =SUM(C20:C39) -> 0 | D40: =SUM(D20:D39) -> 0 | E40: =SUM(E20:E39) -> 0 | F40: =SUM(F20:F39) -> 0 | G40: =SUM(G20:G39) -> 0 | H40: =SUM(H20:H39) -> 0 | I40: =SUM(I20:I39) -> 0 | J40: =SUM(J20:J39) -> 0 | ... M40: =SUM(M20:M39) -> 0 | Q40: VIP-salary total | R40: =+AC40 -> 0 | S40: =SUM(S20:S39) -> 0 | T40: =SUM(T20:T39) -> 0 | U40: =SUM(U20:U39) -> 0 | V40: =SUM(V20:V39) -> 0 | W40: =SUM(W20:W39) -> 0 | X40: =SUM(X20:X39) -> 0 | Y40: =SUM(Y20:Y39) -> 0 | Z40: =SUM(Z20:Z39) -> 0 | ... AB40: =SUM(AB20:AB39) -> 0 | AC40: =SUM(S40:AB40) -> 0 | AE40: =SUM(AE20:AE39) -> 0 | AF40: =IFERROR(AC40/AE40,0) -> 0 | AH40: =SUM(AH20:AH39) -> 0 | AI40: =IFERROR(S40/AH40,0) -> 0 | AK40: =SUM(AK20:AK39) -> 0 | AL40: =IFERROR(T40/AK40,0) -> 0 | AN40: =SUM(AN20:AN39) -> 0 | AO40: =IFERROR(U40/AN40,0) -> 0 | AQ40: =SUM(AQ20:AQ39) -> 0 | AR40: =IFERROR(V40/AQ40,0) -> 0 | AT40: =SUM(AT20:AT39) -> 0 | AU40: =IFERROR(W40/AT40,0) -> 0 | AW40: =SUM(AW20:AW39) -> 0 | AX40: =IFERROR(X40/AW40,0) -> 0 | AZ40: =SUM(AZ20:AZ39) -> 0 | BA40: =IFERROR(Z40/AZ40,0) -> 0 | BC40: =SUM(BC20:BC39) -> 0 | BD40: =IFERROR(Z40/BC40,0) -> 0 | BF40: =SUM(BF20:BF39) -> 0 | BG40: =IFERROR(AC40/BF40,0) -> 0 | BI40: =SUM(BI20:BI39) -> 0 | BJ40: =IFERROR(AF40/BI40,0) -> 0
A42: Choose TAP and insert count of months | C42: =+C19 -> 2026 | D42: =+D19 -> 2027 | E42: =+E19 -> 2028 | F42: =+F19 -> 2029 | G42: =+G19 -> 2030 | H42: =+H19 -> 2031 | I42: =+I19 -> 2032 | J42: =+J19 -> 2033 | ... L42: =+L19 -> 2035 | M42: Total | Q42: TAP-salary | R42: Total | S42: =+C19 -> 2026 | T42: =+D19 -> 2027 | U42: =+E19 -> 2028 | V42: =+F19 -> 2029 | W42: =+G19 -> 2030 | X42: =+H19 -> 2031 | Y42: =+I19 -> 2032 | Z42: =+J19 -> 2033 | ... AB42: =+L19 -> 2035 | AC42: Total | AE42: Total | AH42: =+AH19 -> 2026 | AK42: =+AK19 -> 2027 | AN42: =+AN19 -> 2028 | AQ42: =+AQ19 -> 2029 | AT42: =+AT19 -> 2030 | AW42: =+AW19 -> 2031 | AZ42: =+AZ19 -> 2032 | BC42: =+BC19 -> 2033 | BF42: =+BF19 -> 2034 | BI42: =+BI19 -> 2035
A43: "Choose job position" | B43: =+VLOOKUP(A43,Takstblad!$A$33:$B$54,2,FALSE) | M43: =SUM(C43:L43) -> 0 | O43: External funding | R43: =+AC43 -> 0 | S43: =+IFERROR(IF(S$19=Takstblad!C$3,VLOOKUP($A43,takstblad,3,FALSE)*C43,"fejl i år"),0) -> 0 | T43: =+IFERROR(IF(T$19=Takstblad!D$3,VLOOKUP($A43,takstblad,4,FALSE)*D43,"fejl i år"),0) -> 0 | U43: =+IFERROR(IF(U$19=Takstblad!E$3,VLOOKUP($A43,takstblad,5,FALSE)*E43,"fejl i år"),0) -> 0 | V43: =+IFERROR(IF(V$19=Takstblad!F$3,VLOOKUP($A43,takstblad,6,FALSE)*F43,"fejl i år"),0) -> 0 | W43: =+IFERROR(IF(W$19=Takstblad!G$3,VLOOKUP($A43,takstblad,7,FALSE)*G43,"fejl i år"),0) -> 0 | X43: =+IFERROR(IF(X$19=Takstblad!H$3,VLOOKUP($A43,takstblad,8,FALSE)*H43,"fejl i år"),0) -> 0 | Y43: =+IFERROR(IF(Y$19=Takstblad!I$3,VLOOKUP($A43,takstblad,9,FALSE)*I43,"fejl i år"),0) -> 0 | Z43: =+IFERROR(IF(Z$19=Takstblad!J$3,VLOOKUP($A43,takstblad,10,FALSE)*J43,"fejl i år"),0) -> 0 | AA43: =+IFERROR(IF(AA$19=Takstblad!K$3,VLOOKUP($A43,takstblad,11,FALSE)*K43,"fejl i år"),0) -> 0 | AB43: =+IFERROR(IF(AB$19=Takstblad!L$3,VLOOKUP($A43,takstblad,12,FALSE)*L43,"fejl i år"),0) -> 0 | AC43: =SUM(S43:AB43) -> 0 | AE43: =+M43*($C$7/12) -> 0 | AF43: =IFERROR(AC43/AE43,0) -> 0 | AH43: =+C43*($C$7/12) -> 0 | AI43: =IFERROR(S43/AH43,0) -> 0 | AK43: =+D43*($C$7/12) -> 0 | AL43: =IFERROR(T43/AK43,0) -> 0 | AN43: =+E43*($C$7/12) -> 0 | AO43: =IFERROR(U43/AN43,0) -> 0 | AQ43: =+F43*($C$7/12) -> 0 | AR43: =IFERROR(V43/AQ43,0) -> 0 | AT43: =+G43*($C$7/12) -> 0 | AU43: =IFERROR(W43/AT43,0) -> 0 | AW43: =+H43*($C$7/12) -> 0 | AX43: =IFERROR(X43/AW43,0) -> 0 | AZ43: =+I43*($C$7/12) -> 0 | BA43: =IFERROR(Y43/AZ43,0) -> 0 | BC43: =+J43*($C$7/12) -> 0 | BD43: =IFERROR(Z43/BC43,0) -> 0 | BF43: =+K43*($C$7/12) -> 0 | BG43: =IFERROR(AB43/BF43,0) -> 0 | BI43: =+L43*($C$7/12) -> 0 | BJ43: =IFERROR(AB43/BI43,0) -> 0
A44: "Choose job position" | B44: =+VLOOKUP(A44,Takstblad!$A$33:$B$54,2,FALSE) | M44: =SUM(C44:L44) -> 0 | O44: External funding | R44: =+AC44 -> 0 | S44: =+IFERROR(IF(S$19=Takstblad!C$3,VLOOKUP($A44,takstblad,3,FALSE)*C44,"fejl i år"),0) -> 0 | T44: =+IFERROR(IF(T$19=Takstblad!D$3,VLOOKUP($A44,takstblad,4,FALSE)*D44,"fejl i år"),0) -> 0 | U44: =+IFERROR(IF(U$19=Takstblad!E$3,VLOOKUP($A44,takstblad,5,FALSE)*E44,"fejl i år"),0) -> 0 | V44: =+IFERROR(IF(V$19=Takstblad!F$3,VLOOKUP($A44,takstblad,6,FALSE)*F44,"fejl i år"),0) -> 0 | W44: =+IFERROR(IF(W$19=Takstblad!G$3,VLOOKUP($A44,takstblad,7,FALSE)*G44,"fejl i år"),0) -> 0 | X44: =+IFERROR(IF(X$19=Takstblad!H$3,VLOOKUP($A44,takstblad,8,FALSE)*H44,"fejl i år"),0) -> 0 | Y44: =+IFERROR(IF(Y$19=Takstblad!I$3,VLOOKUP($A44,takstblad,9,FALSE)*I44,"fejl i år"),0) -> 0 | Z44: =+IFERROR(IF(Z$19=Takstblad!J$3,VLOOKUP($A44,takstblad,10,FALSE)*J44,"fejl i år"),0) -> 0 | AA44: =+IFERROR(IF(AA$19=Takstblad!K$3,VLOOKUP($A44,takstblad,11,FALSE)*K44,"fejl i år"),0) -> 0 | AB44: =+IFERROR(IF(AB$19=Takstblad!L$3,VLOOKUP($A44,takstblad,12,FALSE)*L44,"fejl i år"),0) -> 0 | AC44: =SUM(S44:AB44) -> 0 | AE44: =+M44*($C$7/12) -> 0 | AF44: =IFERROR(AC44/AE44,0) -> 0 | AH44: =+C44*($C$7/12) -> 0 | AI44: =IFERROR(S44/AH44,0) -> 0 | AK44: =+D44*($C$7/12) -> 0 | AL44: =IFERROR(T44/AK44,0) -> 0 | AN44: =+E44*($C$7/12) -> 0 | AO44: =IFERROR(U44/AN44,0) -> 0 | AQ44: =+F44*($C$7/12) -> 0 | AR44: =IFERROR(V44/AQ44,0) -> 0 | AT44: =+G44*($C$7/12) -> 0 | AU44: =IFERROR(W44/AT44,0) -> 0 | AW44: =+H44*($C$7/12) -> 0 | AX44: =IFERROR(X44/AW44,0) -> 0 | AZ44: =+I44*($C$7/12) -> 0 | BA44: =IFERROR(Y44/AZ44,0) -> 0 | BC44: =+J44*($C$7/12) -> 0 | BD44: =IFERROR(Z44/BC44,0) -> 0 | BF44: =+K44*($C$7/12) -> 0 | BG44: =IFERROR(AB44/BF44,0) -> 0 | BI44: =+L44*($C$7/12) -> 0 | BJ44: =IFERROR(AB44/BI44,0) -> 0
A45: "Choose job position" | B45: =+VLOOKUP(A45,Takstblad!$A$33:$B$54,2,FALSE) | M45: =SUM(C45:L45) -> 0 | O45: External funding | R45: =+AC45 -> 0 | S45: =+IFERROR(IF(S$19=Takstblad!C$3,VLOOKUP($A45,takstblad,3,FALSE)*C45,"fejl i år"),0) -> 0 | T45: =+IFERROR(IF(T$19=Takstblad!D$3,VLOOKUP($A45,takstblad,4,FALSE)*D45,"fejl i år"),0) -> 0 | U45: =+IFERROR(IF(U$19=Takstblad!E$3,VLOOKUP($A45,takstblad,5,FALSE)*E45,"fejl i år"),0) -> 0 | V45: =+IFERROR(IF(V$19=Takstblad!F$3,VLOOKUP($A45,takstblad,6,FALSE)*F45,"fejl i år"),0) -> 0 | W45: =+IFERROR(IF(W$19=Takstblad!G$3,VLOOKUP($A45,takstblad,7,FALSE)*G45,"fejl i år"),0) -> 0 | X45: =+IFERROR(IF(X$19=Takstblad!H$3,VLOOKUP($A45,takstblad,8,FALSE)*H45,"fejl i år"),0) -> 0 | Y45: =+IFERROR(IF(Y$19=Takstblad!I$3,VLOOKUP($A45,takstblad,9,FALSE)*I45,"fejl i år"),0) -> 0 | Z45: =+IFERROR(IF(Z$19=Takstblad!J$3,VLOOKUP($A45,takstblad,10,FALSE)*J45,"fejl i år"),0) -> 0 | AA45: =+IFERROR(IF(AA$19=Takstblad!K$3,VLOOKUP($A45,takstblad,11,FALSE)*K45,"fejl i år"),0) -> 0 | AB45: =+IFERROR(IF(AB$19=Takstblad!L$3,VLOOKUP($A45,takstblad,12,FALSE)*L45,"fejl i år"),0) -> 0 | AC45: =SUM(S45:AB45) -> 0 | AE45: =+M45*($C$7/12) -> 0 | AF45: =IFERROR(AC45/AE45,0) -> 0 | AH45: =+C45*($C$7/12) -> 0 | AI45: =IFERROR(S45/AH45,0) -> 0 | AK45: =+D45*($C$7/12) -> 0 | AL45: =IFERROR(T45/AK45,0) -> 0 | AN45: =+E45*($C$7/12) -> 0 | AO45: =IFERROR(U45/AN45,0) -> 0 | AQ45: =+F45*($C$7/12) -> 0 | AR45: =IFERROR(V45/AQ45,0) -> 0 | AT45: =+G45*($C$7/12) -> 0 | AU45: =IFERROR(W45/AT45,0) -> 0 | AW45: =+H45*($C$7/12) -> 0 | AX45: =IFERROR(X45/AW45,0) -> 0 | AZ45: =+I45*($C$7/12) -> 0 | BA45: =IFERROR(Y45/AZ45,0) -> 0 | BC45: =+J45*($C$7/12) -> 0 | BD45: =IFERROR(Z45/BC45,0) -> 0 | BF45: =+K45*($C$7/12) -> 0 | BG45: =IFERROR(AB45/BF45,0) -> 0 | BI45: =+L45*($C$7/12) -> 0 | BJ45: =IFERROR(AB45/BI45,0) -> 0
A46: "Choose job position" | B46: =+VLOOKUP(A46,Takstblad!$A$33:$B$54,2,FALSE) | M46: =SUM(C46:L46) -> 0 | O46: External funding | R46: =+AC46 -> 0 | S46: =+IFERROR(IF(S$19=Takstblad!C$3,VLOOKUP($A46,takstblad,3,FALSE)*C46,"fejl i år"),0) -> 0 | T46: =+IFERROR(IF(T$19=Takstblad!D$3,VLOOKUP($A46,takstblad,4,FALSE)*D46,"fejl i år"),0) -> 0 | U46: =+IFERROR(IF(U$19=Takstblad!E$3,VLOOKUP($A46,takstblad,5,FALSE)*E46,"fejl i år"),0) -> 0 | V46: =+IFERROR(IF(V$19=Takstblad!F$3,VLOOKUP($A46,takstblad,6,FALSE)*F46,"fejl i år"),0) -> 0 | W46: =+IFERROR(IF(W$19=Takstblad!G$3,VLOOKUP($A46,takstblad,7,FALSE)*G46,"fejl i år"),0) -> 0 | X46: =+IFERROR(IF(X$19=Takstblad!H$3,VLOOKUP($A46,takstblad,8,FALSE)*H46,"fejl i år"),0) -> 0 | Y46: =+IFERROR(IF(Y$19=Takstblad!I$3,VLOOKUP($A46,takstblad,9,FALSE)*I46,"fejl i år"),0) -> 0 | Z46: =+IFERROR(IF(Z$19=Takstblad!J$3,VLOOKUP($A46,takstblad,10,FALSE)*J46,"fejl i år"),0) -> 0 | AA46: =+IFERROR(IF(AA$19=Takstblad!K$3,VLOOKUP($A46,takstblad,11,FALSE)*K46,"fejl i år"),0) -> 0 | AB46: =+IFERROR(IF(AB$19=Takstblad!L$3,VLOOKUP($A46,takstblad,12,FALSE)*L46,"fejl i år"),0) -> 0 | AC46: =SUM(S46:AB46) -> 0 | AE46: =+M46*($C$7/12) -> 0 | AF46: =IFERROR(AC46/AE46,0) -> 0 | AH46: =+C46*($C$7/12) -> 0 | AI46: =IFERROR(S46/AH46,0) -> 0 | AK46: =+D46*($C$7/12) -> 0 | AL46: =IFERROR(T46/AK46,0) -> 0 | AN46: =+E46*($C$7/12) -> 0 | AO46: =IFERROR(U46/AN46,0) -> 0 | AQ46: =+F46*($C$7/12) -> 0 | AR46: =IFERROR(V46/AQ46,0) -> 0 | AT46: =+G46*($C$7/12) -> 0 | AU46: =IFERROR(W46/AT46,0) -> 0 | AW46: =+H46*($C$7/12) -> 0 | AX46: =IFERROR(X46/AW46,0) -> 0 | AZ46: =+I46*($C$7/12) -> 0 | BA46: =IFERROR(Y46/AZ46,0) -> 0 | BC46: =+J46*($C$7/12) -> 0 | BD46: =IFERROR(Z46/BC46,0) -> 0 | BF46: =+K46*($C$7/12) -> 0 | BG46: =IFERROR(AB46/BF46,0) -> 0 | BI46: =+L46*($C$7/12) -> 0 | BJ46: =IFERROR(AB46/BI46,0) -> 0
A47: "Choose job position" | B47: =+VLOOKUP(A47,Takstblad!$A$33:$B$54,2,FALSE) | M47: =SUM(C47:L47) -> 0 | O47: External funding | R47: =+AC47 -> 0 | S47: =+IFERROR(IF(S$19=Takstblad!C$3,VLOOKUP($A47,takstblad,3,FALSE)*C47,"fejl i år"),0) -> 0 | T47: =+IFERROR(IF(T$19=Takstblad!D$3,VLOOKUP($A47,takstblad,4,FALSE)*D47,"fejl i år"),0) -> 0 | U47: =+IFERROR(IF(U$19=Takstblad!E$3,VLOOKUP($A47,takstblad,5,FALSE)*E47,"fejl i år"),0) -> 0 | V47: =+IFERROR(IF(V$19=Takstblad!F$3,VLOOKUP($A47,takstblad,6,FALSE)*F47,"fejl i år"),0) -> 0 | W47: =+IFERROR(IF(W$19=Takstblad!G$3,VLOOKUP($A47,takstblad,7,FALSE)*G47,"fejl i år"),0) -> 0 | X47: =+IFERROR(IF(X$19=Takstblad!H$3,VLOOKUP($A47,takstblad,8,FALSE)*H47,"fejl i år"),0) -> 0 | Y47: =+IFERROR(IF(Y$19=Takstblad!I$3,VLOOKUP($A47,takstblad,9,FALSE)*I47,"fejl i år"),0) -> 0 | Z47: =+IFERROR(IF(Z$19=Takstblad!J$3,VLOOKUP($A47,takstblad,10,FALSE)*J47,"fejl i år"),0) -> 0 | AA47: =+IFERROR(IF(AA$19=Takstblad!K$3,VLOOKUP($A47,takstblad,11,FALSE)*K47,"fejl i år"),0) -> 0 | AB47: =+IFERROR(IF(AB$19=Takstblad!L$3,VLOOKUP($A47,takstblad,12,FALSE)*L47,"fejl i år"),0) -> 0 | AC47: =SUM(S47:AB47) -> 0 | AE47: =+M47*($C$7/12) -> 0 | AF47: =IFERROR(AC47/AE47,0) -> 0 | AH47: =+C47*($C$7/12) -> 0 | AI47: =IFERROR(S47/AH47,0) -> 0 | AK47: =+D47*($C$7/12) -> 0 | AL47: =IFERROR(T47/AK47,0) -> 0 | AN47: =+E47*($C$7/12) -> 0 | AO47: =IFERROR(U47/AN47,0) -> 0 | AQ47: =+F47*($C$7/12) -> 0 | AR47: =IFERROR(V47/AQ47,0) -> 0 | AT47: =+G47*($C$7/12) -> 0 | AU47: =IFERROR(W47/AT47,0) -> 0 | AW47: =+H47*($C$7/12) -> 0 | AX47: =IFERROR(X47/AW47,0) -> 0 | AZ47: =+I47*($C$7/12) -> 0 | BA47: =IFERROR(Y47/AZ47,0) -> 0 | BC47: =+J47*($C$7/12) -> 0 | BD47: =IFERROR(Z47/BC47,0) -> 0 | BF47: =+K47*($C$7/12) -> 0 | BG47: =IFERROR(AB47/BF47,0) -> 0 | BI47: =+L47*($C$7/12) -> 0 | BJ47: =IFERROR(AB47/BI47,0) -> 0
A48: "Choose job position" | B48: =+VLOOKUP(A48,Takstblad!$A$33:$B$54,2,FALSE) | M48: =SUM(C48:L48) -> 0 | O48: External funding | R48: =+AC48 -> 0 | S48: =+IFERROR(IF(S$19=Takstblad!C$3,VLOOKUP($A48,takstblad,3,FALSE)*C48,"fejl i år"),0) -> 0 | T48: =+IFERROR(IF(T$19=Takstblad!D$3,VLOOKUP($A48,takstblad,4,FALSE)*D48,"fejl i år"),0) -> 0 | U48: =+IFERROR(IF(U$19=Takstblad!E$3,VLOOKUP($A48,takstblad,5,FALSE)*E48,"fejl i år"),0) -> 0 | V48: =+IFERROR(IF(V$19=Takstblad!F$3,VLOOKUP($A48,takstblad,6,FALSE)*F48,"fejl i år"),0) -> 0 | W48: =+IFERROR(IF(W$19=Takstblad!G$3,VLOOKUP($A48,takstblad,7,FALSE)*G48,"fejl i år"),0) -> 0 | X48: =+IFERROR(IF(X$19=Takstblad!H$3,VLOOKUP($A48,takstblad,8,FALSE)*H48,"fejl i år"),0) -> 0 | Y48: =+IFERROR(IF(Y$19=Takstblad!I$3,VLOOKUP($A48,takstblad,9,FALSE)*I48,"fejl i år"),0) -> 0 | Z48: =+IFERROR(IF(Z$19=Takstblad!J$3,VLOOKUP($A48,takstblad,10,FALSE)*J48,"fejl i år"),0) -> 0 | AA48: =+IFERROR(IF(AA$19=Takstblad!K$3,VLOOKUP($A48,takstblad,11,FALSE)*K48,"fejl i år"),0) -> 0 | AB48: =+IFERROR(IF(AB$19=Takstblad!L$3,VLOOKUP($A48,takstblad,12,FALSE)*L48,"fejl i år"),0) -> 0 | AC48: =SUM(S48:AB48) -> 0 | AE48: =+M48*($C$7/12) -> 0 | AF48: =IFERROR(AC48/AE48,0) -> 0 | AH48: =+C48*($C$7/12) -> 0 | AI48: =IFERROR(S48/AH48,0) -> 0 | AK48: =+D48*($C$7/12) -> 0 | AL48: =IFERROR(T48/AK48,0) -> 0 | AN48: =+E48*($C$7/12) -> 0 | AO48: =IFERROR(U48/AN48,0) -> 0 | AQ48: =+F48*($C$7/12) -> 0 | AR48: =IFERROR(V48/AQ48,0) -> 0 | AT48: =+G48*($C$7/12) -> 0 | AU48: =IFERROR(W48/AT48,0) -> 0 | AW48: =+H48*($C$7/12) -> 0 | AX48: =IFERROR(X48/AW48,0) -> 0 | AZ48: =+I48*($C$7/12) -> 0 | BA48: =IFERROR(Y48/AZ48,0) -> 0 | BC48: =+J48*($C$7/12) -> 0 | BD48: =IFERROR(Z48/BC48,0) -> 0 | BF48: =+K48*($C$7/12) -> 0 | BG48: =IFERROR(AB48/BF48,0) -> 0 | BI48: =+L48*($C$7/12) -> 0 | BJ48: =IFERROR(AB48/BI48,0) -> 0
A49: "Choose job position" | B49: =+VLOOKUP(A49,Takstblad!$A$33:$B$54,2,FALSE) | M49: =SUM(C49:L49) -> 0 | O49: External funding | R49: =+AC49 -> 0 | S49: =+IFERROR(IF(S$19=Takstblad!C$3,VLOOKUP($A49,takstblad,3,FALSE)*C49,"fejl i år"),0) -> 0 | T49: =+IFERROR(IF(T$19=Takstblad!D$3,VLOOKUP($A49,takstblad,4,FALSE)*D49,"fejl i år"),0) -> 0 | U49: =+IFERROR(IF(U$19=Takstblad!E$3,VLOOKUP($A49,takstblad,5,FALSE)*E49,"fejl i år"),0) -> 0 | V49: =+IFERROR(IF(V$19=Takstblad!F$3,VLOOKUP($A49,takstblad,6,FALSE)*F49,"fejl i år"),0) -> 0 | W49: =+IFERROR(IF(W$19=Takstblad!G$3,VLOOKUP($A49,takstblad,7,FALSE)*G49,"fejl i år"),0) -> 0 | X49: =+IFERROR(IF(X$19=Takstblad!H$3,VLOOKUP($A49,takstblad,8,FALSE)*H49,"fejl i år"),0) -> 0 | Y49: =+IFERROR(IF(Y$19=Takstblad!I$3,VLOOKUP($A49,takstblad,9,FALSE)*I49,"fejl i år"),0) -> 0 | Z49: =+IFERROR(IF(Z$19=Takstblad!J$3,VLOOKUP($A49,takstblad,10,FALSE)*J49,"fejl i år"),0) -> 0 | AA49: =+IFERROR(IF(AA$19=Takstblad!K$3,VLOOKUP($A49,takstblad,11,FALSE)*K49,"fejl i år"),0) -> 0 | AB49: =+IFERROR(IF(AB$19=Takstblad!L$3,VLOOKUP($A49,takstblad,12,FALSE)*L49,"fejl i år"),0) -> 0 | AC49: =SUM(S49:AB49) -> 0 | AE49: =+M49*($C$7/12) -> 0 | AF49: =IFERROR(AC49/AE49,0) -> 0 | AH49: =+C49*($C$7/12) -> 0 | AI49: =IFERROR(S49/AH49,0) -> 0 | AK49: =+D49*($C$7/12) -> 0 | AL49: =IFERROR(T49/AK49,0) -> 0 | AN49: =+E49*($C$7/12) -> 0 | AO49: =IFERROR(U49/AN49,0) -> 0 | AQ49: =+F49*($C$7/12) -> 0 | AR49: =IFERROR(V49/AQ49,0) -> 0 | AT49: =+G49*($C$7/12) -> 0 | AU49: =IFERROR(W49/AT49,0) -> 0 | AW49: =+H49*($C$7/12) -> 0 | AX49: =IFERROR(X49/AW49,0) -> 0 | AZ49: =+I49*($C$7/12) -> 0 | BA49: =IFERROR(Y49/AZ49,0) -> 0 | BC49: =+J49*($C$7/12) -> 0 | BD49: =IFERROR(Z49/BC49,0) -> 0 | BF49: =+K49*($C$7/12) -> 0 | BG49: =IFERROR(AB49/BF49,0) -> 0 | BI49: =+L49*($C$7/12) -> 0 | BJ49: =IFERROR(AB49/BI49,0) -> 0
A50: "Choose job position" | B50: =+VLOOKUP(A50,Takstblad!$A$33:$B$54,2,FALSE) | M50: =SUM(C50:L50) -> 0 | O50: External funding | R50: =+AC50 -> 0 | S50: =+IFERROR(IF(S$19=Takstblad!C$3,VLOOKUP($A50,takstblad,3,FALSE)*C50,"fejl i år"),0) -> 0 | T50: =+IFERROR(IF(T$19=Takstblad!D$3,VLOOKUP($A50,takstblad,4,FALSE)*D50,"fejl i år"),0) -> 0 | U50: =+IFERROR(IF(U$19=Takstblad!E$3,VLOOKUP($A50,takstblad,5,FALSE)*E50,"fejl i år"),0) -> 0 | V50: =+IFERROR(IF(V$19=Takstblad!F$3,VLOOKUP($A50,takstblad,6,FALSE)*F50,"fejl i år"),0) -> 0 | W50: =+IFERROR(IF(W$19=Takstblad!G$3,VLOOKUP($A50,takstblad,7,FALSE)*G50,"fejl i år"),0) -> 0 | X50: =+IFERROR(IF(X$19=Takstblad!H$3,VLOOKUP($A50,takstblad,8,FALSE)*H50,"fejl i år"),0) -> 0 | Y50: =+IFERROR(IF(Y$19=Takstblad!I$3,VLOOKUP($A50,takstblad,9,FALSE)*I50,"fejl i år"),0) -> 0 | Z50: =+IFERROR(IF(Z$19=Takstblad!J$3,VLOOKUP($A50,takstblad,10,FALSE)*J50,"fejl i år"),0) -> 0 | AA50: =+IFERROR(IF(AA$19=Takstblad!K$3,VLOOKUP($A50,takstblad,11,FALSE)*K50,"fejl i år"),0) -> 0 | AB50: =+IFERROR(IF(AB$19=Takstblad!L$3,VLOOKUP($A50,takstblad,12,FALSE)*L50,"fejl i år"),0) -> 0 | AC50: =SUM(S50:AB50) -> 0 | AE50: =+M50*($C$7/12) -> 0 | AF50: =IFERROR(AC50/AE50,0) -> 0 | AH50: =+C50*($C$7/12) -> 0 | AI50: =IFERROR(S50/AH50,0) -> 0 | AK50: =+D50*($C$7/12) -> 0 | AL50: =IFERROR(T50/AK50,0) -> 0 | AN50: =+E50*($C$7/12) -> 0 | AO50: =IFERROR(U50/AN50,0) -> 0 | AQ50: =+F50*($C$7/12) -> 0 | AR50: =IFERROR(V50/AQ50,0) -> 0 | AT50: =+G50*($C$7/12) -> 0 | AU50: =IFERROR(W50/AT50,0) -> 0 | AW50: =+H50*($C$7/12) -> 0 | AX50: =IFERROR(X50/AW50,0) -> 0 | AZ50: =+I50*($C$7/12) -> 0 | BA50: =IFERROR(Y50/AZ50,0) -> 0 | BC50: =+J50*($C$7/12) -> 0 | BD50: =IFERROR(Z50/BC50,0) -> 0 | BF50: =+K50*($C$7/12) -> 0 | BG50: =IFERROR(AB50/BF50,0) -> 0 | BI50: =+L50*($C$7/12) -> 0 | BJ50: =IFERROR(AB50/BI50,0) -> 0
A51: "Choose job position" | B51: =+VLOOKUP(A51,Takstblad!$A$33:$B$54,2,FALSE) | M51: =SUM(C51:L51) -> 0 | O51: External funding | R51: =+AC51 -> 0 | S51: =+IFERROR(IF(S$19=Takstblad!C$3,VLOOKUP($A51,takstblad,3,FALSE)*C51,"fejl i år"),0) -> 0 | T51: =+IFERROR(IF(T$19=Takstblad!D$3,VLOOKUP($A51,takstblad,4,FALSE)*D51,"fejl i år"),0) -> 0 | U51: =+IFERROR(IF(U$19=Takstblad!E$3,VLOOKUP($A51,takstblad,5,FALSE)*E51,"fejl i år"),0) -> 0 | V51: =+IFERROR(IF(V$19=Takstblad!F$3,VLOOKUP($A51,takstblad,6,FALSE)*F51,"fejl i år"),0) -> 0 | W51: =+IFERROR(IF(W$19=Takstblad!G$3,VLOOKUP($A51,takstblad,7,FALSE)*G51,"fejl i år"),0) -> 0 | X51: =+IFERROR(IF(X$19=Takstblad!H$3,VLOOKUP($A51,takstblad,8,FALSE)*H51,"fejl i år"),0) -> 0 | Y51: =+IFERROR(IF(Y$19=Takstblad!I$3,VLOOKUP($A51,takstblad,9,FALSE)*I51,"fejl i år"),0) -> 0 | Z51: =+IFERROR(IF(Z$19=Takstblad!J$3,VLOOKUP($A51,takstblad,10,FALSE)*J51,"fejl i år"),0) -> 0 | AA51: =+IFERROR(IF(AA$19=Takstblad!K$3,VLOOKUP($A51,takstblad,11,FALSE)*K51,"fejl i år"),0) -> 0 | AB51: =+IFERROR(IF(AB$19=Takstblad!L$3,VLOOKUP($A51,takstblad,12,FALSE)*L51,"fejl i år"),0) -> 0 | AC51: =SUM(S51:AB51) -> 0 | AE51: =+M51*($C$7/12) -> 0 | AF51: =IFERROR(AC51/AE51,0) -> 0 | AH51: =+C51*($C$7/12) -> 0 | AI51: =IFERROR(S51/AH51,0) -> 0 | AK51: =+D51*($C$7/12) -> 0 | AL51: =IFERROR(T51/AK51,0) -> 0 | AN51: =+E51*($C$7/12) -> 0 | AO51: =IFERROR(U51/AN51,0) -> 0 | AQ51: =+F51*($C$7/12) -> 0 | AR51: =IFERROR(V51/AQ51,0) -> 0 | AT51: =+G51*($C$7/12) -> 0 | AU51: =IFERROR(W51/AT51,0) -> 0 | AW51: =+H51*($C$7/12) -> 0 | AX51: =IFERROR(X51/AW51,0) -> 0 | AZ51: =+I51*($C$7/12) -> 0 | BA51: =IFERROR(Y51/AZ51,0) -> 0 | BC51: =+J51*($C$7/12) -> 0 | BD51: =IFERROR(Z51/BC51,0) -> 0 | BF51: =+K51*($C$7/12) -> 0 | BG51: =IFERROR(AB51/BF51,0) -> 0 | BI51: =+L51*($C$7/12) -> 0 | BJ51: =IFERROR(AB51/BI51,0) -> 0
A52: "Choose job position" | B52: =+VLOOKUP(A52,Takstblad!$A$33:$B$54,2,FALSE) | M52: =SUM(C52:L52) -> 0 | O52: External funding | R52: =+AC52 -> 0 | S52: =+IFERROR(IF(S$19=Takstblad!C$3,VLOOKUP($A52,takstblad,3,FALSE)*C52,"fejl i år"),0) -> 0 | T52: =+IFERROR(IF(T$19=Takstblad!D$3,VLOOKUP($A52,takstblad,4,FALSE)*D52,"fejl i år"),0) -> 0 | U52: =+IFERROR(IF(U$19=Takstblad!E$3,VLOOKUP($A52,takstblad,5,FALSE)*E52,"fejl i år"),0) -> 0 | V52: =+IFERROR(IF(V$19=Takstblad!F$3,VLOOKUP($A52,takstblad,6,FALSE)*F52,"fejl i år"),0) -> 0 | W52: =+IFERROR(IF(W$19=Takstblad!G$3,VLOOKUP($A52,takstblad,7,FALSE)*G52,"fejl i år"),0) -> 0 | X52: =+IFERROR(IF(X$19=Takstblad!H$3,VLOOKUP($A52,takstblad,8,FALSE)*H52,"fejl i år"),0) -> 0 | Y52: =+IFERROR(IF(Y$19=Takstblad!I$3,VLOOKUP($A52,takstblad,9,FALSE)*I52,"fejl i år"),0) -> 0 | Z52: =+IFERROR(IF(Z$19=Takstblad!J$3,VLOOKUP($A52,takstblad,10,FALSE)*J52,"fejl i år"),0) -> 0 | AA52: =+IFERROR(IF(AA$19=Takstblad!K$3,VLOOKUP($A52,takstblad,11,FALSE)*K52,"fejl i år"),0) -> 0 | AB52: =+IFERROR(IF(AB$19=Takstblad!L$3,VLOOKUP($A52,takstblad,12,FALSE)*L52,"fejl i år"),0) -> 0 | AC52: =SUM(S52:AB52) -> 0 | AE52: =+M52*($C$7/12) -> 0 | AF52: =IFERROR(AC52/AE52,0) -> 0 | AH52: =+C52*($C$7/12) -> 0 | AI52: =IFERROR(S52/AH52,0) -> 0 | AK52: =+D52*($C$7/12) -> 0 | AL52: =IFERROR(T52/AK52,0) -> 0 | AN52: =+E52*($C$7/12) -> 0 | AO52: =IFERROR(U52/AN52,0) -> 0 | AQ52: =+F52*($C$7/12) -> 0 | AR52: =IFERROR(V52/AQ52,0) -> 0 | AT52: =+G52*($C$7/12) -> 0 | AU52: =IFERROR(W52/AT52,0) -> 0 | AW52: =+H52*($C$7/12) -> 0 | AX52: =IFERROR(X52/AW52,0) -> 0 | AZ52: =+I52*($C$7/12) -> 0 | BA52: =IFERROR(Y52/AZ52,0) -> 0 | BC52: =+J52*($C$7/12) -> 0 | BD52: =IFERROR(Z52/BC52,0) -> 0 | BF52: =+K52*($C$7/12) -> 0 | BG52: =IFERROR(AB52/BF52,0) -> 0 | BI52: =+L52*($C$7/12) -> 0 | BJ52: =IFERROR(AB52/BI52,0) -> 0
A53: Other Technical assistance TAP - Coverage | C53: =IF($C$12=2,0,IF(OR($G$7="Salary and operations",$G$7="Salary"),S53/Takstblad!C57,0)) -> 0 | D53: =IF($C$12=2,0,IF(OR($G$7="Salary and operations",$G$7="Salary"),T53/Takstblad!D57,0)) -> 0 | E53: =IF($C$12=2,0,IF(OR($G$7="Salary and operations",$G$7="Salary"),U53/Takstblad!E57,0)) -> 0 | F53: =IF($C$12=2,0,IF(OR($G$7="Salary and operations",$G$7="Salary"),V53/Takstblad!F57,0)) -> 0 | G53: =IF($C$12=2,0,IF(OR($G$7="Salary and operations",$G$7="Salary"),W53/Takstblad!G57,0)) -> 0 | H53: =IF($C$12=2,0,IF(OR($G$7="Salary and operations",$G$7="Salary"),X53/Takstblad!H57,0)) -> 0 | I53: =IF($C$12=2,0,IF(OR($G$7="Salary and operations",$G$7="Salary"),Y53/Takstblad!I57,0)) -> 0 | J53: =IF($C$12=2,0,IF(OR($G$7="Salary and operations",$G$7="Salary"),Z53/Takstblad!J57,0)) -> 0 | ... L53: =IF($C$12=2,0,IF(OR($G$7="Salary and operations",$G$7="Salary"),AB53/Takstblad!L57,0)) -> 0 | M53: =SUM(C53:L53) -> 0 | O53: Coverage | R53: =+AC53 -> 0 | S53: =IFERROR(IF($C$12=2,0,IF(OR($G$7="Salary and operations",$G$7="Salary"),VLOOKUP($C$2,Takstblad!$B$58:$L$70,2,FALSE)*C$58,0)),0) -> 0 | T53: =IFERROR(IF($C$12=2,0,IF(OR($G$7="Salary and operations",$G$7="Salary"),VLOOKUP($C$2,Takstblad!$B$58:$L$70,3,FALSE)*D$58,0)),0) -> 0 | U53: =IFERROR(IF($C$12=2,0,IF(OR($G$7="Salary and operations",$G$7="Salary"),VLOOKUP($C$2,Takstblad!$B$58:$L$70,4,FALSE)*E$58,0)),0) -> 0 | V53: =IFERROR(IF($C$12=2,0,IF(OR($G$7="Salary and operations",$G$7="Salary"),VLOOKUP($C$2,Takstblad!$B$58:$L$70,5,FALSE)*F$58,0)),0) -> 0 | W53: =IFERROR(IF($C$12=2,0,IF(OR($G$7="Salary and operations",$G$7="Salary"),VLOOKUP($C$2,Takstblad!$B$58:$L$70,6,FALSE)*G$58,0)),0) -> 0 | X53: =IFERROR(IF($C$12=2,0,IF(OR($G$7="Salary and operations",$G$7="Salary"),VLOOKUP($C$2,Takstblad!$B$58:$L$70,7,FALSE)*H$58,0)),0) -> 0 | Y53: =IFERROR(IF($C$12=2,0,IF(OR($G$7="salary and operations",$G$7="Salary"),VLOOKUP($C$2,Takstblad!$B$58:$L$70,8,FALSE)*I$58,0)),0) -> 0 | Z53: =IFERROR(IF($C$12=2,0,IF(OR($G$7="salary and operations",$G$7="Salary"),VLOOKUP($C$2,Takstblad!$B$58:$L$70,9,FALSE)*J$58,0)),0) -> 0 | AA53: =IFERROR(IF($C$12=2,0,IF(OR($G$7="salary and operations",$G$7="Salary"),VLOOKUP($C$2,Takstblad!$B$58:$L$70,10,FALSE)*K$58,0)),0) -> 0 | AB53: =IFERROR(IF($C$12=2,0,IF(OR($G$7="salary and operations",$G$7="Salary"),VLOOKUP($C$2,Takstblad!$B$58:$L$70,11,FALSE)*L$58,0)),0) -> 0 | AC53: =SUM(S53:AB53) -> 0 | AE53: =+M53*($C$7/12) -> 0 | AF53: =IFERROR(AC53/AE53,0) -> 0 | AH53: =+C53*($C$7/12) -> 0 | AI53: =IFERROR(S53/AH53,0) -> 0 | AK53: =+D53*($C$7/12) -> 0 | AL53: =IFERROR(T53/AK53,0) -> 0 | AN53: =+E53*($C$7/12) -> 0 | AO53: =IFERROR(U53/AN53,0) -> 0 | AQ53: =+F53*($C$7/12) -> 0 | AR53: =IFERROR(V53/AQ53,0) -> 0 | AT53: =+G53*($C$7/12) -> 0 | AU53: =IFERROR(W53/AT53,0) -> 0 | AW53: =+H53*($C$7/12) -> 0 | AX53: =IFERROR(X53/AW53,0) -> 0 | AZ53: =+I53*($C$7/12) -> 0 | BA53: =IFERROR(Y53/AZ53,0) -> 0 | BC53: =+J53*($C$7/12) -> 0 | BD53: =IFERROR(Z53/BC53,0) -> 0 | BF53: =+K53*($C$7/12) -> 0 | BG53: =IFERROR(AB53/BF53,0) -> 0 | BI53: =+L53*($C$7/12) -> 0 | BJ53: =IFERROR(AB53/BI53,0) -> 0
A54: Other Technical assistance TAP - Co-financing covered by department | C54: =IF($C$12=2,0,IF(OR($G$7="Salary and operations",$G$7="Salary"),S54/Takstblad!C57,0)) -> 0 | D54: =IF($C$12=2,0,IF(OR($G$7="Salary and operations",$G$7="Salary"),T54/Takstblad!D57,0)) -> 0 | E54: =IF($C$12=2,0,IF(OR($G$7="Salary and operations",$G$7="Salary"),U54/Takstblad!E57,0)) -> 0 | F54: =IF($C$12=2,0,IF(OR($G$7="Salary and operations",$G$7="Salary"),V54/Takstblad!F57,0)) -> 0 | G54: =IF($C$12=2,0,IF(OR($G$7="Salary and operations",$G$7="Salary"),W54/Takstblad!G57,0)) -> 0 | H54: =IF($C$12=2,0,IF(OR($G$7="Salary and operations",$G$7="Salary"),X54/Takstblad!H57,0)) -> 0 | I54: =IF($C$12=2,0,IF(OR($G$7="Salary and operations",$G$7="Salary"),Y54/Takstblad!I57,0)) -> 0 | J54: =IF($C$12=2,0,IF(OR($G$7="Salary and operations",$G$7="Salary"),Z54/Takstblad!J57,0)) -> 0 | ... L54: =IF($C$12=2,0,IF(OR($G$7="Salary and operations",$G$7="Salary"),AB54/Takstblad!L57,0)) -> 0 | M54: =SUM(C54:L54) -> 0 | O54: Co-financing covered by department | R54: =+AC54 -> 0 | S54: =IFERROR(IF($C$12=2,0,IF(OR($G$7="Salary and operations",$G$7="Salary"),VLOOKUP($C$2,Takstblad!$B$58:$L$70,2,FALSE)*C$59,0)),0) -> 0 | T54: =IFERROR(IF($C$12=2,0,IF(OR($G$7="Salary and operations",$G$7="Salary"),VLOOKUP($C$2,Takstblad!$B$58:$L$70,3,FALSE)*D$59,0)),0) -> 0 | U54: =IFERROR(IF($C$12=2,0,IF(OR($G$7="Salary and operations",$G$7="Salary"),VLOOKUP($C$2,Takstblad!$B$58:$L$70,4,FALSE)*E$59,0)),0) -> 0 | V54: =IFERROR(IF($C$12=2,0,IF(OR($G$7="Salary and operations",$G$7="Salary"),VLOOKUP($C$2,Takstblad!$B$58:$L$70,5,FALSE)*F$59,0)),0) -> 0 | W54: =IFERROR(IF($C$12=2,0,IF(OR($G$7="Salary and operations",$G$7="Salary"),VLOOKUP($C$2,Takstblad!$B$58:$L$70,6,FALSE)*G$59,0)),0) -> 0 | X54: =IFERROR(IF($C$12=2,0,IF(OR($G$7="Salary and operations",$G$7="Salary"),VLOOKUP($C$2,Takstblad!$B$58:$L$70,7,FALSE)*H$59,0)),0) -> 0 | Y54: =IFERROR(IF($C$12=2,0,IF(OR($G$7="salary and operations",$G$7="Salary"),VLOOKUP($C$2,Takstblad!$B$58:$L$70,8,FALSE)*I$59,0)),0) -> 0 | Z54: =IFERROR(IF($C$12=2,0,IF(OR($G$7="salary and operations",$G$7="Salary"),VLOOKUP($C$2,Takstblad!$B$58:$L$70,9,FALSE)*J$59,0)),0) -> 0 | AA54: =IFERROR(IF($C$12=2,0,IF(OR($G$7="salary and operations",$G$7="Salary"),VLOOKUP($C$2,Takstblad!$B$58:$L$70,10,FALSE)*K$59,0)),0) -> 0 | AB54: =IFERROR(IF($C$12=2,0,IF(OR($G$7="salary and operations",$G$7="Salary"),VLOOKUP($C$2,Takstblad!$B$58:$L$70,11,FALSE)*L$59,0)),0) -> 0 | AC54: =SUM(S54:AB54) -> 0 | AE54: =+M54*($C$7/12) -> 0 | AF54: =IFERROR(AC54/AE54,0) -> 0 | AH54: =+C54*($C$7/12) -> 0 | AI54: =IFERROR(S54/AH54,0) -> 0 | AK54: =+D54*($C$7/12) -> 0 | AL54: =IFERROR(T54/AK54,0) -> 0 | AN54: =+E54*($C$7/12) -> 0 | AO54: =IFERROR(U54/AN54,0) -> 0 | AQ54: =+F54*($C$7/12) -> 0 | AR54: =IFERROR(V54/AQ54,0) -> 0 | AT54: =+G54*($C$7/12) -> 0 | AU54: =IFERROR(W54/AT54,0) -> 0 | AW54: =+H54*($C$7/12) -> 0 | AX54: =IFERROR(X54/AW54,0) -> 0 | AZ54: =+I54*($C$7/12) -> 0 | BA54: =IFERROR(Y54/AZ54,0) -> 0 | BC54: =+J54*($C$7/12) -> 0 | BD54: =IFERROR(Z54/BC54,0) -> 0 | BF54: =+K54*($C$7/12) -> 0 | BG54: =IFERROR(AB54/BF54,0) -> 0 | BI54: =+L54*($C$7/12) -> 0 | BJ54: =IFERROR(AB54/BI54,0) -> 0
A55: Laboratory Support | C55: =IF($C$10="Yes",((SUMIFS(C$20:C$29,$O$20:$O$29,Lister!$D$29,$A$20:$A$29,Takstblad!$A$18)+SUMIFS(C$20:C$29,$O$20:$O$29,Lister!$D$29,$A$20:$A$29,Takstblad!$A$19)+SUMIFS(C$20:C$29,$O$20:$O$29,Lister!$D$29,$A$20:$A$29,Takstblad!$A$20)+SUMIFS(C$20:C$29,$O$20:$O$29,Lister!$D$29,$A$20:$A$29,Takstblad!$A$21)+SUMIFS(C$20:C$29,$O$20:$O$29,Lister!$D$29,$A$20:$A$29,Takstblad!$A$22)+SUMIFS(C$20:C$29,$O$20:$O$29,Lister!$D$29,$A$20:$A$29,Takstblad!$A$23)+SUMIFS(C$20:C$29,$O$20:$O$29,Lister!$D$30,$A$20:$A$29,Takstblad!$A$18)+SUMIFS(C$20:C$29,$O$20:$O$29,Lister!$D$30,$A$20:$A$29,Takstblad!$A$19)+SUMIFS(C$20:C$29,$O$20:$O$29,Lister!$D$30,$A$20:$A$29,Takstblad!$A$20)+SUMIFS(C$20:C$29,$O$20:$O$29,Lister!$D$30,$A$20:$A$29,Takstblad!$A$21)+SUMIFS(C$20:C$29,$O$20:$O$29,Lister!$D$30,$A$20:$A$29,Takstblad!$A$22)+SUMIFS(C$20:C$29,$O$20:$O$29,Lister!$D$30,$A$20:$A$29,Takstblad!$A$23))/12)*0.5+((+SUMIF($O$43:$O$52,Lister!$D$29,C$43:C$52)-SUMIFS(C$43:C$52,$O$43:$O$52,Lister!$D$29,$A$43:$A$52,Takstblad!$A$34)-SUMIFS(C$43:C$52,$O$43:$O$52,Lister!$D$29,$A$43:$A$52,Takstblad!$A$36)-SUMIFS(C$43:C$52,$O$43:$O$52,Lister!$D$29,$A$43:$A$52,Takstblad!$A$43)-SUMIFS(C$43:C$52,$O$43:$O$52,Lister!$D$29,$A$43:$A$52,Takstblad!$A$44)+SUMIF($O$43:$O$52,Lister!$D$30,C$43:C$52)-SUMIFS(C$43:C$52,$O$43:$O$52,Lister!$D$30,$A$43:$A$52,Takstblad!$A$34)-SUMIFS(C$43:C$52,$O$43:$O$52,Lister!$D$30,$A$43:$A$52,Takstblad!$A$36)-SUMIFS(C$43:C$52,$O$43:$O$52,Lister!$D$30,$A$43:$A$52,Takstblad!$A$43)-SUMIFS(C$43:C$52,$O$43:$O$52,Lister!$D$30,$A$43:$A$52,Takstblad!$A$44))*0.3),0) -> 0 | D55: =IF($C$10="Yes",((SUMIFS(D$20:D$29,$O$20:$O$29,Lister!$D$29,$A$20:$A$29,Takstblad!$A$18)+SUMIFS(D$20:D$29,$O$20:$O$29,Lister!$D$29,$A$20:$A$29,Takstblad!$A$19)+SUMIFS(D$20:D$29,$O$20:$O$29,Lister!$D$29,$A$20:$A$29,Takstblad!$A$20)+SUMIFS(D$20:D$29,$O$20:$O$29,Lister!$D$29,$A$20:$A$29,Takstblad!$A$21)+SUMIFS(D$20:D$29,$O$20:$O$29,Lister!$D$29,$A$20:$A$29,Takstblad!$A$22)+SUMIFS(D$20:D$29,$O$20:$O$29,Lister!$D$29,$A$20:$A$29,Takstblad!$A$23)+SUMIFS(D$20:D$29,$O$20:$O$29,Lister!$D$30,$A$20:$A$29,Takstblad!$A$18)+SUMIFS(D$20:D$29,$O$20:$O$29,Lister!$D$30,$A$20:$A$29,Takstblad!$A$19)+SUMIFS(D$20:D$29,$O$20:$O$29,Lister!$D$30,$A$20:$A$29,Takstblad!$A$20)+SUMIFS(D$20:D$29,$O$20:$O$29,Lister!$D$30,$A$20:$A$29,Takstblad!$A$21)+SUMIFS(D$20:D$29,$O$20:$O$29,Lister!$D$30,$A$20:$A$29,Takstblad!$A$22)+SUMIFS(D$20:D$29,$O$20:$O$29,Lister!$D$30,$A$20:$A$29,Takstblad!$A$23))/12)*0.5+((+SUMIF($O$43:$O$52,Lister!$D$29,D$43:D$52)-SUMIFS(D$43:D$52,$O$43:$O$52,Lister!$D$29,$A$43:$A$52,Takstblad!$A$34)-SUMIFS(D$43:D$52,$O$43:$O$52,Lister!$D$29,$A$43:$A$52,Takstblad!$A$36)-SUMIFS(D$43:D$52,$O$43:$O$52,Lister!$D$29,$A$43:$A$52,Takstblad!$A$43)-SUMIFS(D$43:D$52,$O$43:$O$52,Lister!$D$29,$A$43:$A$52,Takstblad!$A$44)+SUMIF($O$43:$O$52,Lister!$D$30,D$43:D$52)-SUMIFS(D$43:D$52,$O$43:$O$52,Lister!$D$30,$A$43:$A$52,Takstblad!$A$34)-SUMIFS(D$43:D$52,$O$43:$O$52,Lister!$D$30,$A$43:$A$52,Takstblad!$A$36)-SUMIFS(D$43:D$52,$O$43:$O$52,Lister!$D$30,$A$43:$A$52,Takstblad!$A$43)-SUMIFS(D$43:D$52,$O$43:$O$52,Lister!$D$30,$A$43:$A$52,Takstblad!$A$44))*0.3),0) -> 0 | E55: =IF($C$10="Yes",((SUMIFS(E$20:E$29,$O$20:$O$29,Lister!$D$29,$A$20:$A$29,Takstblad!$A$18)+SUMIFS(E$20:E$29,$O$20:$O$29,Lister!$D$29,$A$20:$A$29,Takstblad!$A$19)+SUMIFS(E$20:E$29,$O$20:$O$29,Lister!$D$29,$A$20:$A$29,Takstblad!$A$20)+SUMIFS(E$20:E$29,$O$20:$O$29,Lister!$D$29,$A$20:$A$29,Takstblad!$A$21)+SUMIFS(E$20:E$29,$O$20:$O$29,Lister!$D$29,$A$20:$A$29,Takstblad!$A$22)+SUMIFS(E$20:E$29,$O$20:$O$29,Lister!$D$29,$A$20:$A$29,Takstblad!$A$23)+SUMIFS(E$20:E$29,$O$20:$O$29,Lister!$D$30,$A$20:$A$29,Takstblad!$A$18)+SUMIFS(E$20:E$29,$O$20:$O$29,Lister!$D$30,$A$20:$A$29,Takstblad!$A$19)+SUMIFS(E$20:E$29,$O$20:$O$29,Lister!$D$30,$A$20:$A$29,Takstblad!$A$20)+SUMIFS(E$20:E$29,$O$20:$O$29,Lister!$D$30,$A$20:$A$29,Takstblad!$A$21)+SUMIFS(E$20:E$29,$O$20:$O$29,Lister!$D$30,$A$20:$A$29,Takstblad!$A$22)+SUMIFS(E$20:E$29,$O$20:$O$29,Lister!$D$30,$A$20:$A$29,Takstblad!$A$23))/12)*0.5+((+SUMIF($O$43:$O$52,Lister!$D$29,E$43:E$52)-SUMIFS(E$43:E$52,$O$43:$O$52,Lister!$D$29,$A$43:$A$52,Takstblad!$A$34)-SUMIFS(E$43:E$52,$O$43:$O$52,Lister!$D$29,$A$43:$A$52,Takstblad!$A$36)-SUMIFS(E$43:E$52,$O$43:$O$52,Lister!$D$29,$A$43:$A$52,Takstblad!$A$43)-SUMIFS(E$43:E$52,$O$43:$O$52,Lister!$D$29,$A$43:$A$52,Takstblad!$A$44)+SUMIF($O$43:$O$52,Lister!$D$30,E$43:E$52)-SUMIFS(E$43:E$52,$O$43:$O$52,Lister!$D$30,$A$43:$A$52,Takstblad!$A$34)-SUMIFS(E$43:E$52,$O$43:$O$52,Lister!$D$30,$A$43:$A$52,Takstblad!$A$36)-SUMIFS(E$43:E$52,$O$43:$O$52,Lister!$D$30,$A$43:$A$52,Takstblad!$A$43)-SUMIFS(E$43:E$52,$O$43:$O$52,Lister!$D$30,$A$43:$A$52,Takstblad!$A$44))*0.3),0) -> 0 | F55: =IF($C$10="Yes",((SUMIFS(F$20:F$29,$O$20:$O$29,Lister!$D$29,$A$20:$A$29,Takstblad!$A$18)+SUMIFS(F$20:F$29,$O$20:$O$29,Lister!$D$29,$A$20:$A$29,Takstblad!$A$19)+SUMIFS(F$20:F$29,$O$20:$O$29,Lister!$D$29,$A$20:$A$29,Takstblad!$A$20)+SUMIFS(F$20:F$29,$O$20:$O$29,Lister!$D$29,$A$20:$A$29,Takstblad!$A$21)+SUMIFS(F$20:F$29,$O$20:$O$29,Lister!$D$29,$A$20:$A$29,Takstblad!$A$22)+SUMIFS(F$20:F$29,$O$20:$O$29,Lister!$D$29,$A$20:$A$29,Takstblad!$A$23)+SUMIFS(F$20:F$29,$O$20:$O$29,Lister!$D$30,$A$20:$A$29,Takstblad!$A$18)+SUMIFS(F$20:F$29,$O$20:$O$29,Lister!$D$30,$A$20:$A$29,Takstblad!$A$19)+SUMIFS(F$20:F$29,$O$20:$O$29,Lister!$D$30,$A$20:$A$29,Takstblad!$A$20)+SUMIFS(F$20:F$29,$O$20:$O$29,Lister!$D$30,$A$20:$A$29,Takstblad!$A$21)+SUMIFS(F$20:F$29,$O$20:$O$29,Lister!$D$30,$A$20:$A$29,Takstblad!$A$22)+SUMIFS(F$20:F$29,$O$20:$O$29,Lister!$D$30,$A$20:$A$29,Takstblad!$A$23))/12)*0.5+((+SUMIF($O$43:$O$52,Lister!$D$29,F$43:F$52)-SUMIFS(F$43:F$52,$O$43:$O$52,Lister!$D$29,$A$43:$A$52,Takstblad!$A$34)-SUMIFS(F$43:F$52,$O$43:$O$52,Lister!$D$29,$A$43:$A$52,Takstblad!$A$36)-SUMIFS(F$43:F$52,$O$43:$O$52,Lister!$D$29,$A$43:$A$52,Takstblad!$A$43)-SUMIFS(F$43:F$52,$O$43:$O$52,Lister!$D$29,$A$43:$A$52,Takstblad!$A$44)+SUMIF($O$43:$O$52,Lister!$D$30,F$43:F$52)-SUMIFS(F$43:F$52,$O$43:$O$52,Lister!$D$30,$A$43:$A$52,Takstblad!$A$34)-SUMIFS(F$43:F$52,$O$43:$O$52,Lister!$D$30,$A$43:$A$52,Takstblad!$A$36)-SUMIFS(F$43:F$52,$O$43:$O$52,Lister!$D$30,$A$43:$A$52,Takstblad!$A$43)-SUMIFS(F$43:F$52,$O$43:$O$52,Lister!$D$30,$A$43:$A$52,Takstblad!$A$44))*0.3),0) -> 0 | G55: =IF($C$10="Yes",((SUMIFS(G$20:G$29,$O$20:$O$29,Lister!$D$29,$A$20:$A$29,Takstblad!$A$18)+SUMIFS(G$20:G$29,$O$20:$O$29,Lister!$D$29,$A$20:$A$29,Takstblad!$A$19)+SUMIFS(G$20:G$29,$O$20:$O$29,Lister!$D$29,$A$20:$A$29,Takstblad!$A$20)+SUMIFS(G$20:G$29,$O$20:$O$29,Lister!$D$29,$A$20:$A$29,Takstblad!$A$21)+SUMIFS(G$20:G$29,$O$20:$O$29,Lister!$D$29,$A$20:$A$29,Takstblad!$A$22)+SUMIFS(G$20:G$29,$O$20:$O$29,Lister!$D$29,$A$20:$A$29,Takstblad!$A$23)+SUMIFS(G$20:G$29,$O$20:$O$29,Lister!$D$30,$A$20:$A$29,Takstblad!$A$18)+SUMIFS(G$20:G$29,$O$20:$O$29,Lister!$D$30,$A$20:$A$29,Takstblad!$A$19)+SUMIFS(G$20:G$29,$O$20:$O$29,Lister!$D$30,$A$20:$A$29,Takstblad!$A$20)+SUMIFS(G$20:G$29,$O$20:$O$29,Lister!$D$30,$A$20:$A$29,Takstblad!$A$21)+SUMIFS(G$20:G$29,$O$20:$O$29,Lister!$D$30,$A$20:$A$29,Takstblad!$A$22)+SUMIFS(G$20:G$29,$O$20:$O$29,Lister!$D$30,$A$20:$A$29,Takstblad!$A$23))/12)*0.5+((+SUMIF($O$43:$O$52,Lister!$D$29,G$43:G$52)-SUMIFS(G$43:G$52,$O$43:$O$52,Lister!$D$29,$A$43:$A$52,Takstblad!$A$34)-SUMIFS(G$43:G$52,$O$43:$O$52,Lister!$D$29,$A$43:$A$52,Takstblad!$A$36)-SUMIFS(G$43:G$52,$O$43:$O$52,Lister!$D$29,$A$43:$A$52,Takstblad!$A$43)-SUMIFS(G$43:G$52,$O$43:$O$52,Lister!$D$29,$A$43:$A$52,Takstblad!$A$44)+SUMIF($O$43:$O$52,Lister!$D$30,G$43:G$52)-SUMIFS(G$43:G$52,$O$43:$O$52,Lister!$D$30,$A$43:$A$52,Takstblad!$A$34)-SUMIFS(G$43:G$52,$O$43:$O$52,Lister!$D$30,$A$43:$A$52,Takstblad!$A$36)-SUMIFS(G$43:G$52,$O$43:$O$52,Lister!$D$30,$A$43:$A$52,Takstblad!$A$43)-SUMIFS(G$43:G$52,$O$43:$O$52,Lister!$D$30,$A$43:$A$52,Takstblad!$A$44))*0.3),0) -> 0 | H55: =IF($C$10="Yes",((SUMIFS(H$20:H$29,$O$20:$O$29,Lister!$D$29,$A$20:$A$29,Takstblad!$A$18)+SUMIFS(H$20:H$29,$O$20:$O$29,Lister!$D$29,$A$20:$A$29,Takstblad!$A$19)+SUMIFS(H$20:H$29,$O$20:$O$29,Lister!$D$29,$A$20:$A$29,Takstblad!$A$20)+SUMIFS(H$20:H$29,$O$20:$O$29,Lister!$D$29,$A$20:$A$29,Takstblad!$A$21)+SUMIFS(H$20:H$29,$O$20:$O$29,Lister!$D$29,$A$20:$A$29,Takstblad!$A$22)+SUMIFS(H$20:H$29,$O$20:$O$29,Lister!$D$29,$A$20:$A$29,Takstblad!$A$23)+SUMIFS(H$20:H$29,$O$20:$O$29,Lister!$D$30,$A$20:$A$29,Takstblad!$A$18)+SUMIFS(H$20:H$29,$O$20:$O$29,Lister!$D$30,$A$20:$A$29,Takstblad!$A$19)+SUMIFS(H$20:H$29,$O$20:$O$29,Lister!$D$30,$A$20:$A$29,Takstblad!$A$20)+SUMIFS(H$20:H$29,$O$20:$O$29,Lister!$D$30,$A$20:$A$29,Takstblad!$A$21)+SUMIFS(H$20:H$29,$O$20:$O$29,Lister!$D$30,$A$20:$A$29,Takstblad!$A$22)+SUMIFS(H$20:H$29,$O$20:$O$29,Lister!$D$30,$A$20:$A$29,Takstblad!$A$23))/12)*0.5+((+SUMIF($O$43:$O$52,Lister!$D$29,H$43:H$52)-SUMIFS(H$43:H$52,$O$43:$O$52,Lister!$D$29,$A$43:$A$52,Takstblad!$A$34)-SUMIFS(H$43:H$52,$O$43:$O$52,Lister!$D$29,$A$43:$A$52,Takstblad!$A$36)-SUMIFS(H$43:H$52,$O$43:$O$52,Lister!$D$29,$A$43:$A$52,Takstblad!$A$43)-SUMIFS(H$43:H$52,$O$43:$O$52,Lister!$D$29,$A$43:$A$52,Takstblad!$A$44)+SUMIF($O$43:$O$52,Lister!$D$30,H$43:H$52)-SUMIFS(H$43:H$52,$O$43:$O$52,Lister!$D$30,$A$43:$A$52,Takstblad!$A$34)-SUMIFS(H$43:H$52,$O$43:$O$52,Lister!$D$30,$A$43:$A$52,Takstblad!$A$36)-SUMIFS(H$43:H$52,$O$43:$O$52,Lister!$D$30,$A$43:$A$52,Takstblad!$A$43)-SUMIFS(H$43:H$52,$O$43:$O$52,Lister!$D$30,$A$43:$A$52,Takstblad!$A$44))*0.3),0) -> 0 | I55: =IF($C$10="Yes",((SUMIFS(I$20:I$29,$O$20:$O$29,Lister!$D$29,$A$20:$A$29,Takstblad!$A$18)+SUMIFS(I$20:I$29,$O$20:$O$29,Lister!$D$29,$A$20:$A$29,Takstblad!$A$19)+SUMIFS(I$20:I$29,$O$20:$O$29,Lister!$D$29,$A$20:$A$29,Takstblad!$A$20)+SUMIFS(I$20:I$29,$O$20:$O$29,Lister!$D$29,$A$20:$A$29,Takstblad!$A$21)+SUMIFS(I$20:I$29,$O$20:$O$29,Lister!$D$29,$A$20:$A$29,Takstblad!$A$22)+SUMIFS(I$20:I$29,$O$20:$O$29,Lister!$D$29,$A$20:$A$29,Takstblad!$A$23)+SUMIFS(I$20:I$29,$O$20:$O$29,Lister!$D$30,$A$20:$A$29,Takstblad!$A$18)+SUMIFS(I$20:I$29,$O$20:$O$29,Lister!$D$30,$A$20:$A$29,Takstblad!$A$19)+SUMIFS(I$20:I$29,$O$20:$O$29,Lister!$D$30,$A$20:$A$29,Takstblad!$A$20)+SUMIFS(I$20:I$29,$O$20:$O$29,Lister!$D$30,$A$20:$A$29,Takstblad!$A$21)+SUMIFS(I$20:I$29,$O$20:$O$29,Lister!$D$30,$A$20:$A$29,Takstblad!$A$22)+SUMIFS(I$20:I$29,$O$20:$O$29,Lister!$D$30,$A$20:$A$29,Takstblad!$A$23))/12)*0.5+((+SUMIF($O$43:$O$52,Lister!$D$29,I$43:I$52)-SUMIFS(I$43:I$52,$O$43:$O$52,Lister!$D$29,$A$43:$A$52,Takstblad!$A$34)-SUMIFS(I$43:I$52,$O$43:$O$52,Lister!$D$29,$A$43:$A$52,Takstblad!$A$36)-SUMIFS(I$43:I$52,$O$43:$O$52,Lister!$D$29,$A$43:$A$52,Takstblad!$A$43)-SUMIFS(I$43:I$52,$O$43:$O$52,Lister!$D$29,$A$43:$A$52,Takstblad!$A$44)+SUMIF($O$43:$O$52,Lister!$D$30,I$43:I$52)-SUMIFS(I$43:I$52,$O$43:$O$52,Lister!$D$30,$A$43:$A$52,Takstblad!$A$34)-SUMIFS(I$43:I$52,$O$43:$O$52,Lister!$D$30,$A$43:$A$52,Takstblad!$A$36)-SUMIFS(I$43:I$52,$O$43:$O$52,Lister!$D$30,$A$43:$A$52,Takstblad!$A$43)-SUMIFS(I$43:I$52,$O$43:$O$52,Lister!$D$30,$A$43:$A$52,Takstblad!$A$44))*0.3),0) -> 0 | J55: =IF($C$10="Yes",((SUMIFS(J$20:J$29,$O$20:$O$29,Lister!$D$29,$A$20:$A$29,Takstblad!$A$18)+SUMIFS(J$20:J$29,$O$20:$O$29,Lister!$D$29,$A$20:$A$29,Takstblad!$A$19)+SUMIFS(J$20:J$29,$O$20:$O$29,Lister!$D$29,$A$20:$A$29,Takstblad!$A$20)+SUMIFS(J$20:J$29,$O$20:$O$29,Lister!$D$29,$A$20:$A$29,Takstblad!$A$21)+SUMIFS(J$20:J$29,$O$20:$O$29,Lister!$D$29,$A$20:$A$29,Takstblad!$A$22)+SUMIFS(J$20:J$29,$O$20:$O$29,Lister!$D$29,$A$20:$A$29,Takstblad!$A$23)+SUMIFS(J$20:J$29,$O$20:$O$29,Lister!$D$30,$A$20:$A$29,Takstblad!$A$18)+SUMIFS(J$20:J$29,$O$20:$O$29,Lister!$D$30,$A$20:$A$29,Takstblad!$A$19)+SUMIFS(J$20:J$29,$O$20:$O$29,Lister!$D$30,$A$20:$A$29,Takstblad!$A$20)+SUMIFS(J$20:J$29,$O$20:$O$29,Lister!$D$30,$A$20:$A$29,Takstblad!$A$21)+SUMIFS(J$20:J$29,$O$20:$O$29,Lister!$D$30,$A$20:$A$29,Takstblad!$A$22)+SUMIFS(J$20:J$29,$O$20:$O$29,Lister!$D$30,$A$20:$A$29,Takstblad!$A$23))/12)*0.5+((+SUMIF($O$43:$O$52,Lister!$D$29,J$43:J$52)-SUMIFS(J$43:J$52,$O$43:$O$52,Lister!$D$29,$A$43:$A$52,Takstblad!$A$34)-SUMIFS(J$43:J$52,$O$43:$O$52,Lister!$D$29,$A$43:$A$52,Takstblad!$A$36)-SUMIFS(J$43:J$52,$O$43:$O$52,Lister!$D$29,$A$43:$A$52,Takstblad!$A$43)-SUMIFS(J$43:J$52,$O$43:$O$52,Lister!$D$29,$A$43:$A$52,Takstblad!$A$44)+SUMIF($O$43:$O$52,Lister!$D$30,J$43:J$52)-SUMIFS(J$43:J$52,$O$43:$O$52,Lister!$D$30,$A$43:$A$52,Takstblad!$A$34)-SUMIFS(J$43:J$52,$O$43:$O$52,Lister!$D$30,$A$43:$A$52,Takstblad!$A$36)-SUMIFS(J$43:J$52,$O$43:$O$52,Lister!$D$30,$A$43:$A$52,Takstblad!$A$43)-SUMIFS(J$43:J$52,$O$43:$O$52,Lister!$D$30,$A$43:$A$52,Takstblad!$A$44))*0.3),0) -> 0 | ... L55: =IF($C$10="Yes",((SUMIFS(L$20:L$29,$O$20:$O$29,Lister!$D$29,$A$20:$A$29,Takstblad!$A$18)+SUMIFS(L$20:L$29,$O$20:$O$29,Lister!$D$29,$A$20:$A$29,Takstblad!$A$19)+SUMIFS(L$20:L$29,$O$20:$O$29,Lister!$D$29,$A$20:$A$29,Takstblad!$A$20)+SUMIFS(L$20:L$29,$O$20:$O$29,Lister!$D$29,$A$20:$A$29,Takstblad!$A$21)+SUMIFS(L$20:L$29,$O$20:$O$29,Lister!$D$29,$A$20:$A$29,Takstblad!$A$22)+SUMIFS(L$20:L$29,$O$20:$O$29,Lister!$D$29,$A$20:$A$29,Takstblad!$A$23)+SUMIFS(L$20:L$29,$O$20:$O$29,Lister!$D$30,$A$20:$A$29,Takstblad!$A$18)+SUMIFS(L$20:L$29,$O$20:$O$29,Lister!$D$30,$A$20:$A$29,Takstblad!$A$19)+SUMIFS(L$20:L$29,$O$20:$O$29,Lister!$D$30,$A$20:$A$29,Takstblad!$A$20)+SUMIFS(L$20:L$29,$O$20:$O$29,Lister!$D$30,$A$20:$A$29,Takstblad!$A$21)+SUMIFS(L$20:L$29,$O$20:$O$29,Lister!$D$30,$A$20:$A$29,Takstblad!$A$22)+SUMIFS(L$20:L$29,$O$20:$O$29,Lister!$D$30,$A$20:$A$29,Takstblad!$A$23))/12)*0.5+((+SUMIF($O$43:$O$52,Lister!$D$29,L$43:L$52)-SUMIFS(L$43:L$52,$O$43:$O$52,Lister!$D$29,$A$43:$A$52,Takstblad!$A$34)-SUMIFS(L$43:L$52,$O$43:$O$52,Lister!$D$29,$A$43:$A$52,Takstblad!$A$36)-SUMIFS(L$43:L$52,$O$43:$O$52,Lister!$D$29,$A$43:$A$52,Takstblad!$A$43)-SUMIFS(L$43:L$52,$O$43:$O$52,Lister!$D$29,$A$43:$A$52,Takstblad!$A$44)+SUMIF($O$43:$O$52,Lister!$D$30,L$43:L$52)-SUMIFS(L$43:L$52,$O$43:$O$52,Lister!$D$30,$A$43:$A$52,Takstblad!$A$34)-SUMIFS(L$43:L$52,$O$43:$O$52,Lister!$D$30,$A$43:$A$52,Takstblad!$A$36)-SUMIFS(L$43:L$52,$O$43:$O$52,Lister!$D$30,$A$43:$A$52,Takstblad!$A$43)-SUMIFS(L$43:L$52,$O$43:$O$52,Lister!$D$30,$A$43:$A$52,Takstblad!$A$44))*0.3),0) -> 0 | M55: =SUM(C55:L55) -> 0 | O55: Coverage | R55: =+AC55 -> 0 | S55: =+C55*Takstblad!C39 -> 0 | T55: =+D55*Takstblad!D39 -> 0 | U55: =+E55*Takstblad!E39 -> 0 | V55: =+F55*Takstblad!F39 -> 0 | W55: =+G55*Takstblad!G39 -> 0 | X55: =+H55*Takstblad!H39 -> 0 | Y55: =+I55*Takstblad!I39 -> 0 | Z55: =+J55*Takstblad!J39 -> 0 | ... AB55: =+L55*Takstblad!L39 -> 0 | AC55: =SUM(S55:AB55) -> 0 | AE55: =+M55*($C$7/12) -> 0 | AF55: =IFERROR(AC55/AE55,0) -> 0 | AH55: =+C55*($C$7/12) -> 0 | AI55: =IFERROR(S55/AH55,0) -> 0 | AK55: =+D55*($C$7/12) -> 0 | AL55: =IFERROR(T55/AK55,0) -> 0 | AN55: =+E55*($C$7/12) -> 0 | AO55: =IFERROR(U55/AN55,0) -> 0 | AQ55: =+F55*($C$7/12) -> 0 | AR55: =IFERROR(V55/AQ55,0) -> 0 | AT55: =+G55*($C$7/12) -> 0 | AU55: =IFERROR(W55/AT55,0) -> 0 | AW55: =+H55*($C$7/12) -> 0 | AX55: =IFERROR(X55/AW55,0) -> 0 | AZ55: =+I55*($C$7/12) -> 0 | BA55: =IFERROR(Y55/AZ55,0) -> 0 | BC55: =+J55*($C$7/12) -> 0 | BD55: =IFERROR(Z55/BC55,0) -> 0 | BF55: =+K55*($C$7/12) -> 0 | BG55: =IFERROR(AB55/BF55,0) -> 0 | BI55: =+L55*($C$7/12) -> 0 | BJ55: =IFERROR(AB55/BI55,0) -> 0
